Workbook

Sheet Run Comparison
A1: Run-by-Run Field Comparison — RAG & Zero Shot
A2: Compares Max Points, Estimated Level, Estimated Points, % Achieved and Justification across the 5 runs of each arm, keyed by Category + Credit ID + Credit Name. 'Consistent?' = Yes when all 5 runs match.
A4: RAG — Run-by-Run Comparison (5 runs, 47 credits)
A5: Max Points
A6: Category | B6: Credit ID | C6: Credit Name | D6: Run 1 | E6: Run 2 | F6: Run 3 | G6: Run 4 | H6: Run 5 | I6: Consistent?
A7: ='RAG Run 1'!D2 -> Climate And Resilience | B7: ='RAG Run 1'!E2 -> CR2.1 | C7: ='RAG Run 1'!F2 -> Avoid Unsuitable Development | D7: =IF('RAG Run 1'!G2="","",'RAG Run 1'!G2) -> 14 | E7: =IF('RAG Run 2'!G2="","",'RAG Run 2'!G2) -> 14 | F7: =IF('RAG Run 3'!G2="","",'RAG Run 3'!G2) -> 14 | G7: =IF('RAG Run 4'!G2="","",'RAG Run 4'!G2) -> 14 | H7: =IF('RAG Run 5'!G2="","",'RAG Run 5'!G2) -> 14 | I7: =IF(AND(D7=E7,E7=F7,F7=G7,G7=H7),"Yes","No") -> Yes
A8: ='RAG Run 1'!D3 -> Climate And Resilience | B8: ='RAG Run 1'!E3 -> CR2.2 | C8: ='RAG Run 1'!F3 -> Assess Climate Change Vulnerability | D8: =IF('RAG Run 1'!G3="","",'RAG Run 1'!G3) -> 20 | E8: =IF('RAG Run 2'!G3="","",'RAG Run 2'!G3) -> 20 | F8: =IF('RAG Run 3'!G3="","",'RAG Run 3'!G3) -> 20 | G8: =IF('RAG Run 4'!G3="","",'RAG Run 4'!G3) -> 20 | H8: =IF('RAG Run 5'!G3="","",'RAG Run 5'!G3) -> 20 | I8: =IF(AND(D8=E8,E8=F8,F8=G8,G8=H8),"Yes","No") -> Yes
A9: ='RAG Run 1'!D4 -> Climate And Resilience | B9: ='RAG Run 1'!E4 -> CR2.3 | C9: ='RAG Run 1'!F4 -> Evaluate Risk and Resilience | D9: =IF('RAG Run 1'!G4="","",'RAG Run 1'!G4) -> 26 | E9: =IF('RAG Run 2'!G4="","",'RAG Run 2'!G4) -> 26 | F9: =IF('RAG Run 3'!G4="","",'RAG Run 3'!G4) -> 26 | G9: =IF('RAG Run 4'!G4="","",'RAG Run 4'!G4) -> 26 | H9: =IF('RAG Run 5'!G4="","",'RAG Run 5'!G4) -> 26 | I9: =IF(AND(D9=E9,E9=F9,F9=G9,G9=H9),"Yes","No") -> Yes
A10: ='RAG Run 1'!D5 -> Climate And Resilience | B10: ='RAG Run 1'!E5 -> CR2.4 | C10: ='RAG Run 1'!F5 -> Establish Resilience Goals and Strategies | D10: =IF('RAG Run 1'!G5="","",'RAG Run 1'!G5) -> 20 | E10: =IF('RAG Run 2'!G5="","",'RAG Run 2'!G5) -> 20 | F10: =IF('RAG Run 3'!G5="","",'RAG Run 3'!G5) -> 20 | G10: =IF('RAG Run 4'!G5="","",'RAG Run 4'!G5) -> 20 | H10: =IF('RAG Run 5'!G5="","",'RAG Run 5'!G5) -> 20 | I10: =IF(AND(D10=E10,E10=F10,F10=G10,G10=H10),"Yes","No") -> Yes
A11: ='RAG Run 1'!D6 -> Climate And Resilience | B11: ='RAG Run 1'!E6 -> CR2.5 | C11: ='RAG Run 1'!F6 -> Maximize Resilience | D11: =IF('RAG Run 1'!G6="","",'RAG Run 1'!G6) -> 26 | E11: =IF('RAG Run 2'!G6="","",'RAG Run 2'!G6) -> 26 | F11: =IF('RAG Run 3'!G6="","",'RAG Run 3'!G6) -> 26 | G11: =IF('RAG Run 4'!G6="","",'RAG Run 4'!G6) -> 26 | H11: =IF('RAG Run 5'!G6="","",'RAG Run 5'!G6) -> 26 | I11: =IF(AND(D11=E11,E11=F11,F11=G11,G11=H11),"Yes","No") -> Yes
A12: ='RAG Run 1'!D7 -> Climate And Resilience | B12: ='RAG Run 1'!E7 -> CR2.6 | C12: ='RAG Run 1'!F7 -> Improve Infrastructure Integration | D12: =IF('RAG Run 1'!G7="","",'RAG Run 1'!G7) -> 18 | E12: =IF('RAG Run 2'!G7="","",'RAG Run 2'!G7) -> 18 | F12: =IF('RAG Run 3'!G7="","",'RAG Run 3'!G7) -> 18 | G12: =IF('RAG Run 4'!G7="","",'RAG Run 4'!G7) -> 18 | H12: =IF('RAG Run 5'!G7="","",'RAG Run 5'!G7) -> 18 | I12: =IF(AND(D12=E12,E12=F12,F12=G12,G12=H12),"Yes","No") -> Yes
A13: ='RAG Run 1'!D8 -> Leadership | B13: ='RAG Run 1'!E8 -> LD1.1 | C13: ='RAG Run 1'!F8 -> Provide Effective Leadership and Commitment | D13: =IF('RAG Run 1'!G8="","",'RAG Run 1'!G8) -> 10 | E13: =IF('RAG Run 2'!G8="","",'RAG Run 2'!G8) -> 10 | F13: =IF('RAG Run 3'!G8="","",'RAG Run 3'!G8) -> 10 | G13: =IF('RAG Run 4'!G8="","",'RAG Run 4'!G8) -> 10 | H13: =IF('RAG Run 5'!G8="","",'RAG Run 5'!G8) -> 10 | I13: =IF(AND(D13=E13,E13=F13,F13=G13,G13=H13),"Yes","No") -> Yes
A14: ='RAG Run 1'!D9 -> Leadership | B14: ='RAG Run 1'!E9 -> LD1.2 | C14: ='RAG Run 1'!F9 -> Foster Collaboration and Teamwork | D14: =IF('RAG Run 1'!G9="","",'RAG Run 1'!G9) -> 8 | E14: =IF('RAG Run 2'!G9="","",'RAG Run 2'!G9) -> 8 | F14: =IF('RAG Run 3'!G9="","",'RAG Run 3'!G9) -> 8 | G14: =IF('RAG Run 4'!G9="","",'RAG Run 4'!G9) -> 8 | H14: =IF('RAG Run 5'!G9="","",'RAG Run 5'!G9) -> 8 | I14: =IF(AND(D14=E14,E14=F14,F14=G14,G14=H14),"Yes","No") -> Yes
A15: ='RAG Run 1'!D10 -> Leadership | B15: ='RAG Run 1'!E10 -> LD1.3 | C15: ='RAG Run 1'!F10 -> Encourage Public Engagement and Participation | D15: =IF('RAG Run 1'!G10="","",'RAG Run 1'!G10) -> 8 | E15: =IF('RAG Run 2'!G10="","",'RAG Run 2'!G10) -> 8 | F15: =IF('RAG Run 3'!G10="","",'RAG Run 3'!G10) -> 8 | G15: =IF('RAG Run 4'!G10="","",'RAG Run 4'!G10) -> 8 | H15: =IF('RAG Run 5'!G10="","",'RAG Run 5'!G10) -> 8 | I15: =IF(AND(D15=E15,E15=F15,F15=G15,G15=H15),"Yes","No") -> Yes
A16: ='RAG Run 1'!D11 -> Leadership | B16: ='RAG Run 1'!E11 -> LD1.4 | C16: ='RAG Run 1'!F11 -> Pursue Byproduct Synergies | D16: =IF('RAG Run 1'!G11="","",'RAG Run 1'!G11) -> 10 | E16: =IF('RAG Run 2'!G11="","",'RAG Run 2'!G11) -> 10 | F16: =IF('RAG Run 3'!G11="","",'RAG Run 3'!G11) -> 10 | G16: =IF('RAG Run 4'!G11="","",'RAG Run 4'!G11) -> 10 | H16: =IF('RAG Run 5'!G11="","",'RAG Run 5'!G11) -> 10 | I16: =IF(AND(D16=E16,E16=F16,F16=G16,G16=H16),"Yes","No") -> Yes
A17: ='RAG Run 1'!D12 -> Leadership | B17: ='RAG Run 1'!E12 -> LD2.1 | C17: ='RAG Run 1'!F12 -> Establish a Sustainability Management Plan | D17: =IF('RAG Run 1'!G12="","",'RAG Run 1'!G12) -> 12 | E17: =IF('RAG Run 2'!G12="","",'RAG Run 2'!G12) -> 12 | F17: =IF('RAG Run 3'!G12="","",'RAG Run 3'!G12) -> 12 | G17: =IF('RAG Run 4'!G12="","",'RAG Run 4'!G12) -> 12 | H17: =IF('RAG Run 5'!G12="","",'RAG Run 5'!G12) -> 14 | I17: =IF(AND(D17=E17,E17=F17,F17=G17,G17=H17),"Yes","No") -> No
A18: ='RAG Run 1'!D13 -> Leadership | B18: ='RAG Run 1'!E13 -> LD2.2 | C18: ='RAG Run 1'!F13 -> Plan for Sustainable Communities | D18: =IF('RAG Run 1'!G13="","",'RAG Run 1'!G13) -> 10 | E18: =IF('RAG Run 2'!G13="","",'RAG Run 2'!G13) -> 10 | F18: =IF('RAG Run 3'!G13="","",'RAG Run 3'!G13) -> 10 | G18: =IF('RAG Run 4'!G13="","",'RAG Run 4'!G13) -> 10 | H18: =IF('RAG Run 5'!G13="","",'RAG Run 5'!G13) -> 12 | I18: =IF(AND(D18=E18,E18=F18,F18=G18,G18=H18),"Yes","No") -> No
... A53: ='RAG Run 1'!D48 -> Resource Allocation | B53: ='RAG Run 1'!E48 -> RA3.4 | C53: ='RAG Run 1'!F48 -> Monitor Water Systems | D53: =IF('RAG Run 1'!G48="","",'RAG Run 1'!G48) -> 8 | E53: =IF('RAG Run 2'!G48="","",'RAG Run 2'!G48) -> 8 | F53: =IF('RAG Run 3'!G48="","",'RAG Run 3'!G48) -> 8 | G53: =IF('RAG Run 4'!G48="","",'RAG Run 4'!G48) -> 6 | H53: =IF('RAG Run 5'!G48="","",'RAG Run 5'!G48) -> 8 | I53: =IF(AND(D53=E53,E53=F53,F53=G53,G53=H53),"Yes","No") -> No
A55: Estimated Level
A56: Category | B56: Credit ID | C56: Credit Name | D56: Run 1 | E56: Run 2 | F56: Run 3 | G56: Run 4 | H56: Run 5 | I56: Consistent?
A57: ='RAG Run 1'!D2 -> Climate And Resilience | B57: ='RAG Run 1'!E2 -> CR2.1 | C57: ='RAG Run 1'!F2 -> Avoid Unsuitable Development | D57: =IF('RAG Run 1'!I2="","",'RAG Run 1'!I2) -> No Level | E57: =IF('RAG Run 2'!I2="","",'RAG Run 2'!I2) -> No Level | F57: =IF('RAG Run 3'!I2="","",'RAG Run 3'!I2) -> Improved | G57: =IF('RAG Run 4'!I2="","",'RAG Run 4'!I2) -> No Level | H57: =IF('RAG Run 5'!I2="","",'RAG Run 5'!I2) -> No Level | I57: =IF(AND(D57=E57,E57=F57,F57=G57,G57=H57),"Yes","No") -> No
A58: ='RAG Run 1'!D3 -> Climate And Resilience | B58: ='RAG Run 1'!E3 -> CR2.2 | C58: ='RAG Run 1'!F3 -> Assess Climate Change Vulnerability | D58: =IF('RAG Run 1'!I3="","",'RAG Run 1'!I3) -> Improved | E58: =IF('RAG Run 2'!I3="","",'RAG Run 2'!I3) -> No Level | F58: =IF('RAG Run 3'!I3="","",'RAG Run 3'!I3) -> Improved | G58: =IF('RAG Run 4'!I3="","",'RAG Run 4'!I3) -> No Level | H58: =IF('RAG Run 5'!I3="","",'RAG Run 5'!I3) -> No Level | I58: =IF(AND(D58=E58,E58=F58,F58=G58,G58=H58),"Yes","No") -> No
A59: ='RAG Run 1'!D4 -> Climate And Resilience | B59: ='RAG Run 1'!E4 -> CR2.3 | C59: ='RAG Run 1'!F4 -> Evaluate Risk and Resilience | D59: =IF('RAG Run 1'!I4="","",'RAG Run 1'!I4) -> No Level | E59: =IF('RAG Run 2'!I4="","",'RAG Run 2'!I4) -> No Level | F59: =IF('RAG Run 3'!I4="","",'RAG Run 3'!I4) -> Improved | G59: =IF('RAG Run 4'!I4="","",'RAG Run 4'!I4) -> No Level | H59: =IF('RAG Run 5'!I4="","",'RAG Run 5'!I4) -> No Level | I59: =IF(AND(D59=E59,E59=F59,F59=G59,G59=H59),"Yes","No") -> No
A60: ='RAG Run 1'!D5 -> Climate And Resilience | B60: ='RAG Run 1'!E5 -> CR2.4 | C60: ='RAG Run 1'!F5 -> Establish Resilience Goals and Strategies | D60: =IF('RAG Run 1'!I5="","",'RAG Run 1'!I5) -> No Level | E60: =IF('RAG Run 2'!I5="","",'RAG Run 2'!I5) -> No Level | F60: =IF('RAG Run 3'!I5="","",'RAG Run 3'!I5) -> Enhanced | G60: =IF('RAG Run 4'!I5="","",'RAG Run 4'!I5) -> No Level | H60: =IF('RAG Run 5'!I5="","",'RAG Run 5'!I5) -> No Level | I60: =IF(AND(D60=E60,E60=F60,F60=G60,G60=H60),"Yes","No") -> No
A61: ='RAG Run 1'!D6 -> Climate And Resilience | B61: ='RAG Run 1'!E6 -> CR2.5 | C61: ='RAG Run 1'!F6 -> Maximize Resilience | D61: =IF('RAG Run 1'!I6="","",'RAG Run 1'!I6) -> No Level | E61: =IF('RAG Run 2'!I6="","",'RAG Run 2'!I6) -> No Level | F61: =IF('RAG Run 3'!I6="","",'RAG Run 3'!I6) -> Enhanced | G61: =IF('RAG Run 4'!I6="","",'RAG Run 4'!I6) -> No Level | H61: =IF('RAG Run 5'!I6="","",'RAG Run 5'!I6) -> No Level | I61: =IF(AND(D61=E61,E61=F61,F61=G61,G61=H61),"Yes","No") -> No
A62: ='RAG Run 1'!D7 -> Climate And Resilience | B62: ='RAG Run 1'!E7 -> CR2.6 | C62: ='RAG Run 1'!F7 -> Improve Infrastructure Integration | D62: =IF('RAG Run 1'!I7="","",'RAG Run 1'!I7) -> No Level | E62: =IF('RAG Run 2'!I7="","",'RAG Run 2'!I7) -> No Level | F62: =IF('RAG Run 3'!I7="","",'RAG Run 3'!I7) -> Improved | G62: =IF('RAG Run 4'!I7="","",'RAG Run 4'!I7) -> No Level | H62: =IF('RAG Run 5'!I7="","",'RAG Run 5'!I7) -> No Level | I62: =IF(AND(D62=E62,E62=F62,F62=G62,G62=H62),"Yes","No") -> No
A63: ='RAG Run 1'!D8 -> Leadership | B63: ='RAG Run 1'!E8 -> LD1.1 | C63: ='RAG Run 1'!F8 -> Provide Effective Leadership and Commitment | D63: =IF('RAG Run 1'!I8="","",'RAG Run 1'!I8) -> Improved | E63: =IF('RAG Run 2'!I8="","",'RAG Run 2'!I8) -> Improved | F63: =IF('RAG Run 3'!I8="","",'RAG Run 3'!I8) -> Improved | G63: =IF('RAG Run 4'!I8="","",'RAG Run 4'!I8) -> Improved | H63: =IF('RAG Run 5'!I8="","",'RAG Run 5'!I8) -> Improved | I63: =IF(AND(D63=E63,E63=F63,F63=G63,G63=H63),"Yes","No") -> Yes
A64: ='RAG Run 1'!D9 -> Leadership | B64: ='RAG Run 1'!E9 -> LD1.2 | C64: ='RAG Run 1'!F9 -> Foster Collaboration and Teamwork | D64: =IF('RAG Run 1'!I9="","",'RAG Run 1'!I9) -> Improved | E64: =IF('RAG Run 2'!I9="","",'RAG Run 2'!I9) -> Improved | F64: =IF('RAG Run 3'!I9="","",'RAG Run 3'!I9) -> Improved | G64: =IF('RAG Run 4'!I9="","",'RAG Run 4'!I9) -> Improved | H64: =IF('RAG Run 5'!I9="","",'RAG Run 5'!I9) -> Improved | I64: =IF(AND(D64=E64,E64=F64,F64=G64,G64=H64),"Yes","No") -> Yes
A65: ='RAG Run 1'!D10 -> Leadership | B65: ='RAG Run 1'!E10 -> LD1.3 | C65: ='RAG Run 1'!F10 -> Encourage Public Engagement and Participation | D65: =IF('RAG Run 1'!I10="","",'RAG Run 1'!I10) -> No Level | E65: =IF('RAG Run 2'!I10="","",'RAG Run 2'!I10) -> No Level | F65: =IF('RAG Run 3'!I10="","",'RAG Run 3'!I10) -> No Level | G65: =IF('RAG Run 4'!I10="","",'RAG Run 4'!I10) -> No Level | H65: =IF('RAG Run 5'!I10="","",'RAG Run 5'!I10) -> No Level | I65: =IF(AND(D65=E65,E65=F65,F65=G65,G65=H65),"Yes","No") -> Yes
A66: ='RAG Run 1'!D11 -> Leadership | B66: ='RAG Run 1'!E11 -> LD1.4 | C66: ='RAG Run 1'!F11 -> Pursue Byproduct Synergies | D66: =IF('RAG Run 1'!I11="","",'RAG Run 1'!I11) -> No Level | E66: =IF('RAG Run 2'!I11="","",'RAG Run 2'!I11) -> No Level | F66: =IF('RAG Run 3'!I11="","",'RAG Run 3'!I11) -> No Level | G66: =IF('RAG Run 4'!I11="","",'RAG Run 4'!I11) -> No Level | H66: =IF('RAG Run 5'!I11="","",'RAG Run 5'!I11) -> No Level | I66: =IF(AND(D66=E66,E66=F66,F66=G66,G66=H66),"Yes","No") -> Yes
A67: ='RAG Run 1'!D12 -> Leadership | B67: ='RAG Run 1'!E12 -> LD2.1 | C67: ='RAG Run 1'!F12 -> Establish a Sustainability Management Plan | D67: =IF('RAG Run 1'!I12="","",'RAG Run 1'!I12) -> No Level | E67: =IF('RAG Run 2'!I12="","",'RAG Run 2'!I12) -> No Level | F67: =IF('RAG Run 3'!I12="","",'RAG Run 3'!I12) -> No Level | G67: =IF('RAG Run 4'!I12="","",'RAG Run 4'!I12) -> No Level | H67: =IF('RAG Run 5'!I12="","",'RAG Run 5'!I12) -> No Level | I67: =IF(AND(D67=E67,E67=F67,F67=G67,G67=H67),"Yes","No") -> Yes
A68: ='RAG Run 1'!D13 -> Leadership | B68: ='RAG Run 1'!E13 -> LD2.2 | C68: ='RAG Run 1'!F13 -> Plan for Sustainable Communities | D68: =IF('RAG Run 1'!I13="","",'RAG Run 1'!I13) -> No Level | E68: =IF('RAG Run 2'!I13="","",'RAG Run 2'!I13) -> No Level | F68: =IF('RAG Run 3'!I13="","",'RAG Run 3'!I13) -> No Level | G68: =IF('RAG Run 4'!I13="","",'RAG Run 4'!I13) -> No Level | H68: =IF('RAG Run 5'!I13="","",'RAG Run 5'!I13) -> No Level | I68: =IF(AND(D68=E68,E68=F68,F68=G68,G68=H68),"Yes","No") -> Yes
... A103: ='RAG Run 1'!D48 -> Resource Allocation | B103: ='RAG Run 1'!E48 -> RA3.4 | C103: ='RAG Run 1'!F48 -> Monitor Water Systems | D103: =IF('RAG Run 1'!I48="","",'RAG Run 1'!I48) -> No Level | E103: =IF('RAG Run 2'!I48="","",'RAG Run 2'!I48) -> No Level | F103: =IF('RAG Run 3'!I48="","",'RAG Run 3'!I48) -> No Level | G103: =IF('RAG Run 4'!I48="","",'RAG Run 4'!I48) -> No Level | H103: =IF('RAG Run 5'!I48="","",'RAG Run 5'!I48) -> No Level | I103: =IF(AND(D103=E103,E103=F103,F103=G103,G103=H103),"Yes","No") -> Yes
A105: Estimated Points
A106: Category | B106: Credit ID | C106: Credit Name | D106: Run 1 | E106: Run 2 | F106: Run 3 | G106: Run 4 | H106: Run 5 | I106: Consistent?
A107: ='RAG Run 1'!D2 -> Climate And Resilience | B107: ='RAG Run 1'!E2 -> CR2.1 | C107: ='RAG Run 1'!F2 -> Avoid Unsuitable Development | D107: =IF('RAG Run 1'!J2="","",'RAG Run 1'!J2) -> 0 | E107: =IF('RAG Run 2'!J2="","",'RAG Run 2'!J2) -> 0 | F107: =IF('RAG Run 3'!J2="","",'RAG Run 3'!J2) -> 0 | G107: =IF('RAG Run 4'!J2="","",'RAG Run 4'!J2) -> 0 | H107: =IF('RAG Run 5'!J2="","",'RAG Run 5'!J2) -> 0 | I107: =IF(AND(D107=E107,E107=F107,F107=G107,G107=H107),"Yes","No") -> Yes
A108: ='RAG Run 1'!D3 -> Climate And Resilience | B108: ='RAG Run 1'!E3 -> CR2.2 | C108: ='RAG Run 1'!F3 -> Assess Climate Change Vulnerability | D108: =IF('RAG Run 1'!J3="","",'RAG Run 1'!J3) -> 8 | E108: =IF('RAG Run 2'!J3="","",'RAG Run 2'!J3) -> 0 | F108: =IF('RAG Run 3'!J3="","",'RAG Run 3'!J3) -> 0 | G108: =IF('RAG Run 4'!J3="","",'RAG Run 4'!J3) -> 0 | H108: =IF('RAG Run 5'!J3="","",'RAG Run 5'!J3) -> 0 | I108: =IF(AND(D108=E108,E108=F108,F108=G108,G108=H108),"Yes","No") -> No
A109: ='RAG Run 1'!D4 -> Climate And Resilience | B109: ='RAG Run 1'!E4 -> CR2.3 | C109: ='RAG Run 1'!F4 -> Evaluate Risk and Resilience | D109: =IF('RAG Run 1'!J4="","",'RAG Run 1'!J4) -> 0 | E109: =IF('RAG Run 2'!J4="","",'RAG Run 2'!J4) -> 0 | F109: =IF('RAG Run 3'!J4="","",'RAG Run 3'!J4) -> 0 | G109: =IF('RAG Run 4'!J4="","",'RAG Run 4'!J4) -> 0 | H109: =IF('RAG Run 5'!J4="","",'RAG Run 5'!J4) -> 0 | I109: =IF(AND(D109=E109,E109=F109,F109=G109,G109=H109),"Yes","No") -> Yes
A110: ='RAG Run 1'!D5 -> Climate And Resilience | B110: ='RAG Run 1'!E5 -> CR2.4 | C110: ='RAG Run 1'!F5 -> Establish Resilience Goals and Strategies | D110: =IF('RAG Run 1'!J5="","",'RAG Run 1'!J5) -> 0 | E110: =IF('RAG Run 2'!J5="","",'RAG Run 2'!J5) -> 0 | F110: =IF('RAG Run 3'!J5="","",'RAG Run 3'!J5) -> 0 | G110: =IF('RAG Run 4'!J5="","",'RAG Run 4'!J5) -> 0 | H110: =IF('RAG Run 5'!J5="","",'RAG Run 5'!J5) -> 0 | I110: =IF(AND(D110=E110,E110=F110,F110=G110,G110=H110),"Yes","No") -> Yes
A111: ='RAG Run 1'!D6 -> Climate And Resilience | B111: ='RAG Run 1'!E6 -> CR2.5 | C111: ='RAG Run 1'!F6 -> Maximize Resilience | D111: =IF('RAG Run 1'!J6="","",'RAG Run 1'!J6) -> 0 | E111: =IF('RAG Run 2'!J6="","",'RAG Run 2'!J6) -> 0 | F111: =IF('RAG Run 3'!J6="","",'RAG Run 3'!J6) -> 0 | G111: =IF('RAG Run 4'!J6="","",'RAG Run 4'!J6) -> 0 | H111: =IF('RAG Run 5'!J6="","",'RAG Run 5'!J6) -> 0 | I111: =IF(AND(D111=E111,E111=F111,F111=G111,G111=H111),"Yes","No") -> Yes
A112: ='RAG Run 1'!D7 -> Climate And Resilience | B112: ='RAG Run 1'!E7 -> CR2.6 | C112: ='RAG Run 1'!F7 -> Improve Infrastructure Integration | D112: =IF('RAG Run 1'!J7="","",'RAG Run 1'!J7) -> 0 | E112: =IF('RAG Run 2'!J7="","",'RAG Run 2'!J7) -> 0 | F112: =IF('RAG Run 3'!J7="","",'RAG Run 3'!J7) -> 0 | G112: =IF('RAG Run 4'!J7="","",'RAG Run 4'!J7) -> 0 | H112: =IF('RAG Run 5'!J7="","",'RAG Run 5'!J7) -> 0 | I112: =IF(AND(D112=E112,E112=F112,F112=G112,G112=H112),"Yes","No") -> Yes
A113: ='RAG Run 1'!D8 -> Leadership | B113: ='RAG Run 1'!E8 -> LD1.1 | C113: ='RAG Run 1'!F8 -> Provide Effective Leadership and Commitment | D113: =IF('RAG Run 1'!J8="","",'RAG Run 1'!J8) -> 2 | E113: =IF('RAG Run 2'!J8="","",'RAG Run 2'!J8) -> 2 | F113: =IF('RAG Run 3'!J8="","",'RAG Run 3'!J8) -> 2 | G113: =IF('RAG Run 4'!J8="","",'RAG Run 4'!J8) -> 2 | H113: =IF('RAG Run 5'!J8="","",'RAG Run 5'!J8) -> 2 | I113: =IF(AND(D113=E113,E113=F113,F113=G113,G113=H113),"Yes","No") -> Yes
A114: ='RAG Run 1'!D9 -> Leadership | B114: ='RAG Run 1'!E9 -> LD1.2 | C114: ='RAG Run 1'!F9 -> Foster Collaboration and Teamwork | D114: =IF('RAG Run 1'!J9="","",'RAG Run 1'!J9) -> 2 | E114: =IF('RAG Run 2'!J9="","",'RAG Run 2'!J9) -> 2 | F114: =IF('RAG Run 3'!J9="","",'RAG Run 3'!J9) -> 2 | G114: =IF('RAG Run 4'!J9="","",'RAG Run 4'!J9) -> 2 | H114: =IF('RAG Run 5'!J9="","",'RAG Run 5'!J9) -> 2 | I114: =IF(AND(D114=E114,E114=F114,F114=G114,G114=H114),"Yes","No") -> Yes
A115: ='RAG Run 1'!D10 -> Leadership | B115: ='RAG Run 1'!E10 -> LD1.3 | C115: ='RAG Run 1'!F10 -> Encourage Public Engagement and Participation | D115: =IF('RAG Run 1'!J10="","",'RAG Run 1'!J10) -> 0 | E115: =IF('RAG Run 2'!J10="","",'RAG Run 2'!J10) -> 0 | F115: =IF('RAG Run 3'!J10="","",'RAG Run 3'!J10) -> 0 | G115: =IF('RAG Run 4'!J10="","",'RAG Run 4'!J10) -> 0 | H115: =IF('RAG Run 5'!J10="","",'RAG Run 5'!J10) -> 0 | I115: =IF(AND(D115=E115,E115=F115,F115=G115,G115=H115),"Yes","No") -> Yes
A116: ='RAG Run 1'!D11 -> Leadership | B116: ='RAG Run 1'!E11 -> LD1.4 | C116: ='RAG Run 1'!F11 -> Pursue Byproduct Synergies | D116: =IF('RAG Run 1'!J11="","",'RAG Run 1'!J11) -> 0 | E116: =IF('RAG Run 2'!J11="","",'RAG Run 2'!J11) -> 0 | F116: =IF('RAG Run 3'!J11="","",'RAG Run 3'!J11) -> 0 | G116: =IF('RAG Run 4'!J11="","",'RAG Run 4'!J11) -> 0 | H116: =IF('RAG Run 5'!J11="","",'RAG Run 5'!J11) -> 0 | I116: =IF(AND(D116=E116,E116=F116,F116=G116,G116=H116),"Yes","No") -> Yes
A117: ='RAG Run 1'!D12 -> Leadership | B117: ='RAG Run 1'!E12 -> LD2.1 | C117: ='RAG Run 1'!F12 -> Establish a Sustainability Management Plan | D117: =IF('RAG Run 1'!J12="","",'RAG Run 1'!J12) -> 0 | E117: =IF('RAG Run 2'!J12="","",'RAG Run 2'!J12) -> 0 | F117: =IF('RAG Run 3'!J12="","",'RAG Run 3'!J12) -> 0 | G117: =IF('RAG Run 4'!J12="","",'RAG Run 4'!J12) -> 0 | H117: =IF('RAG Run 5'!J12="","",'RAG Run 5'!J12) -> 0 | I117: =IF(AND(D117=E117,E117=F117,F117=G117,G117=H117),"Yes","No") -> Yes
A118: ='RAG Run 1'!D13 -> Leadership | B118: ='RAG Run 1'!E13 -> LD2.2 | C118: ='RAG Run 1'!F13 -> Plan for Sustainable Communities | D118: =IF('RAG Run 1'!J13="","",'RAG Run 1'!J13) -> 0 | E118: =IF('RAG Run 2'!J13="","",'RAG Run 2'!J13) -> 0 | F118: =IF('RAG Run 3'!J13="","",'RAG Run 3'!J13) -> 0 | G118: =IF('RAG Run 4'!J13="","",'RAG Run 4'!J13) -> 0 | H118: =IF('RAG Run 5'!J13="","",'RAG Run 5'!J13) -> 0 | I118: =IF(AND(D118=E118,E118=F118,F118=G118,G118=H118),"Yes","No") -> Yes
... A153: ='RAG Run 1'!D48 -> Resource Allocation | B153: ='RAG Run 1'!E48 -> RA3.4 | C153: ='RAG Run 1'!F48 -> Monitor Water Systems | D153: =IF('RAG Run 1'!J48="","",'RAG Run 1'!J48) -> 0 | E153: =IF('RAG Run 2'!J48="","",'RAG Run 2'!J48) -> 0 | F153: =IF('RAG Run 3'!J48="","",'RAG Run 3'!J48) -> 0 | G153: =IF('RAG Run 4'!J48="","",'RAG Run 4'!J48) -> 0 | H153: =IF('RAG Run 5'!J48="","",'RAG Run 5'!J48) -> 0 | I153: =IF(AND(D153=E153,E153=F153,F153=G153,G153=H153),"Yes","No") -> Yes
A155: % Achieved
A156: Category | B156: Credit ID | C156: Credit Name | D156: Run 1 | E156: Run 2 | F156: Run 3 | G156: Run 4 | H156: Run 5 | I156: Consistent?
A157: ='RAG Run 1'!D2 -> Climate And Resilience | B157: ='RAG Run 1'!E2 -> CR2.1 | C157: ='RAG Run 1'!F2 -> Avoid Unsuitable Development | D157: =IF('RAG Run 1'!K2="","",'RAG Run 1'!K2) -> 0 | E157: =IF('RAG Run 2'!K2="","",'RAG Run 2'!K2) -> 0 | F157: =IF('RAG Run 3'!K2="","",'RAG Run 3'!K2) -> 0 | G157: =IF('RAG Run 4'!K2="","",'RAG Run 4'!K2) -> 0 | H157: =IF('RAG Run 5'!K2="","",'RAG Run 5'!K2) -> 0 | I157: =IF(AND(D157=E157,E157=F157,F157=G157,G157=H157),"Yes","No") -> Yes
A158: ='RAG Run 1'!D3 -> Climate And Resilience | B158: ='RAG Run 1'!E3 -> CR2.2 | C158: ='RAG Run 1'!F3 -> Assess Climate Change Vulnerability | D158: =IF('RAG Run 1'!K3="","",'RAG Run 1'!K3) -> 40 | E158: =IF('RAG Run 2'!K3="","",'RAG Run 2'!K3) -> 0 | F158: =IF('RAG Run 3'!K3="","",'RAG Run 3'!K3) -> 0 | G158: =IF('RAG Run 4'!K3="","",'RAG Run 4'!K3) -> 0 | H158: =IF('RAG Run 5'!K3="","",'RAG Run 5'!K3) -> 0 | I158: =IF(AND(D158=E158,E158=F158,F158=G158,G158=H158),"Yes","No") -> No
A159: ='RAG Run 1'!D4 -> Climate And Resilience | B159: ='RAG Run 1'!E4 -> CR2.3 | C159: ='RAG Run 1'!F4 -> Evaluate Risk and Resilience | D159: =IF('RAG Run 1'!K4="","",'RAG Run 1'!K4) -> 0 | E159: =IF('RAG Run 2'!K4="","",'RAG Run 2'!K4) -> 0 | F159: =IF('RAG Run 3'!K4="","",'RAG Run 3'!K4) -> 0 | G159: =IF('RAG Run 4'!K4="","",'RAG Run 4'!K4) -> 0 | H159: =IF('RAG Run 5'!K4="","",'RAG Run 5'!K4) -> 0 | I159: =IF(AND(D159=E159,E159=F159,F159=G159,G159=H159),"Yes","No") -> Yes
A160: ='RAG Run 1'!D5 -> Climate And Resilience | B160: ='RAG Run 1'!E5 -> CR2.4 | C160: ='RAG Run 1'!F5 -> Establish Resilience Goals and Strategies | D160: =IF('RAG Run 1'!K5="","",'RAG Run 1'!K5) -> 0 | E160: =IF('RAG Run 2'!K5="","",'RAG Run 2'!K5) -> 0 | F160: =IF('RAG Run 3'!K5="","",'RAG Run 3'!K5) -> 0 | G160: =IF('RAG Run 4'!K5="","",'RAG Run 4'!K5) -> 0 | H160: =IF('RAG Run 5'!K5="","",'RAG Run 5'!K5) -> 0 | I160: =IF(AND(D160=E160,E160=F160,F160=G160,G160=H160),"Yes","No") -> Yes
A161: ='RAG Run 1'!D6 -> Climate And Resilience | B161: ='RAG Run 1'!E6 -> CR2.5 | C161: ='RAG Run 1'!F6 -> Maximize Resilience | D161: =IF('RAG Run 1'!K6="","",'RAG Run 1'!K6) -> 0 | E161: =IF('RAG Run 2'!K6="","",'RAG Run 2'!K6) -> 0 | F161: =IF('RAG Run 3'!K6="","",'RAG Run 3'!K6) -> 0 | G161: =IF('RAG Run 4'!K6="","",'RAG Run 4'!K6) -> 0 | H161: =IF('RAG Run 5'!K6="","",'RAG Run 5'!K6) -> 0 | I161: =IF(AND(D161=E161,E161=F161,F161=G161,G161=H161),"Yes","No") -> Yes
A162: ='RAG Run 1'!D7 -> Climate And Resilience | B162: ='RAG Run 1'!E7 -> CR2.6 | C162: ='RAG Run 1'!F7 -> Improve Infrastructure Integration | D162: =IF('RAG Run 1'!K7="","",'RAG Run 1'!K7) -> 0 | E162: =IF('RAG Run 2'!K7="","",'RAG Run 2'!K7) -> 0 | F162: =IF('RAG Run 3'!K7="","",'RAG Run 3'!K7) -> 0 | G162: =IF('RAG Run 4'!K7="","",'RAG Run 4'!K7) -> 0 | H162: =IF('RAG Run 5'!K7="","",'RAG Run 5'!K7) -> 0 | I162: =IF(AND(D162=E162,E162=F162,F162=G162,G162=H162),"Yes","No") -> Yes
A163: ='RAG Run 1'!D8 -> Leadership | B163: ='RAG Run 1'!E8 -> LD1.1 | C163: ='RAG Run 1'!F8 -> Provide Effective Leadership and Commitment | D163: =IF('RAG Run 1'!K8="","",'RAG Run 1'!K8) -> 20 | E163: =IF('RAG Run 2'!K8="","",'RAG Run 2'!K8) -> 20 | F163: =IF('RAG Run 3'!K8="","",'RAG Run 3'!K8) -> 20 | G163: =IF('RAG Run 4'!K8="","",'RAG Run 4'!K8) -> 20 | H163: =IF('RAG Run 5'!K8="","",'RAG Run 5'!K8) -> 20 | I163: =IF(AND(D163=E163,E163=F163,F163=G163,G163=H163),"Yes","No") -> Yes
A164: ='RAG Run 1'!D9 -> Leadership | B164: ='RAG Run 1'!E9 -> LD1.2 | C164: ='RAG Run 1'!F9 -> Foster Collaboration and Teamwork | D164: =IF('RAG Run 1'!K9="","",'RAG Run 1'!K9) -> 25 | E164: =IF('RAG Run 2'!K9="","",'RAG Run 2'!K9) -> 25 | F164: =IF('RAG Run 3'!K9="","",'RAG Run 3'!K9) -> 25 | G164: =IF('RAG Run 4'!K9="","",'RAG Run 4'!K9) -> 25 | H164: =IF('RAG Run 5'!K9="","",'RAG Run 5'!K9) -> 25 | I164: =IF(AND(D164=E164,E164=F164,F164=G164,G164=H164),"Yes","No") -> Yes
A165: ='RAG Run 1'!D10 -> Leadership | B165: ='RAG Run 1'!E10 -> LD1.3 | C165: ='RAG Run 1'!F10 -> Encourage Public Engagement and Participation | D165: =IF('RAG Run 1'!K10="","",'RAG Run 1'!K10) -> 0 | E165: =IF('RAG Run 2'!K10="","",'RAG Run 2'!K10) -> 0 | F165: =IF('RAG Run 3'!K10="","",'RAG Run 3'!K10) -> 0 | G165: =IF('RAG Run 4'!K10="","",'RAG Run 4'!K10) -> 0 | H165: =IF('RAG Run 5'!K10="","",'RAG Run 5'!K10) -> 0 | I165: =IF(AND(D165=E165,E165=F165,F165=G165,G165=H165),"Yes","No") -> Yes
A166: ='RAG Run 1'!D11 -> Leadership | B166: ='RAG Run 1'!E11 -> LD1.4 | C166: ='RAG Run 1'!F11 -> Pursue Byproduct Synergies | D166: =IF('RAG Run 1'!K11="","",'RAG Run 1'!K11) -> 0 | E166: =IF('RAG Run 2'!K11="","",'RAG Run 2'!K11) -> 0 | F166: =IF('RAG Run 3'!K11="","",'RAG Run 3'!K11) -> 0 | G166: =IF('RAG Run 4'!K11="","",'RAG Run 4'!K11) -> 0 | H166: =IF('RAG Run 5'!K11="","",'RAG Run 5'!K11) -> 0 | I166: =IF(AND(D166=E166,E166=F166,F166=G166,G166=H166),"Yes","No") -> Yes
A167: ='RAG Run 1'!D12 -> Leadership | B167: ='RAG Run 1'!E12 -> LD2.1 | C167: ='RAG Run 1'!F12 -> Establish a Sustainability Management Plan | D167: =IF('RAG Run 1'!K12="","",'RAG Run 1'!K12) -> 0 | E167: =IF('RAG Run 2'!K12="","",'RAG Run 2'!K12) -> 0 | F167: =IF('RAG Run 3'!K12="","",'RAG Run 3'!K12) -> 0 | G167: =IF('RAG Run 4'!K12="","",'RAG Run 4'!K12) -> 0 | H167: =IF('RAG Run 5'!K12="","",'RAG Run 5'!K12) -> 0 | I167: =IF(AND(D167=E167,E167=F167,F167=G167,G167=H167),"Yes","No") -> Yes
A168: ='RAG Run 1'!D13 -> Leadership | B168: ='RAG Run 1'!E13 -> LD2.2 | C168: ='RAG Run 1'!F13 -> Plan for Sustainable Communities | D168: =IF('RAG Run 1'!K13="","",'RAG Run 1'!K13) -> 0 | E168: =IF('RAG Run 2'!K13="","",'RAG Run 2'!K13) -> 0 | F168: =IF('RAG Run 3'!K13="","",'RAG Run 3'!K13) -> 0 | G168: =IF('RAG Run 4'!K13="","",'RAG Run 4'!K13) -> 0 | H168: =IF('RAG Run 5'!K13="","",'RAG Run 5'!K13) -> 0 | I168: =IF(AND(D168=E168,E168=F168,F168=G168,G168=H168),"Yes","No") -> Yes
... A203: ='RAG Run 1'!D48 -> Resource Allocation | B203: ='RAG Run 1'!E48 -> RA3.4 | C203: ='RAG Run 1'!F48 -> Monitor Water Systems | D203: =IF('RAG Run 1'!K48="","",'RAG Run 1'!K48) -> 0 | E203: =IF('RAG Run 2'!K48="","",'RAG Run 2'!K48) -> 0 | F203: =IF('RAG Run 3'!K48="","",'RAG Run 3'!K48) -> 0 | G203: =IF('RAG Run 4'!K48="","",'RAG Run 4'!K48) -> 0 | H203: =IF('RAG Run 5'!K48="","",'RAG Run 5'!K48) -> 0 | I203: =IF(AND(D203=E203,E203=F203,F203=G203,G203=H203),"Yes","No") -> Yes
A205: Justification
A206: Category | B206: Credit ID | C206: Credit Name | D206: Run 1 | E206: Run 2 | F206: Run 3 | G206: Run 4 | H206: Run 5 | I206: Consistent?
A207: ='RAG Run 1'!D2 -> Climate And Resilience | B207: ='RAG Run 1'!E2 -> CR2.1 | C207: ='RAG Run 1'!F2 -> Avoid Unsuitable Development | D207: =IF('RAG Run 1'!L2="","",'RAG Run 1'!L2) | E207: =IF('RAG Run 2'!L2="","",'RAG Run 2'!L2) -> The project is located in Brownsville, PA, and has a significant impact on the community. It would be difficult to demonstrate that this credit is not relevant or applicable. | F207: =IF('RAG Run 3'!L2="","",'RAG Run 3'!L2) -> The project is located in Brownsville, PA, and the PDF metadata does not indicate any unsuitable development. | G207: =IF('RAG Run 4'!L2="","",'RAG Run 4'!L2) | H207: =IF('RAG Run 5'!L2="","",'RAG Run 5'!L2) -> The project is located in Brownsville, PA, and the PDF metadata does not indicate that it avoids unsuitable development. | I207: =IF(AND(D207=E207,E207=F207,F207=G207,G207=H207),"Yes","No") -> No
A208: ='RAG Run 1'!D3 -> Climate And Resilience | B208: ='RAG Run 1'!E3 -> CR2.2 | C208: ='RAG Run 1'!F3 -> Assess Climate Change Vulnerability | D208: =IF('RAG Run 1'!L3="","",'RAG Run 1'!L3) | E208: =IF('RAG Run 2'!L3="","",'RAG Run 2'!L3) -> The project is potentially impacted by climate change, and it would be difficult to demonstrate that this credit is not relevant or applicable. | F208: =IF('RAG Run 3'!L3="","",'RAG Run 3'!L3) -> The project is located in Brownsville, PA, and climate change vulnerability assessment is relevant to the project. | G208: =IF('RAG Run 4'!L3="","",'RAG Run 4'!L3) | H208: =IF('RAG Run 5'!L3="","",'RAG Run 5'!L3) -> The project is located in Brownsville, PA, and climate change vulnerability assessment is relevant to the project. | I208: =IF(AND(D208=E208,E208=F208,F208=G208,G208=H208),"Yes","No") -> No
A209: ='RAG Run 1'!D4 -> Climate And Resilience | B209: ='RAG Run 1'!E4 -> CR2.3 | C209: ='RAG Run 1'!F4 -> Evaluate Risk and Resilience | D209: =IF('RAG Run 1'!L4="","",'RAG Run 1'!L4) | E209: =IF('RAG Run 2'!L4="","",'RAG Run 2'!L4) -> The project is exposed to risks, and it would be difficult to demonstrate that this credit is not relevant or applicable. | F209: =IF('RAG Run 3'!L4="","",'RAG Run 3'!L4) -> The project is located in Brownsville, PA, and risk and resilience evaluation is relevant to the project. | G209: =IF('RAG Run 4'!L4="","",'RAG Run 4'!L4) | H209: =IF('RAG Run 5'!L4="","",'RAG Run 5'!L4) -> The project is located in Brownsville, PA, and risk and resilience evaluation is relevant to the project. | I209: =IF(AND(D209=E209,E209=F209,F209=G209,G209=H209),"Yes","No") -> No
A210: ='RAG Run 1'!D5 -> Climate And Resilience | B210: ='RAG Run 1'!E5 -> CR2.4 | C210: ='RAG Run 1'!F5 -> Establish Resilience Goals and Strategies | D210: =IF('RAG Run 1'!L5="","",'RAG Run 1'!L5) | E210: =IF('RAG Run 2'!L5="","",'RAG Run 2'!L5) -> The project is exposed to risks, and it would be difficult to demonstrate that this credit is not relevant or applicable. | F210: =IF('RAG Run 3'!L5="","",'RAG Run 3'!L5) -> The project is located in Brownsville, PA, and establishing resilience goals and strategies is relevant to the project. | G210: =IF('RAG Run 4'!L5="","",'RAG Run 4'!L5) | H210: =IF('RAG Run 5'!L5="","",'RAG Run 5'!L5) -> The project is located in Brownsville, PA, and establishing resilience goals and strategies is relevant to the project. | I210: =IF(AND(D210=E210,E210=F210,F210=G210,G210=H210),"Yes","No") -> No
A211: ='RAG Run 1'!D6 -> Climate And Resilience | B211: ='RAG Run 1'!E6 -> CR2.5 | C211: ='RAG Run 1'!F6 -> Maximize Resilience | D211: =IF('RAG Run 1'!L6="","",'RAG Run 1'!L6) | E211: =IF('RAG Run 2'!L6="","",'RAG Run 2'!L6) -> The project is exposed to risks, and it would be difficult to demonstrate that this credit is not relevant or applicable. | F211: =IF('RAG Run 3'!L6="","",'RAG Run 3'!L6) -> The project is located in Brownsville, PA, and maximizing resilience is relevant to the project. | G211: =IF('RAG Run 4'!L6="","",'RAG Run 4'!L6) | H211: =IF('RAG Run 5'!L6="","",'RAG Run 5'!L6) -> The project is located in Brownsville, PA, and maximizing resilience is relevant to the project. | I211: =IF(AND(D211=E211,E211=F211,F211=G211,G211=H211),"Yes","No") -> No
A212: ='RAG Run 1'!D7 -> Climate And Resilience | B212: ='RAG Run 1'!E7 -> CR2.6 | C212: ='RAG Run 1'!F7 -> Improve Infrastructure Integration | D212: =IF('RAG Run 1'!L7="","",'RAG Run 1'!L7) | E212: =IF('RAG Run 2'!L7="","",'RAG Run 2'!L7) -> The project is part of a larger infrastructure system, and it would be difficult to demonstrate that this credit is not relevant or applicable. | F212: =IF('RAG Run 3'!L7="","",'RAG Run 3'!L7) -> The project is located in Brownsville, PA, and improving infrastructure integration is relevant to the project. | G212: =IF('RAG Run 4'!L7="","",'RAG Run 4'!L7) | H212: =IF('RAG Run 5'!L7="","",'RAG Run 5'!L7) -> The project is located in Brownsville, PA, and improving infrastructure integration is relevant to the project. | I212: =IF(AND(D212=E212,E212=F212,F212=G212,G212=H212),"Yes","No") -> No
A213: ='RAG Run 1'!D8 -> Leadership | B213: ='RAG Run 1'!E8 -> LD1.1 | C213: ='RAG Run 1'!F8 -> Provide Effective Leadership and Commitment | D213: =IF('RAG Run 1'!L8="","",'RAG Run 1'!L8) | E213: =IF('RAG Run 2'!L8="","",'RAG Run 2'!L8) | F213: =IF('RAG Run 3'!L8="","",'RAG Run 3'!L8) | G213: =IF('RAG Run 4'!L8="","",'RAG Run 4'!L8) | H213: =IF('RAG Run 5'!L8="","",'RAG Run 5'!L8) | I213: =IF(AND(D213=E213,E213=F213,F213=G213,G213=H213),"Yes","No") -> Yes
A214: ='RAG Run 1'!D9 -> Leadership | B214: ='RAG Run 1'!E9 -> LD1.2 | C214: ='RAG Run 1'!F9 -> Foster Collaboration and Teamwork | D214: =IF('RAG Run 1'!L9="","",'RAG Run 1'!L9) | E214: =IF('RAG Run 2'!L9="","",'RAG Run 2'!L9) | F214: =IF('RAG Run 3'!L9="","",'RAG Run 3'!L9) | G214: =IF('RAG Run 4'!L9="","",'RAG Run 4'!L9) | H214: =IF('RAG Run 5'!L9="","",'RAG Run 5'!L9) | I214: =IF(AND(D214=E214,E214=F214,F214=G214,G214=H214),"Yes","No") -> Yes
A215: ='RAG Run 1'!D10 -> Leadership | B215: ='RAG Run 1'!E10 -> LD1.3 | C215: ='RAG Run 1'!F10 -> Encourage Public Engagement and Participation | D215: =IF('RAG Run 1'!L10="","",'RAG Run 1'!L10) | E215: =IF('RAG Run 2'!L10="","",'RAG Run 2'!L10) | F215: =IF('RAG Run 3'!L10="","",'RAG Run 3'!L10) | G215: =IF('RAG Run 4'!L10="","",'RAG Run 4'!L10) | H215: =IF('RAG Run 5'!L10="","",'RAG Run 5'!L10) | I215: =IF(AND(D215=E215,E215=F215,F215=G215,G215=H215),"Yes","No") -> Yes
A216: ='RAG Run 1'!D11 -> Leadership | B216: ='RAG Run 1'!E11 -> LD1.4 | C216: ='RAG Run 1'!F11 -> Pursue Byproduct Synergies | D216: =IF('RAG Run 1'!L11="","",'RAG Run 1'!L11) | E216: =IF('RAG Run 2'!L11="","",'RAG Run 2'!L11) | F216: =IF('RAG Run 3'!L11="","",'RAG Run 3'!L11) | G216: =IF('RAG Run 4'!L11="","",'RAG Run 4'!L11) | H216: =IF('RAG Run 5'!L11="","",'RAG Run 5'!L11) | I216: =IF(AND(D216=E216,E216=F216,F216=G216,G216=H216),"Yes","No") -> Yes
A217: ='RAG Run 1'!D12 -> Leadership | B217: ='RAG Run 1'!E12 -> LD2.1 | C217: ='RAG Run 1'!F12 -> Establish a Sustainability Management Plan | D217: =IF('RAG Run 1'!L12="","",'RAG Run 1'!L12) | E217: =IF('RAG Run 2'!L12="","",'RAG Run 2'!L12) | F217: =IF('RAG Run 3'!L12="","",'RAG Run 3'!L12) | G217: =IF('RAG Run 4'!L12="","",'RAG Run 4'!L12) | H217: =IF('RAG Run 5'!L12="","",'RAG Run 5'!L12) | I217: =IF(AND(D217=E217,E217=F217,F217=G217,G217=H217),"Yes","No") -> Yes
A218: ='RAG Run 1'!D13 -> Leadership | B218: ='RAG Run 1'!E13 -> LD2.2 | C218: ='RAG Run 1'!F13 -> Plan for Sustainable Communities | D218: =IF('RAG Run 1'!L13="","",'RAG Run 1'!L13) | E218: =IF('RAG Run 2'!L13="","",'RAG Run 2'!L13) | F218: =IF('RAG Run 3'!L13="","",'RAG Run 3'!L13) | G218: =IF('RAG Run 4'!L13="","",'RAG Run 4'!L13) | H218: =IF('RAG Run 5'!L13="","",'RAG Run 5'!L13) | I218: =IF(AND(D218=E218,E218=F218,F218=G218,G218=H218),"Yes","No") -> Yes
... A253: ='RAG Run 1'!D48 -> Resource Allocation | B253: ='RAG Run 1'!E48 -> RA3.4 | C253: ='RAG Run 1'!F48 -> Monitor Water Systems | D253: =IF('RAG Run 1'!L48="","",'RAG Run 1'!L48) | E253: =IF('RAG Run 2'!L48="","",'RAG Run 2'!L48) | F253: =IF('RAG Run 3'!L48="","",'RAG Run 3'!L48) | G253: =IF('RAG Run 4'!L48="","",'RAG Run 4'!L48) | H253: =IF('RAG Run 5'!L48="","",'RAG Run 5'!L48) | I253: =IF(AND(D253=E253,E253=F253,F253=G253,G253=H253),"Yes","No") -> Yes
A255: ZERO SHOT — Run-by-Run Comparison (5 runs, 35 credits)
A256: Max Points
A257: Category | B257: Credit ID | C257: Credit Name | D257: Run 1 | E257: Run 2 | F257: Run 3 | G257: Run 4 | H257: Run 5 | I257: Consistent?
A258: ='Zero Shot Run 1'!D2 -> Climate And Resilience | B258: ='Zero Shot Run 1'!E2 -> CR1.1 | C258: ='Zero Shot Run 1'!F2 -> Reduce Net Embodied Carbon | D258: =IF('Zero Shot Run 1'!G2="","",'Zero Shot Run 1'!G2) | E258: =IF('Zero Shot Run 2'!G2="","",'Zero Shot Run 2'!G2) | F258: =IF('Zero Shot Run 3'!G2="","",'Zero Shot Run 3'!G2) | G258: =IF('Zero Shot Run 4'!G2="","",'Zero Shot Run 4'!G2) | H258: =IF('Zero Shot Run 5'!G2="","",'Zero Shot Run 5'!G2) | I258: =IF(AND(D258=E258,E258=F258,F258=G258,G258=H258),"Yes","No") -> Yes
A259: ='Zero Shot Run 1'!D3 -> Climate And Resilience | B259: ='Zero Shot Run 1'!E3 -> CR1.2 | C259: ='Zero Shot Run 1'!F3 -> Reduce Greenhouse Gas Emissions | D259: =IF('Zero Shot Run 1'!G3="","",'Zero Shot Run 1'!G3) | E259: =IF('Zero Shot Run 2'!G3="","",'Zero Shot Run 2'!G3) | F259: =IF('Zero Shot Run 3'!G3="","",'Zero Shot Run 3'!G3) | G259: =IF('Zero Shot Run 4'!G3="","",'Zero Shot Run 4'!G3) | H259: =IF('Zero Shot Run 5'!G3="","",'Zero Shot Run 5'!G3) | I259: =IF(AND(D259=E259,E259=F259,F259=G259,G259=H259),"Yes","No") -> Yes
A260: ='Zero Shot Run 1'!D4 -> Climate And Resilience | B260: ='Zero Shot Run 1'!E4 -> CR1.3 | C260: ='Zero Shot Run 1'!F4 -> Reduce Air Pollutant Emissions | D260: =IF('Zero Shot Run 1'!G4="","",'Zero Shot Run 1'!G4) | E260: =IF('Zero Shot Run 2'!G4="","",'Zero Shot Run 2'!G4) | F260: =IF('Zero Shot Run 3'!G4="","",'Zero Shot Run 3'!G4) | G260: =IF('Zero Shot Run 4'!G4="","",'Zero Shot Run 4'!G4) | H260: =IF('Zero Shot Run 5'!G4="","",'Zero Shot Run 5'!G4) | I260: =IF(AND(D260=E260,E260=F260,F260=G260,G260=H260),"Yes","No") -> Yes
A261: ='Zero Shot Run 1'!D5 -> Climate And Resilience | B261: ='Zero Shot Run 1'!E5 -> CR2.1 | C261: ='Zero Shot Run 1'!F5 -> Avoid Unsuitable Development | D261: =IF('Zero Shot Run 1'!G5="","",'Zero Shot Run 1'!G5) | E261: =IF('Zero Shot Run 2'!G5="","",'Zero Shot Run 2'!G5) | F261: =IF('Zero Shot Run 3'!G5="","",'Zero Shot Run 3'!G5) | G261: =IF('Zero Shot Run 4'!G5="","",'Zero Shot Run 4'!G5) | H261: =IF('Zero Shot Run 5'!G5="","",'Zero Shot Run 5'!G5) | I261: =IF(AND(D261=E261,E261=F261,F261=G261,G261=H261),"Yes","No") -> Yes
A262: ='Zero Shot Run 1'!D6 -> Climate And Resilience | B262: ='Zero Shot Run 1'!E6 -> CR2.2 | C262: ='Zero Shot Run 1'!F6 -> Assess Climate Change Vulnerability | D262: =IF('Zero Shot Run 1'!G6="","",'Zero Shot Run 1'!G6) | E262: =IF('Zero Shot Run 2'!G6="","",'Zero Shot Run 2'!G6) | F262: =IF('Zero Shot Run 3'!G6="","",'Zero Shot Run 3'!G6) | G262: =IF('Zero Shot Run 4'!G6="","",'Zero Shot Run 4'!G6) | H262: =IF('Zero Shot Run 5'!G6="","",'Zero Shot Run 5'!G6) | I262: =IF(AND(D262=E262,E262=F262,F262=G262,G262=H262),"Yes","No") -> Yes
A263: ='Zero Shot Run 1'!D7 -> Climate And Resilience | B263: ='Zero Shot Run 1'!E7 -> CR2.3 | C263: ='Zero Shot Run 1'!F7 -> Evaluate Risk and Resilience | D263: =IF('Zero Shot Run 1'!G7="","",'Zero Shot Run 1'!G7) | E263: =IF('Zero Shot Run 2'!G7="","",'Zero Shot Run 2'!G7) | F263: =IF('Zero Shot Run 3'!G7="","",'Zero Shot Run 3'!G7) | G263: =IF('Zero Shot Run 4'!G7="","",'Zero Shot Run 4'!G7) | H263: =IF('Zero Shot Run 5'!G7="","",'Zero Shot Run 5'!G7) | I263: =IF(AND(D263=E263,E263=F263,F263=G263,G263=H263),"Yes","No") -> Yes
A264: ='Zero Shot Run 1'!D8 -> Climate And Resilience | B264: ='Zero Shot Run 1'!E8 -> CR2.4 | C264: ='Zero Shot Run 1'!F8 -> Establish Resilience Goals and Strategies | D264: =IF('Zero Shot Run 1'!G8="","",'Zero Shot Run 1'!G8) | E264: =IF('Zero Shot Run 2'!G8="","",'Zero Shot Run 2'!G8) | F264: =IF('Zero Shot Run 3'!G8="","",'Zero Shot Run 3'!G8) | G264: =IF('Zero Shot Run 4'!G8="","",'Zero Shot Run 4'!G8) | H264: =IF('Zero Shot Run 5'!G8="","",'Zero Shot Run 5'!G8) | I264: =IF(AND(D264=E264,E264=F264,F264=G264,G264=H264),"Yes","No") -> Yes
A265: ='Zero Shot Run 1'!D9 -> Climate And Resilience | B265: ='Zero Shot Run 1'!E9 -> CR2.5 | C265: ='Zero Shot Run 1'!F9 -> Maximize Resilience | D265: =IF('Zero Shot Run 1'!G9="","",'Zero Shot Run 1'!G9) | E265: =IF('Zero Shot Run 2'!G9="","",'Zero Shot Run 2'!G9) | F265: =IF('Zero Shot Run 3'!G9="","",'Zero Shot Run 3'!G9) | G265: =IF('Zero Shot Run 4'!G9="","",'Zero Shot Run 4'!G9) | H265: =IF('Zero Shot Run 5'!G9="","",'Zero Shot Run 5'!G9) | I265: =IF(AND(D265=E265,E265=F265,F265=G265,G265=H265),"Yes","No") -> Yes
A266: ='Zero Shot Run 1'!D10 -> Climate And Resilience | B266: ='Zero Shot Run 1'!E10 -> CR2.6 | C266: ='Zero Shot Run 1'!F10 -> Improve Infrastructure Integration | D266: =IF('Zero Shot Run 1'!G10="","",'Zero Shot Run 1'!G10) | E266: =IF('Zero Shot Run 2'!G10="","",'Zero Shot Run 2'!G10) | F266: =IF('Zero Shot Run 3'!G10="","",'Zero Shot Run 3'!G10) | G266: =IF('Zero Shot Run 4'!G10="","",'Zero Shot Run 4'!G10) | H266: =IF('Zero Shot Run 5'!G10="","",'Zero Shot Run 5'!G10) | I266: =IF(AND(D266=E266,E266=F266,F266=G266,G266=H266),"Yes","No") -> Yes
A267: ='Zero Shot Run 1'!D11 -> Leadership | B267: ='Zero Shot Run 1'!E11 -> LD1.1 | C267: ='Zero Shot Run 1'!F11 -> Provide Effective Leadership and Commitment | D267: =IF('Zero Shot Run 1'!G11="","",'Zero Shot Run 1'!G11) | E267: =IF('Zero Shot Run 2'!G11="","",'Zero Shot Run 2'!G11) | F267: =IF('Zero Shot Run 3'!G11="","",'Zero Shot Run 3'!G11) | G267: =IF('Zero Shot Run 4'!G11="","",'Zero Shot Run 4'!G11) | H267: =IF('Zero Shot Run 5'!G11="","",'Zero Shot Run 5'!G11) | I267: =IF(AND(D267=E267,E267=F267,F267=G267,G267=H267),"Yes","No") -> Yes
A268: ='Zero Shot Run 1'!D12 -> Leadership | B268: ='Zero Shot Run 1'!E12 -> LD1.2 | C268: ='Zero Shot Run 1'!F12 -> Foster Collaboration and Teamwork | D268: =IF('Zero Shot Run 1'!G12="","",'Zero Shot Run 1'!G12) | E268: =IF('Zero Shot Run 2'!G12="","",'Zero Shot Run 2'!G12) | F268: =IF('Zero Shot Run 3'!G12="","",'Zero Shot Run 3'!G12) | G268: =IF('Zero Shot Run 4'!G12="","",'Zero Shot Run 4'!G12) | H268: =IF('Zero Shot Run 5'!G12="","",'Zero Shot Run 5'!G12) | I268: =IF(AND(D268=E268,E268=F268,F268=G268,G268=H268),"Yes","No") -> Yes
A269: ='Zero Shot Run 1'!D13 -> Leadership | B269: ='Zero Shot Run 1'!E13 -> LD1.3 | C269: ='Zero Shot Run 1'!F13 -> Provide for Stakeholder Involvement | D269: =IF('Zero Shot Run 1'!G13="","",'Zero Shot Run 1'!G13) | E269: =IF('Zero Shot Run 2'!G13="","",'Zero Shot Run 2'!G13) | F269: =IF('Zero Shot Run 3'!G13="","",'Zero Shot Run 3'!G13) | G269: =IF('Zero Shot Run 4'!G13="","",'Zero Shot Run 4'!G13) | H269: =IF('Zero Shot Run 5'!G13="","",'Zero Shot Run 5'!G13) | I269: =IF(AND(D269=E269,E269=F269,F269=G269,G269=H269),"Yes","No") -> Yes
... A292: ='Zero Shot Run 1'!D36 -> Resource Allocation | B292: ='Zero Shot Run 1'!E36 -> RA3.4 | C292: ='Zero Shot Run 1'!F36 -> Monitor Water Systems | D292: =IF('Zero Shot Run 1'!G36="","",'Zero Shot Run 1'!G36) | E292: =IF('Zero Shot Run 2'!G36="","",'Zero Shot Run 2'!G36) | F292: =IF('Zero Shot Run 3'!G36="","",'Zero Shot Run 3'!G36) | G292: =IF('Zero Shot Run 4'!G36="","",'Zero Shot Run 4'!G36) | H292: =IF('Zero Shot Run 5'!G36="","",'Zero Shot Run 5'!G36) | I292: =IF(AND(D292=E292,E292=F292,F292=G292,G292=H292),"Yes","No") -> Yes
A294: Estimated Level
A295: Category | B295: Credit ID | C295: Credit Name | D295: Run 1 | E295: Run 2 | F295: Run 3 | G295: Run 4 | H295: Run 5 | I295: Consistent?
A296: ='Zero Shot Run 1'!D2 -> Climate And Resilience | B296: ='Zero Shot Run 1'!E2 -> CR1.1 | C296: ='Zero Shot Run 1'!F2 -> Reduce Net Embodied Carbon | D296: =IF('Zero Shot Run 1'!I2="","",'Zero Shot Run 1'!I2) -> No Level | E296: =IF('Zero Shot Run 2'!I2="","",'Zero Shot Run 2'!I2) -> No Level | F296: =IF('Zero Shot Run 3'!I2="","",'Zero Shot Run 3'!I2) -> No Level | G296: =IF('Zero Shot Run 4'!I2="","",'Zero Shot Run 4'!I2) -> No Level | H296: =IF('Zero Shot Run 5'!I2="","",'Zero Shot Run 5'!I2) -> No Level | I296: =IF(AND(D296=E296,E296=F296,F296=G296,G296=H296),"Yes","No") -> Yes
A297: ='Zero Shot Run 1'!D3 -> Climate And Resilience | B297: ='Zero Shot Run 1'!E3 -> CR1.2 | C297: ='Zero Shot Run 1'!F3 -> Reduce Greenhouse Gas Emissions | D297: =IF('Zero Shot Run 1'!I3="","",'Zero Shot Run 1'!I3) -> No Level | E297: =IF('Zero Shot Run 2'!I3="","",'Zero Shot Run 2'!I3) -> No Level | F297: =IF('Zero Shot Run 3'!I3="","",'Zero Shot Run 3'!I3) -> No Level | G297: =IF('Zero Shot Run 4'!I3="","",'Zero Shot Run 4'!I3) -> No Level | H297: =IF('Zero Shot Run 5'!I3="","",'Zero Shot Run 5'!I3) -> No Level | I297: =IF(AND(D297=E297,E297=F297,F297=G297,G297=H297),"Yes","No") -> Yes
A298: ='Zero Shot Run 1'!D4 -> Climate And Resilience | B298: ='Zero Shot Run 1'!E4 -> CR1.3 | C298: ='Zero Shot Run 1'!F4 -> Reduce Air Pollutant Emissions | D298: =IF('Zero Shot Run 1'!I4="","",'Zero Shot Run 1'!I4) -> No Level | E298: =IF('Zero Shot Run 2'!I4="","",'Zero Shot Run 2'!I4) -> No Level | F298: =IF('Zero Shot Run 3'!I4="","",'Zero Shot Run 3'!I4) -> No Level | G298: =IF('Zero Shot Run 4'!I4="","",'Zero Shot Run 4'!I4) -> No Level | H298: =IF('Zero Shot Run 5'!I4="","",'Zero Shot Run 5'!I4) -> No Level | I298: =IF(AND(D298=E298,E298=F298,F298=G298,G298=H298),"Yes","No") -> Yes
A299: ='Zero Shot Run 1'!D5 -> Climate And Resilience | B299: ='Zero Shot Run 1'!E5 -> CR2.1 | C299: ='Zero Shot Run 1'!F5 -> Avoid Unsuitable Development | D299: =IF('Zero Shot Run 1'!I5="","",'Zero Shot Run 1'!I5) -> No Level | E299: =IF('Zero Shot Run 2'!I5="","",'Zero Shot Run 2'!I5) -> No Level | F299: =IF('Zero Shot Run 3'!I5="","",'Zero Shot Run 3'!I5) -> No Level | G299: =IF('Zero Shot Run 4'!I5="","",'Zero Shot Run 4'!I5) -> No Level | H299: =IF('Zero Shot Run 5'!I5="","",'Zero Shot Run 5'!I5) -> No Level | I299: =IF(AND(D299=E299,E299=F299,F299=G299,G299=H299),"Yes","No") -> Yes
...

Sheet RAG Run 1
A1: Arm | B1: Run | C1: File | D1: Category | E1: Credit ID | F1: Credit Name | G1: Max Points | H1: Applicability | I1: Estimated Level | J1: Estimated Points | K1: % Achieved | L1: Justification | M1: Questions Summary | N1: Level Guide Reference | O1: Concept Phase Actions | P1: Documentation Needed | Q1: Input Tokens | R1: Output Tokens | S1: Elapsed (s) | T1: Valid JSON | U1: Truncated | V1: Success
A2: rag | B2: 1 | C2: 00_sample_project | D2: Climate And Resilience | E2: CR2.1 | F2: Avoid Unsuitable Development | G2: 14 | H2: Applicable | I2: No Level | J2: 0 | K2: 0 | M2: QA:Insufficient Data(No information on site selection process) | QB:Insufficient Data(No environmental impact assessment available) | N2: A + B required for Improved | O2: Conduct site selection process with environmental considerations; Perform environmental impact assessment | P2: Site selection report; Environmental impact assessment | Q2: 17617 | R2: 1284 | S2: 366.91 | T2: TRUE | U2: FALSE | V2: TRUE
A3: rag | B3: 1 | C3: 00_sample_project | D3: Climate And Resilience | E3: CR2.2 | F3: Assess Climate Change Vulnerability | G3: 20 | H3: Applicable | I3: Improved | J3: 8 | K3: 40 | M3: QA:Likely Yes(Project location in Brownsville, PA, suggests potential climate change impacts) | QB:Insufficient Data(No vulnerability assessment available) | N3: A + B required for Improved | O3: Conduct climate change vulnerability assessment | P3: Climate change vulnerability assessment report | Q3: 17617 | R3: 1284 | S3: 366.91 | T3: TRUE | U3: FALSE | V3: TRUE
A4: rag | B4: 1 | C4: 00_sample_project | D4: Climate And Resilience | E4: CR2.3 | F4: Evaluate Risk and Resilience | G4: 26 | H4: Applicable | I4: No Level | J4: 0 | K4: 0 | M4: QA:Insufficient Data(No risk assessment available) | QB:Insufficient Data(No identification of critical functions and dependencies) | N4: A + B + C + D + E required for Conserving | O4: Conduct risk assessment; Identify critical functions and dependencies | P4: Risk assessment report; Critical functions and dependencies identification document | Q4: 17617 | R4: 1284 | S4: 366.91 | T4: TRUE | U4: FALSE | V4: TRUE
A5: rag | B5: 1 | C5: 00_sample_project | D5: Climate And Resilience | E5: CR2.4 | F5: Establish Resilience Goals and Strategies | G5: 20 | H5: Applicable | I5: No Level | J5: 0 | K5: 0 | M5: QA:Insufficient Data(No project performance goals available) | QB:Insufficient Data(No risk management strategies developed) | N5: A + B required for Enhanced | O5: Develop project performance goals; Establish risk management strategies | P5: Project performance goals document; Risk management strategies report | Q5: 17617 | R5: 1284 | S5: 366.91 | T5: TRUE | U5: FALSE | V5: TRUE
A6: rag | B6: 1 | C6: 00_sample_project | D6: Climate And Resilience | E6: CR2.5 | F6: Maximize Resilience | G6: 26 | H6: Applicable | I6: No Level | J6: 0 | K6: 0 | M6: QA:Insufficient Data(No resilience goals and strategies developed) | QB:Insufficient Data(No implementation of resilience strategies) | N6: A + B + C + D + E required for Conserving | O6: Develop resilience goals and strategies; Implement resilience strategies | P6: Resilience goals and strategies document; Resilience strategies implementation report | Q6: 17617 | R6: 1284 | S6: 366.91 | T6: TRUE | U6: FALSE | V6: TRUE
A7: rag | B7: 1 | C7: 00_sample_project | D7: Climate And Resilience | E7: CR2.6 | F7: Improve Infrastructure Integration | G7: 18 | H7: Applicable | I7: No Level | J7: 0 | K7: 0 | M7: QA:Insufficient Data(No consideration of infrastructure integration) | QB:Insufficient Data(No evaluation of systems performance) | N7: A + B required for Improved | O7: Consider infrastructure integration; Evaluate systems performance | P7: Infrastructure integration report; Systems performance evaluation document | Q7: 17617 | R7: 1284 | S7: 366.91 | T7: TRUE | U7: FALSE | V7: TRUE
A8: rag | B8: 1 | C8: 00_sample_project | D8: Leadership | E8: LD1.1 | F8: Provide Effective Leadership and Commitment | G8: 10 | H8: Applicable | I8: Improved | J8: 2 | K8: 20 | M8: QA:Likely Yes(Project team includes multiple stakeholders (Cartesian Inverse, PA; Etienne Oise) | QB:Insufficient Data(No information on sustainability goals or targets) | N8: A + B required for Enhanced | O8: Develop sustainability goals and targets | P8: Sustainability management plan; Stakeholder engagement records | Q8: 17191 | R8: 1953 | S8: 542.38 | T8: TRUE | U8: FALSE | V8: TRUE
A9: rag | B9: 1 | C9: 00_sample_project | D9: Leadership | E9: LD1.2 | F9: Foster Collaboration and Teamwork | G9: 8 | H9: Applicable | I9: Improved | J9: 2 | K9: 25 | M9: QA:Likely Yes(Multiple stakeholders involved in project team (Cartesian Inverse, PA; Etienne O) | QB:Insufficient Data(No information on collaboration tools or processes) | N9: A + B required for Enhanced | O9: Establish collaboration tools and processes | P9: Collaboration plan; Meeting minutes | Q9: 17191 | R9: 1953 | S9: 542.38 | T9: TRUE | U9: FALSE | V9: TRUE
A10: rag | B10: 1 | C10: 00_sample_project | D10: Leadership | E10: LD1.3 | F10: Encourage Public Engagement and Participation | G10: 8 | H10: Applicable | I10: No Level | J10: 0 | K10: 0 | M10: QA:Insufficient Data(No information on public engagement or participation) | QB:Insufficient Data(No information on community outreach or education) | N10: A + B required for Improved | O10: Develop public engagement and participation plan | P10: Public engagement plan; Community outreach records | Q10: 17191 | R10: 1953 | S10: 542.38 | T10: TRUE | U10: FALSE | V10: TRUE
A11: rag | B11: 1 | C11: 00_sample_project | D11: Leadership | E11: LD1.4 | F11: Pursue Byproduct Synergies | G11: 10 | H11: Applicable | I11: No Level | J11: 0 | K11: 0 | M11: QA:Insufficient Data(No information on byproduct synergies) | QB:Insufficient Data(No information on waste reduction or material reuse) | N11: A + B required for Improved | O11: Investigate byproduct synergies and waste reduction opportunities | P11: Byproduct synergy plan; Waste reduction strategy | Q11: 17191 | R11: 1953 | S11: 542.38 | T11: TRUE | U11: FALSE | V11: TRUE
A12: rag | B12: 1 | C12: 00_sample_project | D12: Leadership | E12: LD2.1 | F12: Establish a Sustainability Management Plan | G12: 12 | H12: Applicable | I12: No Level | J12: 0 | K12: 0 | M12: QA:Insufficient Data(No information on sustainability management plan) | QB:Insufficient Data(No information on monitoring and reporting processes) | N12: A + B required for Improved | O12: Develop sustainability management plan | P12: Sustainability management plan; Monitoring and reporting records | Q12: 17191 | R12: 1953 | S12: 542.38 | T12: TRUE | U12: FALSE | V12: TRUE
A13: rag | B13: 1 | C13: 00_sample_project | D13: Leadership | E13: LD2.2 | F13: Plan for Sustainable Communities | G13: 10 | H13: Applicable | I13: No Level | J13: 0 | K13: 0 | M13: QA:Insufficient Data(No information on community planning or development) | QB:Insufficient Data(No information on social and economic benefits) | N13: A + B required for Improved | O13: Develop community planning and development strategy | P13: Community plan; Social and economic benefit analysis | Q13: 17191 | R13: 1953 | S13: 542.38 | T13: TRUE | U13: FALSE | V13: TRUE
... A17: rag | B17: 1 | C17: 00_sample_project | D17: Leadership | E17: LD3.3 | F17: Conduct a Life-Cycle Assessment | G17: 12 | H17: Applicable | I17: No Level | J17: 0 | K17: 0 | M17: QA:Insufficient Data(No information on life-cycle assessment) | QB:Insufficient Data(No information on environmental impacts or benefits) | N17: A + B required for Improved | O17: Conduct life-cycle assessment | P17: Life-cycle assessment report; Environmental impact analysis | Q17: 17191 | R17: 1953 | S17: 542.38 | T17: TRUE | U17: FALSE | V17: TRUE
A18: rag | B18: 1 | C18: 00_sample_project | D18: Natural World | E18: NW1.1 | F18: Conserve Natural Areas | G18: 14 | H18: APPLICABLE | I18: No Level | J18: 0 | K18: 0 | L18: The project is located in an area with potential natural habitats and ecosystems, making conservation of natural areas relevant. | M18: QA:Insufficient Data(No information on natural habitat preservation) | QB:Insufficient Data(No data on native plant species used in landscaping) | N18: A + B required for Improved | O18: Conduct site assessment to identify natural habitats; Research local native plant species for landscaping | P18: Site assessment report; Native plant species list | Q18: 17916 | R18: 1349 | S18: 405.26 | T18: TRUE | U18: FALSE | V18: TRUE
A19: rag | B19: 1 | C19: 00_sample_project | D19: Natural World | E19: NW1.2 | F19: Provide Wetland and Surface Water Buffers | G19: 10 | H19: APPLICABLE | I19: No Level | J19: 0 | K19: 0 | L19: The project's location near water bodies makes wetland and surface water buffers relevant. | M19: QA:Insufficient Data(No information on wetland or surface water buffer zones) | QB:Insufficient Data(No data on buffer zone maintenance plans) | N19: A + B required for Improved | O19: Conduct wetland and surface water assessment; Develop buffer zone maintenance plan | P19: Wetland and surface water assessment report; Buffer zone maintenance plan | Q19: 17916 | R19: 1349 | S19: 405.26 | T19: TRUE | U19: FALSE | V19: TRUE
A20: rag | B20: 1 | C20: 00_sample_project | D20: Natural World | E20: NW2.2 | F20: Manage Stormwater | G20: 24 | H20: APPLICABLE | I20: No Level | J20: 0 | K20: 0 | L20: The project's potential impact on stormwater runoff makes management relevant. | M20: QA:Insufficient Data(No information on stormwater management strategies) | QB:Insufficient Data(No data on stormwater runoff reduction targets) | N20: A + B required for Improved | O20: Develop stormwater management plan; Set stormwater runoff reduction targets | P20: Stormwater management plan; Runoff reduction target documentation | Q20: 17916 | R20: 1349 | S20: 405.26 | T20: TRUE | U20: FALSE | V20: TRUE
A21: rag | B21: 1 | C21: 00_sample_project | D21: Natural World | E21: NW2.4 | F21: Protect Surface and Groundwater Quality | G21: 14 | H21: APPLICABLE | I21: No Level | J21: 0 | K21: 0 | L21: The project's potential impact on surface and groundwater quality makes protection relevant. | M21: QA:Insufficient Data(No information on surface and groundwater protection measures) | QB:Insufficient Data(No data on water quality monitoring plans) | N21: A + B required for Improved | O21: Develop surface and groundwater protection plan; Establish water quality monitoring program | P21: Surface and groundwater protection plan; Water quality monitoring plan | Q21: 17916 | R21: 1349 | S21: 405.26 | T21: TRUE | U21: FALSE | V21: TRUE
A22: rag | B22: 1 | C22: 00_sample_project | D22: Natural World | E22: NW3.3 | F22: Maintain Floodplain Functions | G22: 14 | H22: APPLICABLE | I22: No Level | J22: 0 | K22: 0 | L22: The project's location in a floodplain makes maintaining floodplain functions relevant. | M22: QA:Insufficient Data(No information on floodplain function preservation) | QB:Insufficient Data(No data on vegetated zone preservation) | N22: A + B required for Improved | O22: Conduct floodplain function assessment; Develop plan to preserve vegetated zones | P22: Floodplain function assessment report; Vegetated zone preservation plan | Q22: 17916 | R22: 1349 | S22: 405.26 | T22: TRUE | U22: FALSE | V22: TRUE
A23: rag | B23: 1 | C23: 00_sample_project | D23: Natural World | E23: NW3.5 | F23: Protect Soil Health | G23: 10 | H23: APPLICABLE | I23: No Level | J23: 0 | K23: 0 | L23: The project's potential impact on soil health makes protection relevant. | M23: QA:Insufficient Data(No information on soil health protection measures) | QB:Insufficient Data(No data on soil erosion control plans) | N23: A + B required for Improved | O23: Develop soil health protection plan; Establish soil erosion control measures | P23: Soil health protection plan; Soil erosion control plan | Q23: 17916 | R23: 1349 | S23: 405.26 | T23: TRUE | U23: FALSE | V23: TRUE
A24: rag | B24: 1 | C24: 00_sample_project | D24: Quality Of Life | E24: QL1.1 | F24: Improve Community Quality of Life | G24: 26 | H24: Applicable | I24: Improved | J24: 2 | K24: 7.7 | L24: The project is a mixed-use development with residential, commercial, and community spaces, indicating potential for community quality of life improvements. | M24: QA:Likely Yes(Project includes live/work units and community spaces.) | QB:Insufficient Data(Lack of information on community engagement and feedback mechanisms.) | N24: A + B required for Enhanced | O24: Engage with local stakeholders to understand community needs and priorities. | P24: Community engagement records; Stakeholder feedback mechanisms | Q24: 17220 | R24: 2486 | S24: 844.38 | T24: TRUE | U24: FALSE | V24: TRUE
A25: rag | B25: 1 | C25: 00_sample_project | D25: Quality Of Life | E25: QL1.2 | F25: Enhance Public Health & Safety | G25: 20 | H25: Applicable | I25: Improved | J25: 2 | K25: 10 | L25: The project includes residential and commercial spaces, which can impact public health and safety. | M25: QA:Likely Yes(Project includes fire resistive walls and smoke barriers.) | QB:Insufficient Data(Lack of information on emergency response planning and evacuation procedures.) | N25: A + B required for Enhanced | O25: Develop emergency response plan and evacuation procedures. | P25: Emergency response plan; Evacuation procedure documents | Q25: 17220 | R25: 2486 | S25: 844.38 | T25: TRUE | U25: FALSE | V25: TRUE
A26: rag | B26: 1 | C26: 00_sample_project | D26: Quality Of Life | E26: QL1.3 | F26: Improve Construction Safety | G26: 14 | H26: Applicable | I26: Improved | J26: 2 | K26: 14.3 | L26: The project involves construction activities that can impact worker safety. | M26: QA:Likely Yes(Project includes safety protocols for workers.) | QB:Insufficient Data(Lack of information on worker training programs and site-specific hazard assessm) | N26: A + B required for Enhanced | O26: Develop worker training programs and conduct site-specific hazard assessments. | P26: Worker training records; Site-specific hazard assessment reports | Q26: 17220 | R26: 2486 | S26: 844.38 | T26: TRUE | U26: FALSE | V26: TRUE
A27: rag | B27: 1 | C27: 00_sample_project | D27: Quality Of Life | E27: QL1.4 | F27: Minimize Noise & Vibration | G27: 12 | H27: Applicable | I27: Improved | J27: 1 | K27: 8.3 | L27: The project includes residential and commercial spaces that can be impacted by noise and vibration. | M27: QA:Likely Yes(Project includes soundproofing measures.) | QB:Insufficient Data(Lack of information on vibration mitigation strategies.) | N27: A + B required for Enhanced | O27: Investigate vibration mitigation strategies and implement soundproofing measures. | P27: Soundproofing design documents; Vibration mitigation strategy reports | Q27: 17220 | R27: 2486 | S27: 844.38 | T27: TRUE | U27: FALSE | V27: TRUE
A28: rag | B28: 1 | C28: 00_sample_project | D28: Quality Of Life | E28: QL1.5 | F28: Minimize Light Pollution | G28: 12 | H28: Applicable | I28: Improved | J28: 1 | K28: 8.3 | L28: The project includes exterior lighting that can contribute to light pollution. | M28: QA:Likely Yes(Project includes energy-efficient lighting.) | QB:Insufficient Data(Lack of information on lighting design and controls.) | N28: A + B required for Enhanced | O28: Develop lighting design and control strategies to minimize light pollution. | P28: Lighting design documents; Control strategy reports | Q28: 17220 | R28: 2486 | S28: 844.38 | T28: TRUE | U28: FALSE | V28: TRUE
A29: rag | B29: 1 | C29: 00_sample_project | D29: Quality Of Life | E29: QL1.6 | F29: Minimize Construction Impacts | G29: 8 | H29: Applicable | I29: Improved | J29: 1 | K29: 12.5 | L29: The project involves construction activities that can impact the surrounding environment. | M29: QA:Likely Yes(Project includes waste management plan.) | QB:Insufficient Data(Lack of information on construction sequencing and scheduling.) | N29: A + B required for Enhanced | O29: Develop construction sequencing and scheduling strategies to minimize impacts. | P29: Construction sequencing documents; Scheduling reports | Q29: 17220 | R29: 2486 | S29: 844.38 | T29: TRUE | U29: FALSE | V29: TRUE
... A33: rag | B33: 1 | C33: 00_sample_project | D33: Quality Of Life | E33: QL3.1 | F33: Advance Equity & Social Justice | G33: 18 | H33: Applicable | I33: Improved | J33: 3 | K33: 16.7 | L33: The project includes community spaces that can impact equity and social justice. | M33: QA:Likely Yes(Project includes community engagement and outreach.) | QB:Insufficient Data(Lack of information on inclusive design principles and social impact assessments) | N33: A + B required for Enhanced | O33: Investigate inclusive design principles and social impact assessments. | P33: Inclusive design principle reports; Social impact assessment documents | Q33: 17220 | R33: 2486 | S33: 844.38 | T33: TRUE | U33: FALSE | V33: TRUE
A34: rag | B34: 1 | C34: 00_sample_project | D34: Quality Of Life | E34: QL3.2 | F34: Preserve Historic & Cultural Resources | G34: 18 | H34: Not Applicable | J34: 0 | K34: 0 | L34: The project does not involve historic or cultural resources. | Q34: 17220 | R34: 2486 | S34: 844.38 | T34: TRUE | U34: FALSE | V34: TRUE
A35: rag | B35: 1 | C35: 00_sample_project | D35: Quality Of Life | E35: QL3.3 | F35: Enhance Views & Local Character | G35: 14 | H35: Applicable | I35: Improved | J35: 1 | K35: 7.1 | L35: The project includes public spaces that can impact views and local character. | M35: QA:Likely Yes(Project includes design elements that enhance local character.) | QB:Insufficient Data(Lack of information on view preservation and enhancement strategies.) | N35: A + B required for Enhanced | O35: Investigate view preservation and enhancement strategies. | P35: View preservation reports; Enhancement strategy documents | Q35: 17220 | R35: 2486 | S35: 844.38 | T35: TRUE | U35: FALSE | V35: TRUE
A36: rag | B36: 1 | C36: 00_sample_project | D36: Resource Allocation | E36: RA1.1 | F36: Reduce Materials Use | G36: 12 | H36: Applicable | I36: No Level | J36: 0 | K36: 0 | M36: QA:Insufficient Data(No material takeoff or bill of quantities in the model) | QB:Insufficient Data(No information on recycled content or sustainable materials) | N36: A + B required for Improved | O36: Develop a material takeoff and bill of quantities; Research sustainable materials and recycled content options | P36: Material takeoff and bill of quantities; Sustainable materials and recycled content research | Q36: 17210 | R36: 2640 | S36: 929.49 | T36: TRUE | U36: FALSE | V36: TRUE
A37: rag | B37: 1 | C37: 00_sample_project | D37: Resource Allocation | E37: RA1.2 | F37: Use Recycled Materials | G37: 10 | H37: Applicable | I37: No Level | J37: 0 | K37: 0 | M37: QA:Insufficient Data(No information on recycled materials used in the project) | QB:Insufficient Data(No documentation of recycled material quantities) | N37: A + B required for Improved | O37: Research recycled material options; Develop a plan for incorporating recycled materials into the project | P37: Recycled material research; Plan for incorporating recycled materials | Q37: 17210 | R37: 2640 | S37: 929.49 | T37: TRUE | U37: FALSE | V37: TRUE
A38: rag | B38: 1 | C38: 00_sample_project | D38: Resource Allocation | E38: RA1.3 | F38: Reduce Operational Waste | G38: 8 | H38: Applicable | I38: No Level | J38: 0 | K38: 0 | M38: QA:Insufficient Data(No information on operational waste reduction strategies) | QB:Insufficient Data(No documentation of waste reduction goals or targets) | N38: A + B required for Improved | O38: Develop a plan for reducing operational waste; Research waste reduction strategies and technologies | P38: Operational waste reduction plan; Waste reduction goals or targets | Q38: 17210 | R38: 2640 | S38: 929.49 | T38: TRUE | U38: FALSE | V38: TRUE
A39: rag | B39: 1 | C39: 00_sample_project | D39: Resource Allocation | E39: RA1.4 | F39: Reduce Construction Waste | G39: 10 | H39: Applicable | I39: No Level | J39: 0 | K39: 0 | M39: QA:Insufficient Data(No information on construction waste reduction strategies) | QB:Insufficient Data(No documentation of waste reduction goals or targets) | N39: A + B required for Improved | O39: Develop a plan for reducing construction waste; Research waste reduction strategies and technologies | P39: Construction waste reduction plan; Waste reduction goals or targets | Q39: 17210 | R39: 2640 | S39: 929.49 | T39: TRUE | U39: FALSE | V39: TRUE
A40: rag | B40: 1 | C40: 00_sample_project | D40: Resource Allocation | E40: RA1.5 | F40: Balance Earthwork On Site | G40: 6 | H40: Applicable | I40: No Level | J40: 0 | K40: 0 | M40: QA:Insufficient Data(No information on earthwork balancing strategies) | QB:Insufficient Data(No documentation of earthwork balancing goals or targets) | N40: A + B required for Improved | O40: Develop a plan for balancing earthwork on site; Research earthwork balancing strategies and technologies | P40: Earthwork balancing plan; Earthwork balancing goals or targets | Q40: 17210 | R40: 2640 | S40: 929.49 | T40: TRUE | U40: FALSE | V40: TRUE
A41: rag | B41: 1 | C41: 00_sample_project | D41: Resource Allocation | E41: RA2.1 | F41: Reduce Operational Energy Consumption | G41: 20 | H41: Applicable | I41: No Level | J41: 0 | K41: 0 | M41: QA:Insufficient Data(No information on operational energy consumption reduction strategies) | QB:Insufficient Data(No documentation of energy reduction goals or targets) | N41: A + B required for Improved | O41: Develop a plan for reducing operational energy consumption; Research energy reduction strategies and technologies | P41: Operational energy reduction plan; Energy reduction goals or targets | Q41: 17210 | R41: 2640 | S41: 929.49 | T41: TRUE | U41: FALSE | V41: TRUE
A42: rag | B42: 1 | C42: 00_sample_project | D42: Resource Allocation | E42: RA2.2 | F42: Reduce Construction Energy Consumption | G42: 12 | H42: Applicable | I42: No Level | J42: 0 | K42: 0 | M42: QA:Insufficient Data(No information on construction energy consumption reduction strategies) | QB:Insufficient Data(No documentation of energy reduction goals or targets) | N42: A + B required for Improved | O42: Develop a plan for reducing construction energy consumption; Research energy reduction strategies and technologies | P42: Construction energy reduction plan; Energy reduction goals or targets | Q42: 17210 | R42: 2640 | S42: 929.49 | T42: TRUE | U42: FALSE | V42: TRUE
A43: rag | B43: 1 | C43: 00_sample_project | D43: Resource Allocation | E43: RA2.3 | F43: Use Renewable Energy | G43: 10 | H43: Applicable | I43: No Level | J43: 0 | K43: 0 | M43: QA:Insufficient Data(No information on renewable energy sources) | QB:Insufficient Data(No documentation of renewable energy goals or targets) | N43: A + B required for Improved | O43: Research renewable energy sources; Develop a plan for incorporating renewable energy into the project | P43: Renewable energy research; Plan for incorporating renewable energy | Q43: 17210 | R43: 2640 | S43: 929.49 | T43: TRUE | U43: FALSE | V43: TRUE
A44: rag | B44: 1 | C44: 00_sample_project | D44: Resource Allocation | E44: RA2.4 | F44: Commission and Monitor Energy Systems | G44: 8 | H44: Applicable | I44: No Level | J44: 0 | K44: 0 | M44: QA:Insufficient Data(No information on energy system commissioning or monitoring) | QB:Insufficient Data(No documentation of energy system performance goals or targets) | N44: A + B required for Improved | O44: Develop a plan for commissioning and monitoring energy systems; Research energy system performance metrics | P44: Energy system commissioning and monitoring plan; Energy system performance goals or targets | Q44: 17210 | R44: 2640 | S44: 929.49 | T44: TRUE | U44: FALSE | V44: TRUE
A45: rag | B45: 1 | C45: 00_sample_project | D45: Resource Allocation | E45: RA3.1 | F45: Preserve Water Resources | G45: 14 | H45: Applicable | I45: No Level | J45: 0 | K45: 0 | M45: QA:Insufficient Data(No information on water conservation strategies) | QB:Insufficient Data(No documentation of water reduction goals or targets) | N45: A + B required for Improved | O45: Develop a plan for preserving water resources; Research water conservation strategies and technologies | P45: Water preservation plan; Water reduction goals or targets | Q45: 17210 | R45: 2640 | S45: 929.49 | T45: TRUE | U45: FALSE | V45: TRUE
A46: rag | B46: 1 | C46: 00_sample_project | D46: Resource Allocation | E46: RA3.2 | F46: Reduce Operational Water Consumption | G46: 12 | H46: Applicable | I46: No Level | J46: 0 | K46: 0 | M46: QA:Insufficient Data(No information on operational water consumption reduction strategies) | QB:Insufficient Data(No documentation of water reduction goals or targets) | N46: A + B required for Improved | O46: Develop a plan for reducing operational water consumption; Research water reduction strategies and technologies | P46: Operational water reduction plan; Water reduction goals or targets | Q46: 17210 | R46: 2640 | S46: 929.49 | T46: TRUE | U46: FALSE | V46: TRUE
A47: rag | B47: 1 | C47: 00_sample_project | D47: Resource Allocation | E47: RA3.3 | F47: Reduce Construction Water Consumption | G47: 10 | H47: Applicable | I47: No Level | J47: 0 | K47: 0 | M47: QA:Insufficient Data(No information on construction water consumption reduction strategies) | QB:Insufficient Data(No documentation of water reduction goals or targets) | N47: A + B required for Improved | O47: Develop a plan for reducing construction water consumption; Research water reduction strategies and technologies | P47: Construction water reduction plan; Water reduction goals or targets | Q47: 17210 | R47: 2640 | S47: 929.49 | T47: TRUE | U47: FALSE | V47: TRUE
A48: rag | B48: 1 | C48: 00_sample_project | D48: Resource Allocation | E48: RA3.4 | F48: Monitor Water Systems | G48: 8 | H48: Applicable | I48: No Level | J48: 0 | K48: 0 | M48: QA:Insufficient Data(No information on water system monitoring) | QB:Insufficient Data(No documentation of water system performance goals or targets) | N48: A + B required for Improved | O48: Develop a plan for monitoring water systems; Research water system performance metrics | P48: Water system monitoring plan; Water system performance goals or targets | Q48: 17210 | R48: 2640 | S48: 929.49 | T48: TRUE | U48: FALSE | V48: TRUE

Sheet RAG Run 2
A1: Arm | B1: Run | C1: File | D1: Category | E1: Credit ID | F1: Credit Name | G1: Max Points | H1: Applicability | I1: Estimated Level | J1: Estimated Points | K1: % Achieved | L1: Justification | M1: Questions Summary | N1: Level Guide Reference | O1: Concept Phase Actions | P1: Documentation Needed | Q1: Input Tokens | R1: Output Tokens | S1: Elapsed (s) | T1: Valid JSON | U1: Truncated | V1: Success
A2: rag | B2: 2 | C2: 00_sample_project | D2: Climate And Resilience | E2: CR2.1 | F2: Avoid Unsuitable Development | G2: 14 | H2: APPLICABLE | I2: No Level | J2: 0 | K2: 0 | L2: The project is located in Brownsville, PA, and has a significant impact on the community. It would be difficult to demonstrate that this credit is not relevant or applicable. | M2: QA:Insufficient Data(No information on site selection process) | QB:Insufficient Data(No information on environmental impact assessment) | N2: A + B required for Improved | O2: Conduct site selection process; Perform environmental impact assessment | P2: Site selection report; Environmental impact assessment report | Q2: 17617 | R2: 1700 | S2: 610.15 | T2: TRUE | U2: FALSE | V2: TRUE
A3: rag | B3: 2 | C3: 00_sample_project | D3: Climate And Resilience | E3: CR2.2 | F3: Assess Climate Change Vulnerability | G3: 20 | H3: APPLICABLE | I3: No Level | J3: 0 | K3: 0 | L3: The project is potentially impacted by climate change, and it would be difficult to demonstrate that this credit is not relevant or applicable. | M3: QA:Insufficient Data(No information on climate change threats) | QB:Insufficient Data(No information on project vulnerability) | QC:Insufficient Data(No information on infrastructure system vulnerability) | QD:Insufficient Data(No information on community vulnerability) | QE:Insufficient Data(No information on sharing climate threat findings) | N3: A + B required for Improved | O3: Conduct climate change vulnerability assessment; Identify project and infrastructure system vulnerabilities | P3: Climate change vulnerability assessment report; Project and infrastructure system vulnerability reports | Q3: 17617 | R3: 1700 | S3: 610.15 | T3: TRUE | U3: FALSE | V3: TRUE
A4: rag | B4: 2 | C4: 00_sample_project | D4: Climate And Resilience | E4: CR2.3 | F4: Evaluate Risk and Resilience | G4: 26 | H4: APPLICABLE | I4: No Level | J4: 0 | K4: 0 | L4: The project is exposed to risks, and it would be difficult to demonstrate that this credit is not relevant or applicable. | M4: QA:Insufficient Data(No information on risk assessment) | QB:Insufficient Data(No information on critical functions and dependencies) | QC:Insufficient Data(No information on threats or hazards) | QD:Insufficient Data(No information on vulnerabilities of critical functions and dependencies) | QE:Insufficient Data(No information on risk evaluation) | QF:Insufficient Data(No information on stakeholder participation in risk evaluation) | N4: A + B + C + D + E required for Improved | O4: Conduct risk assessment; Identify critical functions and dependencies; Evaluate risks | P4: Risk assessment report; Critical functions and dependencies report; Risk evaluation report | Q4: 17617 | R4: 1700 | S4: 610.15 | T4: TRUE | U4: FALSE | V4: TRUE
A5: rag | B5: 2 | C5: 00_sample_project | D5: Climate And Resilience | E5: CR2.4 | F5: Establish Resilience Goals and Strategies | G5: 20 | H5: APPLICABLE | I5: No Level | J5: 0 | K5: 0 | L5: The project is exposed to risks, and it would be difficult to demonstrate that this credit is not relevant or applicable. | M5: QA:Insufficient Data(No information on project performance goals and risk appetite) | QB:Insufficient Data(No information on risk management strategies) | QC:Insufficient Data(No information on stakeholder engagement in developing resilience goals) | QD:Insufficient Data(No information on community resilience or climate change adaptation goals) | N5: A + B required for Enhanced | O5: Establish project performance goals and risk appetite; Develop risk management strategies | P5: Project performance goals and risk appetite report; Risk management strategies report | Q5: 17617 | R5: 1700 | S5: 610.15 | T5: TRUE | U5: FALSE | V5: TRUE
A6: rag | B6: 2 | C6: 00_sample_project | D6: Climate And Resilience | E6: CR2.5 | F6: Maximize Resilience | G6: 26 | H6: APPLICABLE | I6: No Level | J6: 0 | K6: 0 | L6: The project is exposed to risks, and it would be difficult to demonstrate that this credit is not relevant or applicable. | M6: QA:Insufficient Data(No information on resilience goals and strategies) | QB:Insufficient Data(No information on implementation of resilience strategies) | QC:Insufficient Data(No information on monitoring and review of resilience strategies) | QD:Insufficient Data(No information on incorporation of resilience goals and strategies into operatio) | QE:Insufficient Data(No information on methods for measuring or quantifying resilience performance ta) | N6: A + B required for Improved | O6: Develop resilience goals and strategies; Implement resilience strategies | P6: Resilience goals and strategies report; Implementation of resilience strategies report | Q6: 17617 | R6: 1700 | S6: 610.15 | T6: TRUE | U6: FALSE | V6: TRUE
A7: rag | B7: 2 | C7: 00_sample_project | D7: Climate And Resilience | E7: CR2.6 | F7: Improve Infrastructure Integration | G7: 18 | H7: APPLICABLE | I7: No Level | J7: 0 | K7: 0 | L7: The project is part of a larger infrastructure system, and it would be difficult to demonstrate that this credit is not relevant or applicable. | M7: QA:Insufficient Data(No information on infrastructure integration) | N7: A required for Improved | O7: Improve infrastructure integration | P7: Infrastructure integration report | Q7: 17617 | R7: 1700 | S7: 610.15 | T7: TRUE | U7: FALSE | V7: TRUE
A8: rag | B8: 2 | C8: 00_sample_project | D8: Leadership | E8: LD1.1 | F8: Provide Effective Leadership and Commitment | G8: 10 | H8: Applicable | I8: Improved | J8: 2 | K8: 20 | M8: QA:Likely Yes(Project team includes multiple stakeholders (Cartesian Inverse, PA; Etienne Oise) | QB:Insufficient Data(No information on sustainability goals or targets) | N8: A + B required for Enhanced | O8: Develop sustainability goals and targets | P8: Sustainability management plan; Stakeholder engagement records | Q8: 17191 | R8: 1954 | S8: 693.75 | T8: TRUE | U8: FALSE | V8: TRUE
A9: rag | B9: 2 | C9: 00_sample_project | D9: Leadership | E9: LD1.2 | F9: Foster Collaboration and Teamwork | G9: 8 | H9: Applicable | I9: Improved | J9: 2 | K9: 25 | M9: QA:Likely Yes(Multiple stakeholders involved in project team (Cartesian Inverse, PA; Etienne O) | QB:Insufficient Data(No information on collaboration tools or processes) | N9: A + B required for Enhanced | O9: Establish collaboration tools and processes | P9: Collaboration plan; Meeting minutes | Q9: 17191 | R9: 1954 | S9: 693.75 | T9: TRUE | U9: FALSE | V9: TRUE
A10: rag | B10: 2 | C10: 00_sample_project | D10: Leadership | E10: LD1.3 | F10: Encourage Public Engagement and Participation | G10: 8 | H10: Applicable | I10: No Level | J10: 0 | K10: 0 | M10: QA:Insufficient Data(No information on public engagement or participation) | QB:Insufficient Data(No information on community outreach or education) | N10: A + B required for Improved | O10: Develop public engagement and participation plan | P10: Public engagement plan; Community outreach records | Q10: 17191 | R10: 1954 | S10: 693.75 | T10: TRUE | U10: FALSE | V10: TRUE
A11: rag | B11: 2 | C11: 00_sample_project | D11: Leadership | E11: LD1.4 | F11: Pursue Byproduct Synergies | G11: 10 | H11: Applicable | I11: No Level | J11: 0 | K11: 0 | M11: QA:Insufficient Data(No information on byproduct synergies) | QB:Insufficient Data(No information on waste reduction or material reuse) | N11: A + B required for Improved | O11: Investigate byproduct synergies and waste reduction opportunities | P11: Byproduct synergy plan; Waste reduction strategy | Q11: 17191 | R11: 1954 | S11: 693.75 | T11: TRUE | U11: FALSE | V11: TRUE
A12: rag | B12: 2 | C12: 00_sample_project | D12: Leadership | E12: LD2.1 | F12: Establish a Sustainability Management Plan | G12: 12 | H12: Applicable | I12: No Level | J12: 0 | K12: 0 | M12: QA:Insufficient Data(No information on sustainability management plan) | QB:Insufficient Data(No information on monitoring and reporting processes) | N12: A + B required for Improved | O12: Develop sustainability management plan | P12: Sustainability management plan; Monitoring and reporting records | Q12: 17191 | R12: 1954 | S12: 693.75 | T12: TRUE | U12: FALSE | V12: TRUE
A13: rag | B13: 2 | C13: 00_sample_project | D13: Leadership | E13: LD2.2 | F13: Plan for Sustainable Communities | G13: 10 | H13: Applicable | I13: No Level | J13: 0 | K13: 0 | M13: QA:Insufficient Data(No information on community planning or development) | QB:Insufficient Data(No information on social and economic benefits) | N13: A + B required for Improved | O13: Develop community planning and development strategy | P13: Community plan; Social and economic impact assessment | Q13: 17191 | R13: 1954 | S13: 693.75 | T13: TRUE | U13: FALSE | V13: TRUE
A14: rag | B14: 2 | C14: 00_sample_project | D14: Leadership | E14: LD2.3 | F14: Conduct a Life-Cycle Economic Evaluation | G14: 12 | H14: Applicable | I14: No Level | J14: 0 | K14: 0 | M14: QA:Insufficient Data(No information on life-cycle economic evaluation) | QB:Insufficient Data(No information on cost-benefit analysis or return on investment) | N14: A + B required for Improved | O14: Conduct life-cycle economic evaluation | P14: Life-cycle economic evaluation report; Cost-benefit analysis | Q14: 17191 | R14: 1954 | S14: 693.75 | T14: TRUE | U14: FALSE | V14: TRUE
A15: rag | B15: 2 | C15: 00_sample_project | D15: Leadership | E15: LD3.1 | F15: Encourage Sustainable Procurement Practices | G15: 10 | H15: Applicable | I15: No Level | J15: 0 | K15: 0 | M15: QA:Insufficient Data(No information on sustainable procurement practices) | QB:Insufficient Data(No information on environmentally responsible purchasing) | N15: A + B required for Improved | O15: Develop sustainable procurement plan | P15: Sustainable procurement plan; Environmentally responsible purchasing records | Q15: 17191 | R15: 1954 | S15: 693.75 | T15: TRUE | U15: FALSE | V15: TRUE
A16: rag | B16: 2 | C16: 00_sample_project | D16: Leadership | E16: LD3.2 | F16: Support Local and Regional Economies | G16: 8 | H16: Applicable | I16: No Level | J16: 0 | K16: 0 | M16: QA:Insufficient Data(No information on local or regional economic benefits) | QB:Insufficient Data(No information on community development or job creation) | N16: A + B required for Improved | O16: Develop local and regional economic development strategy | P16: Local and regional economic development plan; Community development records | Q16: 17191 | R16: 1954 | S16: 693.75 | T16: TRUE | U16: FALSE | V16: TRUE
A17: rag | B17: 2 | C17: 00_sample_project | D17: Leadership | E17: LD3.3 | F17: Conduct a Life-Cycle Assessment | G17: 12 | H17: Applicable | I17: No Level | J17: 0 | K17: 0 | M17: QA:Insufficient Data(No information on life-cycle assessment) | QB:Insufficient Data(No information on environmental impacts or resource usage) | N17: A + B required for Improved | O17: Conduct life-cycle assessment | P17: Life-cycle assessment report; Environmental impact statement | Q17: 17191 | R17: 1954 | S17: 693.75 | T17: TRUE | U17: FALSE | V17: TRUE
A18: rag | B18: 2 | C18: 00_sample_project | D18: Natural World | E18: NW1.1 | F18: Conserve Natural Areas | G18: 14 | H18: APPLICABLE | I18: Improved | J18: 2 | K18: 14.3 | L18: The project is located in Brownsville, PA, and has a site plan, indicating potential natural areas to conserve. | M18: QA:Insufficient Data(No information on natural area conservation) | QB:Insufficient Data(No information on habitat preservation) | N18: A + B required for Improved | O18: Conduct site analysis to identify natural areas; Develop conservation plan | P18: Site analysis report; Conservation plan | Q18: 17916 | R18: 1325 | S18: 506.66 | T18: TRUE | U18: FALSE | V18: TRUE
A19: rag | B19: 2 | C19: 00_sample_project | D19: Natural World | E19: NW1.2 | F19: Provide Wetland and Surface Water Buffers | G19: 10 | H19: APPLICABLE | I19: Improved | J19: 2 | K19: 20 | L19: The project has a site plan, indicating potential wetlands or surface water to buffer. | M19: QA:Insufficient Data(No information on wetland or surface water buffers) | QB:Insufficient Data(No information on buffer zone size) | N19: A + B required for Improved | O19: Conduct site analysis to identify wetlands or surface water; Develop buffer zone plan | P19: Site analysis report; Buffer zone plan | Q19: 17916 | R19: 1325 | S19: 506.66 | T19: TRUE | U19: FALSE | V19: TRUE
A20: rag | B20: 2 | C20: 00_sample_project | D20: Natural World | E20: NW2.2 | F20: Manage Stormwater | G20: 24 | H20: APPLICABLE | I20: Improved | J20: 2 | K20: 8.3 | L20: The project has a site plan, indicating potential stormwater management needs. | M20: QA:Insufficient Data(No information on stormwater management) | QB:Insufficient Data(No information on rate or quantity of runoff) | N20: A + B required for Improved | O20: Conduct stormwater analysis; Develop stormwater management plan | P20: Stormwater analysis report; Stormwater management plan | Q20: 17916 | R20: 1325 | S20: 506.66 | T20: TRUE | U20: FALSE | V20: TRUE
A21: rag | B21: 2 | C21: 00_sample_project | D21: Natural World | E21: NW2.4 | F21: Protect Surface and Groundwater Quality | G21: 14 | H21: APPLICABLE | I21: Improved | J21: 1 | K21: 7.1 | L21: The project has a site plan, indicating potential surface or groundwater quality concerns. | M21: QA:Insufficient Data(No information on surface or groundwater quality protection) | QB:Insufficient Data(No information on pollution prevention measures) | N21: A + B required for Improved | O21: Conduct water quality analysis; Develop pollution prevention plan | P21: Water quality analysis report; Pollution prevention plan | Q21: 17916 | R21: 1325 | S21: 506.66 | T21: TRUE | U21: FALSE | V21: TRUE
A22: rag | B22: 2 | C22: 00_sample_project | D22: Natural World | E22: NW3.3 | F22: Maintain Floodplain Functions | G22: 14 | H22: APPLICABLE | I22: Improved | J22: 1 | K22: 7.1 | L22: The project is located in Brownsville, PA, and has a site plan, indicating potential floodplain functions to maintain. | M22: QA:Insufficient Data(No information on floodplain functions) | QB:Insufficient Data(No information on vegetated zones preservation) | N22: A + B required for Improved | O22: Conduct floodplain analysis; Develop floodplain management plan | P22: Floodplain analysis report; Floodplain management plan | Q22: 17916 | R22: 1325 | S22: 506.66 | T22: TRUE | U22: FALSE | V22: TRUE
A23: rag | B23: 2 | C23: 00_sample_project | D23: Natural World | E23: NW3.5 | F23: Protect Soil Health | G23: 10 | H23: APPLICABLE | I23: Improved | J23: 2 | K23: 20 | L23: The project has a site plan, indicating potential soil health concerns. | M23: QA:Insufficient Data(No information on soil health protection) | QB:Insufficient Data(No information on erosion control measures) | N23: A + B required for Improved | O23: Conduct soil analysis; Develop erosion control plan | P23: Soil analysis report; Erosion control plan | Q23: 17916 | R23: 1325 | S23: 506.66 | T23: TRUE | U23: FALSE | V23: TRUE
A24: rag | B24: 2 | C24: 00_sample_project | D24: Quality Of Life | E24: QL1.1 | F24: Improve Community Quality of Life | G24: 26 | H24: Applicable | I24: Improved | J24: 5 | K24: 19.2 | L24: The project is a mixed-use development with residential, commercial, and community spaces, indicating potential for community quality of life improvements. | M24: QA:Likely Yes(Project includes live/work units and community spaces.) | QB:Insufficient Data(Lack of information on community engagement and feedback mechanisms.) | QC:Likely Yes(Project incorporates green spaces and outdoor areas.) | QD:Insufficient Data(Lack of information on accessibility features and universal design principles.) | N24: A + B | O24: Conduct community outreach and engagement to inform design decisions.; Incorporate accessible and universal design principles into the project. | P24: Community engagement records; Accessibility features and universal design principles documentation | Q24: 17220 | R24: 2964 | S24: 1069.15 | T24: TRUE | U24: FALSE | V24: TRUE
A25: rag | B25: 2 | C25: 00_sample_project | D25: Quality Of Life | E25: QL1.2 | F25: Enhance Public Health & Safety | G25: 20 | H25: Applicable | I25: Improved | J25: 7 | K25: 35 | L25: The project includes residential and commercial spaces, indicating potential public health and safety concerns. | M25: QA:Likely Yes(Project incorporates natural ventilation and daylighting strategies.) | QB:Insufficient Data(Lack of information on indoor air quality monitoring and maintenance protocols.) | QC:Likely Yes(Project includes emergency response plan and fire suppression systems.) | N25: A + B | O25: Develop indoor air quality monitoring and maintenance protocols.; Incorporate public health and safety considerations into the project's emergency response plan. | P25: Indoor air quality monitoring and maintenance protocols; Public health and safety considerations documentation | Q25: 17220 | R25: 2964 | S25: 1069.15 | T25: TRUE | U25: FALSE | V25: TRUE
A26: rag | B26: 2 | C26: 00_sample_project | D26: Quality Of Life | E26: QL1.3 | F26: Improve Construction Safety | G26: 14 | H26: Applicable | I26: Improved | J26: 5 | K26: 35.7 | L26: The project involves construction activities, indicating potential construction safety concerns. | M26: QA:Likely Yes(Project includes construction safety plan and training programs.) | QB:Insufficient Data(Lack of information on site-specific hazard assessments and mitigation strategie) | N26: A + B | O26: Conduct site-specific hazard assessments and develop mitigation strategies.; Incorporate construction safety considerations into the project's overall safety plan. | P26: Construction safety plan and training programs documentation; Site-specific hazard assessments and mitigation strategies documentation | Q26: 17220 | R26: 2964 | S26: 1069.15 | T26: TRUE | U26: FALSE | V26: TRUE
A27: rag | B27: 2 | C27: 00_sample_project | D27: Quality Of Life | E27: QL1.4 | F27: Minimize Noise & Vibration | G27: 12 | H27: Applicable | I27: Improved | J27: 3 | K27: 25 | L27: The project includes residential and commercial spaces, indicating potential noise and vibration concerns. | M27: QA:Likely Yes(Project incorporates sound-absorbing materials and acoustic design strategies.) | QB:Insufficient Data(Lack of information on vibration mitigation measures and monitoring protocols.) | N27: A + B | O27: Develop vibration mitigation measures and monitoring protocols.; Incorporate noise and vibration considerations into the project's overall design. | P27: Sound-absorbing materials and acoustic design strategies documentation; Vibration mitigation measures and monitoring protocols documentation | Q27: 17220 | R27: 2964 | S27: 1069.15 | T27: TRUE | U27: FALSE | V27: TRUE
A28: rag | B28: 2 | C28: 00_sample_project | D28: Quality Of Life | E28: QL1.5 | F28: Minimize Light Pollution | G28: 12 | H28: Applicable | I28: Improved | J28: 3 | K28: 25 | L28: The project includes exterior lighting, indicating potential light pollution concerns. | M28: QA:Likely Yes(Project incorporates energy-efficient and shielded lighting fixtures.) | QB:Insufficient Data(Lack of information on lighting controls and scheduling protocols.) | N28: A + B | O28: Develop lighting controls and scheduling protocols.; Incorporate light pollution considerations into the project's overall design. | P28: Energy-efficient and shielded lighting fixtures documentation; Lighting controls and scheduling protocols documentation | Q28: 17220 | R28: 2964 | S28: 1069.15 | T28: TRUE | U28: FALSE | V28: TRUE
A29: rag | B29: 2 | C29: 00_sample_project | D29: Quality Of Life | E29: QL1.6 | F29: Minimize Construction Impacts | G29: 8 | H29: Applicable | I29: Improved | J29: 2 | K29: 25 | L29: The project involves construction activities, indicating potential construction impacts. | M29: QA:Likely Yes(Project includes construction waste management plan and recycling programs.) | QB:Insufficient Data(Lack of information on site-specific construction impact assessments and mitigat) | N29: A + B | O29: Conduct site-specific construction impact assessments and develop mitigation strategies.; Incorporate construction impact considerations into the project's overall plan. | P29: Construction waste management plan and recycling programs documentation; Site-specific construction impact assessments and mitigation strategies documentation | Q29: 17220 | R29: 2964 | S29: 1069.15 | T29: TRUE | U29: FALSE | V29: TRUE
... A35: rag | B35: 2 | C35: 00_sample_project | D35: Quality Of Life | E35: QL3.3 | F35: Enhance Views & Local Character | G35: 14 | H35: Applicable | I35: Improved | J35: 3 | K35: 21.4 | L35: The project includes residential and commercial spaces, indicating potential view and local character concerns. | M35: QA:Likely Yes(Project incorporates view preservation strategies and local character considerat) | QB:Insufficient Data(Lack of information on streetscape design and public art integration.) | N35: A + B | O35: Develop streetscape design and public art integration strategies.; Incorporate view and local character considerations into the project's overall design. | P35: View preservation strategies and local character considerations documentation; Streetscape design and public art integration documentation | Q35: 17220 | R35: 2964 | S35: 1069.15 | T35: TRUE | U35: FALSE | V35: TRUE
A36: rag | B36: 2 | C36: 00_sample_project | D36: Resource Allocation | E36: RA1.1 | F36: Reduce Materials Use | G36: 12 | H36: Applicable | I36: No Level | J36: 0 | K36: 0 | M36: QA:Insufficient Data(No material takeoff or bill of quantities in the model) | QB:Insufficient Data(No information on recycled content or sustainable materials) | N36: A + B required for Improved | O36: Develop a material takeoff and bill of quantities; Research sustainable materials and recycled content options | P36: Material takeoff and bill of quantities; Sustainable materials and recycled content research | Q36: 17210 | R36: 2644 | S36: 930.85 | T36: TRUE | U36: FALSE | V36: TRUE
A37: rag | B37: 2 | C37: 00_sample_project | D37: Resource Allocation | E37: RA1.2 | F37: Use Recycled Materials | G37: 10 | H37: Applicable | I37: No Level | J37: 0 | K37: 0 | M37: QA:Insufficient Data(No information on recycled materials used in the project) | QB:Insufficient Data(No documentation of recycled material quantities) | N37: A + B required for Improved | O37: Research recycled material options; Develop a plan for incorporating recycled materials into the project | P37: Recycled material research; Plan for incorporating recycled materials | Q37: 17210 | R37: 2644 | S37: 930.85 | T37: TRUE | U37: FALSE | V37: TRUE
A38: rag | B38: 2 | C38: 00_sample_project | D38: Resource Allocation | E38: RA1.3 | F38: Reduce Operational Waste | G38: 8 | H38: Applicable | I38: No Level | J38: 0 | K38: 0 | M38: QA:Insufficient Data(No information on operational waste reduction strategies) | QB:Insufficient Data(No documentation of waste reduction goals or targets) | N38: A + B required for Improved | O38: Develop a plan for reducing operational waste; Research waste reduction strategies and technologies | P38: Operational waste reduction plan; Waste reduction goals or targets | Q38: 17210 | R38: 2644 | S38: 930.85 | T38: TRUE | U38: FALSE | V38: TRUE
A39: rag | B39: 2 | C39: 00_sample_project | D39: Resource Allocation | E39: RA1.4 | F39: Reduce Construction Waste | G39: 10 | H39: Applicable | I39: No Level | J39: 0 | K39: 0 | M39: QA:Insufficient Data(No information on construction waste reduction strategies) | QB:Insufficient Data(No documentation of waste reduction goals or targets) | N39: A + B required for Improved | O39: Develop a plan for reducing construction waste; Research waste reduction strategies and technologies | P39: Construction waste reduction plan; Waste reduction goals or targets | Q39: 17210 | R39: 2644 | S39: 930.85 | T39: TRUE | U39: FALSE | V39: TRUE
A40: rag | B40: 2 | C40: 00_sample_project | D40: Resource Allocation | E40: RA1.5 | F40: Balance Earthwork On Site | G40: 6 | H40: Applicable | I40: No Level | J40: 0 | K40: 0 | M40: QA:Insufficient Data(No information on earthwork balancing strategies) | QB:Insufficient Data(No documentation of earthwork balancing goals or targets) | N40: A + B required for Improved | O40: Develop a plan for balancing earthwork on site; Research earthwork balancing strategies and technologies | P40: Earthwork balancing plan; Earthwork balancing goals or targets | Q40: 17210 | R40: 2644 | S40: 930.85 | T40: TRUE | U40: FALSE | V40: TRUE
A41: rag | B41: 2 | C41: 00_sample_project | D41: Resource Allocation | E41: RA2.1 | F41: Reduce Operational Energy Consumption | G41: 20 | H41: Applicable | I41: No Level | J41: 0 | K41: 0 | M41: QA:Insufficient Data(No information on operational energy consumption reduction strategies) | QB:Insufficient Data(No documentation of energy reduction goals or targets) | N41: A + B required for Improved | O41: Develop a plan for reducing operational energy consumption; Research energy reduction strategies and technologies | P41: Operational energy consumption reduction plan; Energy reduction goals or targets | Q41: 17210 | R41: 2644 | S41: 930.85 | T41: TRUE | U41: FALSE | V41: TRUE
A42: rag | B42: 2 | C42: 00_sample_project | D42: Resource Allocation | E42: RA2.2 | F42: Reduce Construction Energy Consumption | G42: 12 | H42: Applicable | I42: No Level | J42: 0 | K42: 0 | M42: QA:Insufficient Data(No information on construction energy consumption reduction strategies) | QB:Insufficient Data(No documentation of energy reduction goals or targets) | N42: A + B required for Improved | O42: Develop a plan for reducing construction energy consumption; Research energy reduction strategies and technologies | P42: Construction energy consumption reduction plan; Energy reduction goals or targets | Q42: 17210 | R42: 2644 | S42: 930.85 | T42: TRUE | U42: FALSE | V42: TRUE
A43: rag | B43: 2 | C43: 00_sample_project | D43: Resource Allocation | E43: RA2.3 | F43: Use Renewable Energy | G43: 10 | H43: Applicable | I43: No Level | J43: 0 | K43: 0 | M43: QA:Insufficient Data(No information on renewable energy sources) | QB:Insufficient Data(No documentation of renewable energy goals or targets) | N43: A + B required for Improved | O43: Research renewable energy sources; Develop a plan for incorporating renewable energy into the project | P43: Renewable energy research; Plan for incorporating renewable energy | Q43: 17210 | R43: 2644 | S43: 930.85 | T43: TRUE | U43: FALSE | V43: TRUE
A44: rag | B44: 2 | C44: 00_sample_project | D44: Resource Allocation | E44: RA2.4 | F44: Commission and Monitor Energy Systems | G44: 8 | H44: Applicable | I44: No Level | J44: 0 | K44: 0 | M44: QA:Insufficient Data(No information on energy system commissioning and monitoring) | QB:Insufficient Data(No documentation of energy system performance goals or targets) | N44: A + B required for Improved | O44: Develop a plan for commissioning and monitoring energy systems; Research energy system performance metrics | P44: Energy system commissioning and monitoring plan; Energy system performance goals or targets | Q44: 17210 | R44: 2644 | S44: 930.85 | T44: TRUE | U44: FALSE | V44: TRUE
A45: rag | B45: 2 | C45: 00_sample_project | D45: Resource Allocation | E45: RA3.1 | F45: Preserve Water Resources | G45: 14 | H45: Applicable | I45: No Level | J45: 0 | K45: 0 | M45: QA:Insufficient Data(No information on water conservation strategies) | QB:Insufficient Data(No documentation of water reduction goals or targets) | N45: A + B required for Improved | O45: Develop a plan for preserving water resources; Research water conservation strategies and technologies | P45: Water preservation plan; Water reduction goals or targets | Q45: 17210 | R45: 2644 | S45: 930.85 | T45: TRUE | U45: FALSE | V45: TRUE
A46: rag | B46: 2 | C46: 00_sample_project | D46: Resource Allocation | E46: RA3.2 | F46: Reduce Operational Water Consumption | G46: 12 | H46: Applicable | I46: No Level | J46: 0 | K46: 0 | M46: QA:Insufficient Data(No information on operational water consumption reduction strategies) | QB:Insufficient Data(No documentation of water reduction goals or targets) | N46: A + B required for Improved | O46: Develop a plan for reducing operational water consumption; Research water reduction strategies and technologies | P46: Operational water consumption reduction plan; Water reduction goals or targets | Q46: 17210 | R46: 2644 | S46: 930.85 | T46: TRUE | U46: FALSE | V46: TRUE
A47: rag | B47: 2 | C47: 00_sample_project | D47: Resource Allocation | E47: RA3.3 | F47: Reduce Construction Water Consumption | G47: 10 | H47: Applicable | I47: No Level | J47: 0 | K47: 0 | M47: QA:Insufficient Data(No information on construction water consumption reduction strategies) | QB:Insufficient Data(No documentation of water reduction goals or targets) | N47: A + B required for Improved | O47: Develop a plan for reducing construction water consumption; Research water reduction strategies and technologies | P47: Construction water consumption reduction plan; Water reduction goals or targets | Q47: 17210 | R47: 2644 | S47: 930.85 | T47: TRUE | U47: FALSE | V47: TRUE
A48: rag | B48: 2 | C48: 00_sample_project | D48: Resource Allocation | E48: RA3.4 | F48: Monitor Water Systems | G48: 8 | H48: Applicable | I48: No Level | J48: 0 | K48: 0 | M48: QA:Insufficient Data(No information on water system monitoring) | QB:Insufficient Data(No documentation of water system performance goals or targets) | N48: A + B required for Improved | O48: Develop a plan for monitoring water systems; Research water system performance metrics | P48: Water system monitoring plan; Water system performance goals or targets | Q48: 17210 | R48: 2644 | S48: 930.85 | T48: TRUE | U48: FALSE | V48: TRUE

Sheet RAG Run 3
A1: Arm | B1: Run | C1: File | D1: Category | E1: Credit ID | F1: Credit Name | G1: Max Points | H1: Applicability | I1: Estimated Level | J1: Estimated Points | K1: % Achieved | L1: Justification | M1: Questions Summary | N1: Level Guide Reference | O1: Concept Phase Actions | P1: Documentation Needed | Q1: Input Tokens | R1: Output Tokens | S1: Elapsed (s) | T1: Valid JSON | U1: Truncated | V1: Success
A2: rag | B2: 3 | C2: 00_sample_project | D2: Climate And Resilience | E2: CR2.1 | F2: Avoid Unsuitable Development | G2: 14 | H2: APPLICABLE | I2: Improved | J2: 0 | K2: 0 | L2: The project is located in Brownsville, PA, and the PDF metadata does not indicate any unsuitable development. | M2: QA:Insufficient Data(No information on site selection process) | QB:Insufficient Data(No information on environmental impact assessment) | N2: A + B required for Improved | O2: Conduct site selection process; Perform environmental impact assessment | P2: Site selection report; Environmental impact assessment report | Q2: 17617 | R2: 1709 | S2: 618.07 | T2: TRUE | U2: FALSE | V2: TRUE
A3: rag | B3: 3 | C3: 00_sample_project | D3: Climate And Resilience | E3: CR2.2 | F3: Assess Climate Change Vulnerability | G3: 20 | H3: APPLICABLE | I3: Improved | J3: 0 | K3: 0 | L3: The project is located in Brownsville, PA, and climate change vulnerability assessment is relevant to the project. | M3: QA:Insufficient Data(No information on climate change threats) | QB:Insufficient Data(No information on project vulnerability) | QC:Insufficient Data(No information on infrastructure system vulnerability) | QD:Insufficient Data(No information on community vulnerability) | QE:Insufficient Data(No information on sharing climate threat findings) | N3: A + B required for Improved | O3: Conduct climate change vulnerability assessment; Identify project and infrastructure system vulnerabilities | P3: Climate change vulnerability assessment report; Project and infrastructure system vulnerability reports | Q3: 17617 | R3: 1709 | S3: 618.07 | T3: TRUE | U3: FALSE | V3: TRUE
A4: rag | B4: 3 | C4: 00_sample_project | D4: Climate And Resilience | E4: CR2.3 | F4: Evaluate Risk and Resilience | G4: 26 | H4: APPLICABLE | I4: Improved | J4: 0 | K4: 0 | L4: The project is located in Brownsville, PA, and risk and resilience evaluation is relevant to the project. | M4: QA:Insufficient Data(No information on risk assessment) | QB:Insufficient Data(No information on critical functions and dependencies) | QC:Insufficient Data(No information on threats or hazards) | QD:Insufficient Data(No information on vulnerabilities of critical functions and dependencies) | QE:Insufficient Data(No information on risk evaluation) | QF:Insufficient Data(No information on stakeholder participation in risk evaluation) | N4: A + B + C + D + E required for Improved | O4: Conduct risk assessment; Identify critical functions and dependencies; Evaluate risks | P4: Risk assessment report; Critical functions and dependencies report; Risk evaluation report | Q4: 17617 | R4: 1709 | S4: 618.07 | T4: TRUE | U4: FALSE | V4: TRUE
A5: rag | B5: 3 | C5: 00_sample_project | D5: Climate And Resilience | E5: CR2.4 | F5: Establish Resilience Goals and Strategies | G5: 20 | H5: APPLICABLE | I5: Enhanced | J5: 0 | K5: 0 | L5: The project is located in Brownsville, PA, and establishing resilience goals and strategies is relevant to the project. | M5: QA:Insufficient Data(No information on project performance goals) | QB:Insufficient Data(No information on risk management strategies) | QC:Insufficient Data(No information on stakeholder engagement in developing resilience goals) | QD:Insufficient Data(No information on community resilience or climate change adaptation goals) | N5: A + B required for Enhanced | O5: Establish project performance goals; Develop risk management strategies | P5: Project performance goals report; Risk management strategies report | Q5: 17617 | R5: 1709 | S5: 618.07 | T5: TRUE | U5: FALSE | V5: TRUE
A6: rag | B6: 3 | C6: 00_sample_project | D6: Climate And Resilience | E6: CR2.5 | F6: Maximize Resilience | G6: 26 | H6: APPLICABLE | I6: Enhanced | J6: 0 | K6: 0 | L6: The project is located in Brownsville, PA, and maximizing resilience is relevant to the project. | M6: QA:Insufficient Data(No information on resilience goals and strategies) | QB:Insufficient Data(No information on implementation of resilience strategies) | QC:Insufficient Data(No information on monitoring and review of resilience strategies) | QD:Insufficient Data(No information on incorporation of resilience goals into operations and maintena) | QE:Insufficient Data(No information on methods for measuring or quantifying resilience performance ta) | N6: A + B required for Enhanced | O6: Develop resilience goals and strategies; Implement resilience strategies | P6: Resilience goals and strategies report; Implementation of resilience strategies report | Q6: 17617 | R6: 1709 | S6: 618.07 | T6: TRUE | U6: FALSE | V6: TRUE
A7: rag | B7: 3 | C7: 00_sample_project | D7: Climate And Resilience | E7: CR2.6 | F7: Improve Infrastructure Integration | G7: 18 | H7: APPLICABLE | I7: Improved | J7: 0 | K7: 0 | L7: The project is located in Brownsville, PA, and improving infrastructure integration is relevant to the project. | M7: QA:Insufficient Data(No information on infrastructure system evaluation) | QB:Insufficient Data(No information on identification of opportunities for integration) | N7: A + B required for Improved | O7: Conduct infrastructure system evaluation; Identify opportunities for integration | P7: Infrastructure system evaluation report; Opportunities for integration report | Q7: 17617 | R7: 1709 | S7: 618.07 | T7: TRUE | U7: FALSE | V7: TRUE
A8: rag | B8: 3 | C8: 00_sample_project | D8: Leadership | E8: LD1.1 | F8: Provide Effective Leadership and Commitment | G8: 10 | H8: Applicable | I8: Improved | J8: 2 | K8: 20 | M8: QA:Likely Yes(Project team includes multiple stakeholders (Cartesian Inverse, PA; Etienne Oise) | QB:Insufficient Data(No information on sustainability goals or targets) | N8: A + B required for Enhanced | O8: Develop and document sustainability goals and targets | P8: Sustainability management plan; Stakeholder engagement records | Q8: 17191 | R8: 2014 | S8: 702.88 | T8: TRUE | U8: FALSE | V8: TRUE
A9: rag | B9: 3 | C9: 00_sample_project | D9: Leadership | E9: LD1.2 | F9: Foster Collaboration and Teamwork | G9: 8 | H9: Applicable | I9: Improved | J9: 2 | K9: 25 | M9: QA:Likely Yes(Multiple stakeholders involved in project team (Cartesian Inverse, PA; Etienne O) | QB:Insufficient Data(No information on collaboration and communication among team members) | N9: A + B required for Enhanced | O9: Establish clear communication channels among team members | P9: Team charter or agreement; Meeting minutes and collaboration records | Q9: 17191 | R9: 2014 | S9: 702.88 | T9: TRUE | U9: FALSE | V9: TRUE
A10: rag | B10: 3 | C10: 00_sample_project | D10: Leadership | E10: LD1.3 | F10: Encourage Public Engagement and Participation | G10: 8 | H10: Applicable | I10: No Level | J10: 0 | K10: 0 | M10: QA:Insufficient Data(No information on public engagement or participation) | QB:Insufficient Data(No information on community needs assessment) | N10: A + B required for Improved | O10: Conduct community needs assessment; Develop public engagement plan | P10: Community needs assessment report; Public engagement plan | Q10: 17191 | R10: 2014 | S10: 702.88 | T10: TRUE | U10: FALSE | V10: TRUE
A11: rag | B11: 3 | C11: 00_sample_project | D11: Leadership | E11: LD1.4 | F11: Pursue Byproduct Synergies | G11: 10 | H11: Applicable | I11: No Level | J11: 0 | K11: 0 | M11: QA:Insufficient Data(No information on byproduct synergies) | QB:Insufficient Data(No information on waste reduction or material reuse) | N11: A + B required for Improved | O11: Identify potential byproduct synergies; Develop plan for waste reduction and material reuse | P11: Byproduct synergy assessment report; Waste reduction and material reuse plan | Q11: 17191 | R11: 2014 | S11: 702.88 | T11: TRUE | U11: FALSE | V11: TRUE
A12: rag | B12: 3 | C12: 00_sample_project | D12: Leadership | E12: LD2.1 | F12: Establish a Sustainability Management Plan | G12: 12 | H12: Applicable | I12: No Level | J12: 0 | K12: 0 | M12: QA:Insufficient Data(No information on sustainability management plan) | QB:Insufficient Data(No information on monitoring and reporting) | N12: A + B required for Improved | O12: Develop sustainability management plan; Establish monitoring and reporting protocols | P12: Sustainability management plan; Monitoring and reporting records | Q12: 17191 | R12: 2014 | S12: 702.88 | T12: TRUE | U12: FALSE | V12: TRUE
A13: rag | B13: 3 | C13: 00_sample_project | D13: Leadership | E13: LD2.2 | F13: Plan for Sustainable Communities | G13: 10 | H13: Applicable | I13: No Level | J13: 0 | K13: 0 | M13: QA:Insufficient Data(No information on community planning) | QB:Insufficient Data(No information on social and economic benefits) | N13: A + B required for Improved | O13: Conduct community planning assessment; Develop plan for social and economic benefits | P13: Community planning report; Social and economic benefits plan | Q13: 17191 | R13: 2014 | S13: 702.88 | T13: TRUE | U13: FALSE | V13: TRUE
A14: rag | B14: 3 | C14: 00_sample_project | D14: Leadership | E14: LD2.3 | F14: Plan for Long-Term Maintenance and Operations | G14: 8 | H14: Applicable | I14: No Level | J14: 0 | K14: 0 | M14: QA:Insufficient Data(No information on maintenance and operations planning) | QB:Insufficient Data(No information on training and capacity building) | N14: A + B required for Improved | O14: Develop maintenance and operations plan; Establish training and capacity building programs | P14: Maintenance and operations plan; Training and capacity building records | Q14: 17191 | R14: 2014 | S14: 702.88 | T14: TRUE | U14: FALSE | V14: TRUE
A15: rag | B15: 3 | C15: 00_sample_project | D15: Leadership | E15: LD3.1 | F15: Conduct a Life-Cycle Economic Evaluation | G15: 12 | H15: Applicable | I15: No Level | J15: 0 | K15: 0 | M15: QA:Insufficient Data(No information on life-cycle economic evaluation) | QB:Insufficient Data(No information on cost-benefit analysis) | N15: A + B required for Improved | O15: Conduct life-cycle economic evaluation; Develop cost-benefit analysis | P15: Life-cycle economic evaluation report; Cost-benefit analysis records | Q15: 17191 | R15: 2014 | S15: 702.88 | T15: TRUE | U15: FALSE | V15: TRUE
A16: rag | B16: 3 | C16: 00_sample_project | D16: Leadership | E16: LD3.2 | F16: Evaluate Environmental and Social Impacts | G16: 10 | H16: Applicable | I16: No Level | J16: 0 | K16: 0 | M16: QA:Insufficient Data(No information on environmental impact assessment) | QB:Insufficient Data(No information on social impact assessment) | N16: A + B required for Improved | O16: Conduct environmental impact assessment; Develop social impact assessment | P16: Environmental impact assessment report; Social impact assessment records | Q16: 17191 | R16: 2014 | S16: 702.88 | T16: TRUE | U16: FALSE | V16: TRUE
A17: rag | B17: 3 | C17: 00_sample_project | D17: Leadership | E17: LD3.3 | F17: Conduct a Life-Cycle Assessment | G17: 12 | H17: Applicable | I17: No Level | J17: 0 | K17: 0 | M17: QA:Insufficient Data(No information on life-cycle assessment) | QB:Insufficient Data(No information on environmental impacts) | N17: A + B required for Improved | O17: Conduct life-cycle assessment; Develop plan to reduce environmental impacts | P17: Life-cycle assessment report; Environmental impact reduction plan | Q17: 17191 | R17: 2014 | S17: 702.88 | T17: TRUE | U17: FALSE | V17: TRUE
A18: rag | B18: 3 | C18: 00_sample_project | D18: Natural World | E18: NW1.1 | F18: Conserve Natural Areas | G18: 14 | H18: APPLICABLE | I18: No Level | J18: 0 | K18: 0 | L18: The project is located in an area with potential natural habitats, and the credit's intent is to conserve these areas. | M18: QA:Insufficient Data(No information on natural habitat conservation) | QB:Insufficient Data(No information on native vegetation preservation) | N18: A + B required for Improved | O18: Conduct natural habitat assessment; Develop conservation plan | P18: Natural habitat assessment report; Conservation plan | Q18: 17916 | R18: 1444 | S18: 551.74 | T18: TRUE | U18: FALSE | V18: TRUE
A19: rag | B19: 3 | C19: 00_sample_project | D19: Natural World | E19: NW1.2 | F19: Provide Wetland and Surface Water Buffers | G19: 10 | H19: APPLICABLE | I19: No Level | J19: 0 | K19: 0 | L19: The project is located near a water body, and the credit's intent is to provide buffers for wetlands and surface water. | M19: QA:Insufficient Data(No information on wetland buffer zones) | QB:Insufficient Data(No information on surface water buffer zones) | N19: A + B required for Improved | O19: Conduct wetland and surface water assessment; Develop buffer zone plan | P19: Wetland and surface water assessment report; Buffer zone plan | Q19: 17916 | R19: 1444 | S19: 551.74 | T19: TRUE | U19: FALSE | V19: TRUE
A20: rag | B20: 3 | C20: 00_sample_project | D20: Natural World | E20: NW2.2 | F20: Manage Stormwater | G20: 24 | H20: APPLICABLE | I20: No Level | J20: 0 | K20: 0 | L20: The project will impact stormwater runoff, and the credit's intent is to manage it. | M20: QA:Insufficient Data(No information on stormwater management plan) | QB:Insufficient Data(No information on rate or quantity of runoff) | N20: A + B required for Improved | O20: Develop stormwater management plan; Conduct runoff analysis | P20: Stormwater management plan; Runoff analysis report | Q20: 17916 | R20: 1444 | S20: 551.74 | T20: TRUE | U20: FALSE | V20: TRUE
A21: rag | B21: 3 | C21: 00_sample_project | D21: Natural World | E21: NW2.4 | F21: Protect Surface and Groundwater Quality | G21: 14 | H21: APPLICABLE | I21: No Level | J21: 0 | K21: 0 | L21: The project will impact surface and groundwater quality, and the credit's intent is to protect it. | M21: QA:Insufficient Data(No information on surface water protection plan) | QB:Insufficient Data(No information on groundwater protection plan) | N21: A + B required for Improved | O21: Develop surface water protection plan; Conduct groundwater assessment | P21: Surface water protection plan; Groundwater assessment report | Q21: 17916 | R21: 1444 | S21: 551.74 | T21: TRUE | U21: FALSE | V21: TRUE
A22: rag | B22: 3 | C22: 00_sample_project | D22: Natural World | E22: NW3.3 | F22: Maintain Floodplain Functions | G22: 14 | H22: APPLICABLE | I22: No Level | J22: 0 | K22: 0 | L22: The project is located in a floodplain, and the credit's intent is to maintain its functions. | M22: QA:Insufficient Data(No information on floodplain assessment) | QB:Insufficient Data(No information on vegetated zone preservation) | N22: A + B required for Improved | O22: Conduct floodplain assessment; Develop vegetated zone preservation plan | P22: Floodplain assessment report; Vegetated zone preservation plan | Q22: 17916 | R22: 1444 | S22: 551.74 | T22: TRUE | U22: FALSE | V22: TRUE
A23: rag | B23: 3 | C23: 00_sample_project | D23: Natural World | E23: NW3.5 | F23: Protect Soil Health | G23: 10 | H23: APPLICABLE | I23: No Level | J23: 0 | K23: 0 | L23: The project will impact soil health, and the credit's intent is to protect it. | M23: QA:Insufficient Data(No information on soil health assessment) | QB:Insufficient Data(No information on soil conservation plan) | N23: A + B required for Improved | O23: Conduct soil health assessment; Develop soil conservation plan | P23: Soil health assessment report; Soil conservation plan | Q23: 17916 | R23: 1444 | S23: 551.74 | T23: TRUE | U23: FALSE | V23: TRUE
A24: rag | B24: 3 | C24: 00_sample_project | D24: Quality Of Life | E24: QL1.1 | F24: Improve Community Quality of Life | G24: 26 | H24: Applicable | I24: Improved | J24: 5 | K24: 19.2 | L24: The project is a mixed-use development with residential, commercial, and community spaces, indicating potential for community quality of life improvements. | M24: QA:Likely Yes(Project includes live/work units and community spaces.) | QB:Insufficient Data(Lack of information on community engagement and feedback mechanisms.) | QC:Likely Yes(Project incorporates green spaces and outdoor areas.) | QD:Insufficient Data(Lack of information on accessibility features and universal design principles.) | N24: A + B | O24: Conduct community outreach and engagement to inform design decisions.; Incorporate accessible and universal design principles into building design. | P24: Community engagement records; Accessibility features and universal design principles documentation | Q24: 17220 | R24: 2918 | S24: 1022.57 | T24: TRUE | U24: FALSE | V24: TRUE
A25: rag | B25: 3 | C25: 00_sample_project | D25: Quality Of Life | E25: QL1.2 | F25: Enhance Public Health & Safety | G25: 20 | H25: Applicable | I25: Improved | J25: 7 | K25: 35 | L25: The project includes residential and commercial spaces, indicating potential public health and safety concerns. | M25: QA:Likely Yes(Project incorporates natural ventilation and daylighting strategies.) | QB:Insufficient Data(Lack of information on indoor air quality monitoring and maintenance protocols.) | QC:Likely Yes(Project includes emergency response plan and fire suppression systems.) | N25: A + B | O25: Develop indoor air quality monitoring and maintenance protocols.; Incorporate public health and safety considerations into design decisions. | P25: Indoor air quality monitoring and maintenance protocols; Public health and safety consideration documentation | Q25: 17220 | R25: 2918 | S25: 1022.57 | T25: TRUE | U25: FALSE | V25: TRUE
A26: rag | B26: 3 | C26: 00_sample_project | D26: Quality Of Life | E26: QL1.3 | F26: Improve Construction Safety | G26: 14 | H26: Applicable | I26: Improved | J26: 5 | K26: 35.7 | L26: The project involves construction activities, indicating potential construction safety concerns. | M26: QA:Likely Yes(Project includes construction safety plan and training programs.) | QB:Insufficient Data(Lack of information on site-specific hazard assessments and mitigation strategie) | N26: A + B | O26: Conduct site-specific hazard assessments and develop mitigation strategies.; Incorporate construction safety considerations into design decisions. | P26: Construction safety plan and training programs; Site-specific hazard assessments and mitigation strategies | Q26: 17220 | R26: 2918 | S26: 1022.57 | T26: TRUE | U26: FALSE | V26: TRUE
A27: rag | B27: 3 | C27: 00_sample_project | D27: Quality Of Life | E27: QL1.4 | F27: Minimize Noise & Vibration | G27: 12 | H27: Applicable | I27: Improved | J27: 3 | K27: 25 | L27: The project includes residential and commercial spaces, indicating potential noise and vibration concerns. | M27: QA:Likely Yes(Project incorporates sound-absorbing materials and acoustic design strategies.) | QB:Insufficient Data(Lack of information on vibration mitigation measures and monitoring protocols.) | N27: A + B | O27: Develop vibration mitigation measures and monitoring protocols.; Incorporate noise and vibration considerations into design decisions. | P27: Sound-absorbing materials and acoustic design strategies; Vibration mitigation measures and monitoring protocols | Q27: 17220 | R27: 2918 | S27: 1022.57 | T27: TRUE | U27: FALSE | V27: TRUE
A28: rag | B28: 3 | C28: 00_sample_project | D28: Quality Of Life | E28: QL1.5 | F28: Minimize Light Pollution | G28: 12 | H28: Applicable | I28: Improved | J28: 3 | K28: 25 | L28: The project includes exterior lighting, indicating potential light pollution concerns. | M28: QA:Likely Yes(Project incorporates energy-efficient and shielded lighting fixtures.) | QB:Insufficient Data(Lack of information on lighting controls and scheduling protocols.) | N28: A + B | O28: Develop lighting controls and scheduling protocols.; Incorporate light pollution considerations into design decisions. | P28: Energy-efficient and shielded lighting fixtures; Lighting controls and scheduling protocols | Q28: 17220 | R28: 2918 | S28: 1022.57 | T28: TRUE | U28: FALSE | V28: TRUE
A29: rag | B29: 3 | C29: 00_sample_project | D29: Quality Of Life | E29: QL1.6 | F29: Minimize Construction Impacts | G29: 8 | H29: Applicable | I29: Improved | J29: 2 | K29: 25 | L29: The project involves construction activities, indicating potential construction impacts. | M29: QA:Likely Yes(Project includes construction waste management plan and recycling programs.) | QB:Insufficient Data(Lack of information on site-specific erosion control measures and sedimentation ) | N29: A + B | O29: Develop site-specific erosion control measures and sedimentation mitigation strategies.; Incorporate construction impact considerations into design decisions. | P29: Construction waste management plan and recycling programs; Site-specific erosion control measures and sedimentation mitigation strategies | Q29: 17220 | R29: 2918 | S29: 1022.57 | T29: TRUE | U29: FALSE | V29: TRUE
... A35: rag | B35: 3 | C35: 00_sample_project | D35: Quality Of Life | E35: QL3.3 | F35: Enhance Views & Local Character | G35: 14 | H35: Applicable | I35: Improved | J35: 3 | K35: 21.4 | L35: The project includes public spaces and views, indicating potential view and local character concerns. | M35: QA:Likely Yes(Project incorporates view preservation strategies and local character design ele) | QB:Insufficient Data(Lack of information on community engagement and feedback mechanisms.) | N35: A + B | O35: Develop community engagement and feedback mechanisms.; Incorporate view and local character considerations into design decisions. | P35: View preservation strategies and local character design elements; Community engagement and feedback mechanisms | Q35: 17220 | R35: 2918 | S35: 1022.57 | T35: TRUE | U35: FALSE | V35: TRUE
A36: rag | B36: 3 | C36: 00_sample_project | D36: Resource Allocation | E36: RA1.1 | F36: Reduce Materials Use | G36: 12 | H36: Applicable | I36: No Level | J36: 0 | K36: 0 | M36: QA:Insufficient Data(No material takeoff or bill of quantities in the model) | QB:Insufficient Data(No information on recycled content or sustainable materials) | N36: A + B required for Improved | O36: Develop a material takeoff and bill of quantities; Research sustainable materials and recycled content options | P36: Material takeoff and bill of quantities; Sustainable materials and recycled content research | Q36: 17210 | R36: 2644 | S36: 934.53 | T36: TRUE | U36: FALSE | V36: TRUE
A37: rag | B37: 3 | C37: 00_sample_project | D37: Resource Allocation | E37: RA1.2 | F37: Use Recycled Materials | G37: 10 | H37: Applicable | I37: No Level | J37: 0 | K37: 0 | M37: QA:Insufficient Data(No information on recycled materials used in the project) | QB:Insufficient Data(No documentation of recycled material quantities) | N37: A + B required for Improved | O37: Research recycled material options; Develop a plan for incorporating recycled materials into the project | P37: Recycled material research; Plan for incorporating recycled materials | Q37: 17210 | R37: 2644 | S37: 934.53 | T37: TRUE | U37: FALSE | V37: TRUE
A38: rag | B38: 3 | C38: 00_sample_project | D38: Resource Allocation | E38: RA1.3 | F38: Reduce Operational Waste | G38: 8 | H38: Applicable | I38: No Level | J38: 0 | K38: 0 | M38: QA:Insufficient Data(No information on operational waste reduction strategies) | QB:Insufficient Data(No documentation of waste reduction goals or targets) | N38: A + B required for Improved | O38: Develop a plan for reducing operational waste; Research waste reduction strategies and technologies | P38: Operational waste reduction plan; Waste reduction goals or targets | Q38: 17210 | R38: 2644 | S38: 934.53 | T38: TRUE | U38: FALSE | V38: TRUE
A39: rag | B39: 3 | C39: 00_sample_project | D39: Resource Allocation | E39: RA1.4 | F39: Reduce Construction Waste | G39: 10 | H39: Applicable | I39: No Level | J39: 0 | K39: 0 | M39: QA:Insufficient Data(No information on construction waste reduction strategies) | QB:Insufficient Data(No documentation of waste reduction goals or targets) | N39: A + B required for Improved | O39: Develop a plan for reducing construction waste; Research waste reduction strategies and technologies | P39: Construction waste reduction plan; Waste reduction goals or targets | Q39: 17210 | R39: 2644 | S39: 934.53 | T39: TRUE | U39: FALSE | V39: TRUE
A40: rag | B40: 3 | C40: 00_sample_project | D40: Resource Allocation | E40: RA1.5 | F40: Balance Earthwork On Site | G40: 6 | H40: Applicable | I40: No Level | J40: 0 | K40: 0 | M40: QA:Insufficient Data(No information on earthwork balancing strategies) | QB:Insufficient Data(No documentation of earthwork balancing goals or targets) | N40: A + B required for Improved | O40: Develop a plan for balancing earthwork on site; Research earthwork balancing strategies and technologies | P40: Earthwork balancing plan; Earthwork balancing goals or targets | Q40: 17210 | R40: 2644 | S40: 934.53 | T40: TRUE | U40: FALSE | V40: TRUE
A41: rag | B41: 3 | C41: 00_sample_project | D41: Resource Allocation | E41: RA2.1 | F41: Reduce Operational Energy Consumption | G41: 20 | H41: Applicable | I41: No Level | J41: 0 | K41: 0 | M41: QA:Insufficient Data(No information on operational energy consumption reduction strategies) | QB:Insufficient Data(No documentation of energy reduction goals or targets) | N41: A + B required for Improved | O41: Develop a plan for reducing operational energy consumption; Research energy reduction strategies and technologies | P41: Operational energy consumption reduction plan; Energy reduction goals or targets | Q41: 17210 | R41: 2644 | S41: 934.53 | T41: TRUE | U41: FALSE | V41: TRUE
A42: rag | B42: 3 | C42: 00_sample_project | D42: Resource Allocation | E42: RA2.2 | F42: Reduce Construction Energy Consumption | G42: 12 | H42: Applicable | I42: No Level | J42: 0 | K42: 0 | M42: QA:Insufficient Data(No information on construction energy consumption reduction strategies) | QB:Insufficient Data(No documentation of energy reduction goals or targets) | N42: A + B required for Improved | O42: Develop a plan for reducing construction energy consumption; Research energy reduction strategies and technologies | P42: Construction energy consumption reduction plan; Energy reduction goals or targets | Q42: 17210 | R42: 2644 | S42: 934.53 | T42: TRUE | U42: FALSE | V42: TRUE
A43: rag | B43: 3 | C43: 00_sample_project | D43: Resource Allocation | E43: RA2.3 | F43: Use Renewable Energy | G43: 10 | H43: Applicable | I43: No Level | J43: 0 | K43: 0 | M43: QA:Insufficient Data(No information on renewable energy sources) | QB:Insufficient Data(No documentation of renewable energy goals or targets) | N43: A + B required for Improved | O43: Research renewable energy sources; Develop a plan for incorporating renewable energy into the project | P43: Renewable energy research; Plan for incorporating renewable energy | Q43: 17210 | R43: 2644 | S43: 934.53 | T43: TRUE | U43: FALSE | V43: TRUE
A44: rag | B44: 3 | C44: 00_sample_project | D44: Resource Allocation | E44: RA2.4 | F44: Commission and Monitor Energy Systems | G44: 8 | H44: Applicable | I44: No Level | J44: 0 | K44: 0 | M44: QA:Insufficient Data(No information on energy system commissioning and monitoring) | QB:Insufficient Data(No documentation of energy system performance goals or targets) | N44: A + B required for Improved | O44: Develop a plan for commissioning and monitoring energy systems; Research energy system performance metrics | P44: Energy system commissioning and monitoring plan; Energy system performance goals or targets | Q44: 17210 | R44: 2644 | S44: 934.53 | T44: TRUE | U44: FALSE | V44: TRUE
A45: rag | B45: 3 | C45: 00_sample_project | D45: Resource Allocation | E45: RA3.1 | F45: Preserve Water Resources | G45: 14 | H45: Applicable | I45: No Level | J45: 0 | K45: 0 | M45: QA:Insufficient Data(No information on water conservation strategies) | QB:Insufficient Data(No documentation of water reduction goals or targets) | N45: A + B required for Improved | O45: Develop a plan for preserving water resources; Research water conservation strategies and technologies | P45: Water preservation plan; Water reduction goals or targets | Q45: 17210 | R45: 2644 | S45: 934.53 | T45: TRUE | U45: FALSE | V45: TRUE
A46: rag | B46: 3 | C46: 00_sample_project | D46: Resource Allocation | E46: RA3.2 | F46: Reduce Operational Water Consumption | G46: 12 | H46: Applicable | I46: No Level | J46: 0 | K46: 0 | M46: QA:Insufficient Data(No information on operational water consumption reduction strategies) | QB:Insufficient Data(No documentation of water reduction goals or targets) | N46: A + B required for Improved | O46: Develop a plan for reducing operational water consumption; Research water reduction strategies and technologies | P46: Operational water consumption reduction plan; Water reduction goals or targets | Q46: 17210 | R46: 2644 | S46: 934.53 | T46: TRUE | U46: FALSE | V46: TRUE
A47: rag | B47: 3 | C47: 00_sample_project | D47: Resource Allocation | E47: RA3.3 | F47: Reduce Construction Water Consumption | G47: 10 | H47: Applicable | I47: No Level | J47: 0 | K47: 0 | M47: QA:Insufficient Data(No information on construction water consumption reduction strategies) | QB:Insufficient Data(No documentation of water reduction goals or targets) | N47: A + B required for Improved | O47: Develop a plan for reducing construction water consumption; Research water reduction strategies and technologies | P47: Construction water consumption reduction plan; Water reduction goals or targets | Q47: 17210 | R47: 2644 | S47: 934.53 | T47: TRUE | U47: FALSE | V47: TRUE
A48: rag | B48: 3 | C48: 00_sample_project | D48: Resource Allocation | E48: RA3.4 | F48: Monitor Water Systems | G48: 8 | H48: Applicable | I48: No Level | J48: 0 | K48: 0 | M48: QA:Insufficient Data(No information on water system monitoring) | QB:Insufficient Data(No documentation of water system performance goals or targets) | N48: A + B required for Improved | O48: Develop a plan for monitoring water systems; Research water system performance metrics | P48: Water system monitoring plan; Water system performance goals or targets | Q48: 17210 | R48: 2644 | S48: 934.53 | T48: TRUE | U48: FALSE | V48: TRUE

Sheet RAG Run 4
A1: Arm | B1: Run | C1: File | D1: Category | E1: Credit ID | F1: Credit Name | G1: Max Points | H1: Applicability | I1: Estimated Level | J1: Estimated Points | K1: % Achieved | L1: Justification | M1: Questions Summary | N1: Level Guide Reference | O1: Concept Phase Actions | P1: Documentation Needed | Q1: Input Tokens | R1: Output Tokens | S1: Elapsed (s) | T1: Valid JSON | U1: Truncated | V1: Success
A2: rag | B2: 4 | C2: 00_sample_project | D2: Climate And Resilience | E2: CR2.1 | F2: Avoid Unsuitable Development | G2: 14 | H2: Applicable | I2: No Level | J2: 0 | K2: 0 | M2: QA:Insufficient Data(No information on site selection process) | QB:Insufficient Data(No environmental impact assessment available) | N2: A + B required for Improved | O2: Conduct site selection process with environmental considerations; Perform environmental impact assessment | P2: Site selection report; Environmental impact assessment | Q2: 17617 | R2: 1228 | S2: 432.19 | T2: TRUE | U2: FALSE | V2: TRUE
A3: rag | B3: 4 | C3: 00_sample_project | D3: Climate And Resilience | E3: CR2.2 | F3: Assess Climate Change Vulnerability | G3: 20 | H3: Applicable | I3: No Level | J3: 0 | K3: 0 | M3: QA:Insufficient Data(No climate change vulnerability assessment available) | QB:Insufficient Data(No information on project vulnerabilities) | N3: A + B required for Improved | O3: Conduct climate change vulnerability assessment; Identify project vulnerabilities | P3: Climate change vulnerability assessment report; Project vulnerability analysis | Q3: 17617 | R3: 1228 | S3: 432.19 | T3: TRUE | U3: FALSE | V3: TRUE
A4: rag | B4: 4 | C4: 00_sample_project | D4: Climate And Resilience | E4: CR2.3 | F4: Evaluate Risk and Resilience | G4: 26 | H4: Applicable | I4: No Level | J4: 0 | K4: 0 | M4: QA:Insufficient Data(No risk evaluation available) | QB:Insufficient Data(No information on critical functions and dependencies) | N4: A + B + C + D + E required for Conserving | O4: Conduct risk evaluation; Identify critical functions and dependencies | P4: Risk evaluation report; Critical functions and dependencies analysis | Q4: 17617 | R4: 1228 | S4: 432.19 | T4: TRUE | U4: FALSE | V4: TRUE
A5: rag | B5: 4 | C5: 00_sample_project | D5: Climate And Resilience | E5: CR2.4 | F5: Establish Resilience Goals and Strategies | G5: 20 | H5: Applicable | I5: No Level | J5: 0 | K5: 0 | M5: QA:Insufficient Data(No resilience goals available) | QB:Insufficient Data(No information on risk management strategies) | N5: A + B required for Enhanced | O5: Establish resilience goals; Develop risk management strategies | P5: Resilience goals document; Risk management strategies report | Q5: 17617 | R5: 1228 | S5: 432.19 | T5: TRUE | U5: FALSE | V5: TRUE
A6: rag | B6: 4 | C6: 00_sample_project | D6: Climate And Resilience | E6: CR2.5 | F6: Maximize Resilience | G6: 26 | H6: Applicable | I6: No Level | J6: 0 | K6: 0 | M6: QA:Insufficient Data(No information on resilience implementation) | QB:Insufficient Data(No information on monitoring and review of resilience strategies) | N6: A + B + C + D + E required for Conserving | O6: Implement resilience strategies; Monitor and review resilience strategies | P6: Resilience implementation plan; Monitoring and review report | Q6: 17617 | R6: 1228 | S6: 432.19 | T6: TRUE | U6: FALSE | V6: TRUE
A7: rag | B7: 4 | C7: 00_sample_project | D7: Climate And Resilience | E7: CR2.6 | F7: Improve Infrastructure Integration | G7: 18 | H7: Applicable | I7: No Level | J7: 0 | K7: 0 | M7: QA:Insufficient Data(No information on infrastructure integration) | N7: A required for Improved | O7: Improve infrastructure integration | P7: Infrastructure integration report | Q7: 17617 | R7: 1228 | S7: 432.19 | T7: TRUE | U7: FALSE | V7: TRUE
A8: rag | B8: 4 | C8: 00_sample_project | D8: Leadership | E8: LD1.1 | F8: Provide Effective Leadership and Commitment | G8: 10 | H8: Applicable | I8: Improved | J8: 2 | K8: 20 | M8: QA:Likely Yes(Project team includes multiple stakeholders (Cartesian Inverse, PA; Etienne Oise) | QB:Insufficient Data(No information on sustainability goals or targets) | N8: A + B required for Enhanced | O8: Develop sustainability goals and targets | P8: Sustainability management plan; Stakeholder engagement records | Q8: 17191 | R8: 1948 | S8: 679.79 | T8: TRUE | U8: FALSE | V8: TRUE
A9: rag | B9: 4 | C9: 00_sample_project | D9: Leadership | E9: LD1.2 | F9: Foster Collaboration and Teamwork | G9: 8 | H9: Applicable | I9: Improved | J9: 2 | K9: 25 | M9: QA:Likely Yes(Multiple stakeholders involved in project team (Cartesian Inverse, PA; Etienne O) | QB:Insufficient Data(No information on collaboration tools or processes) | N9: A + B required for Enhanced | O9: Establish collaboration tools and processes | P9: Collaboration plan; Meeting minutes | Q9: 17191 | R9: 1948 | S9: 679.79 | T9: TRUE | U9: FALSE | V9: TRUE
A10: rag | B10: 4 | C10: 00_sample_project | D10: Leadership | E10: LD1.3 | F10: Encourage Public Engagement and Participation | G10: 8 | H10: Applicable | I10: No Level | J10: 0 | K10: 0 | M10: QA:Insufficient Data(No information on public engagement or participation) | QB:Insufficient Data(No information on community outreach or education) | N10: A + B required for Improved | O10: Develop public engagement and participation plan | P10: Public engagement plan; Community outreach records | Q10: 17191 | R10: 1948 | S10: 679.79 | T10: TRUE | U10: FALSE | V10: TRUE
A11: rag | B11: 4 | C11: 00_sample_project | D11: Leadership | E11: LD1.4 | F11: Pursue Byproduct Synergies | G11: 10 | H11: Applicable | I11: No Level | J11: 0 | K11: 0 | M11: QA:Insufficient Data(No information on byproduct synergies) | QB:Insufficient Data(No information on waste reduction or material reuse) | N11: A + B required for Improved | O11: Investigate byproduct synergies opportunities | P11: Byproduct synergy plan; Waste reduction records | Q11: 17191 | R11: 1948 | S11: 679.79 | T11: TRUE | U11: FALSE | V11: TRUE
A12: rag | B12: 4 | C12: 00_sample_project | D12: Leadership | E12: LD2.1 | F12: Establish a Sustainability Management Plan | G12: 12 | H12: Applicable | I12: No Level | J12: 0 | K12: 0 | M12: QA:Insufficient Data(No information on sustainability management plan) | QB:Insufficient Data(No information on monitoring and reporting processes) | N12: A + B required for Improved | O12: Develop sustainability management plan | P12: Sustainability management plan; Monitoring and reporting records | Q12: 17191 | R12: 1948 | S12: 679.79 | T12: TRUE | U12: FALSE | V12: TRUE
A13: rag | B13: 4 | C13: 00_sample_project | D13: Leadership | E13: LD2.2 | F13: Plan for Sustainable Communities | G13: 10 | H13: Applicable | I13: No Level | J13: 0 | K13: 0 | M13: QA:Insufficient Data(No information on community planning or engagement) | QB:Insufficient Data(No information on social and economic benefits) | N13: A + B required for Improved | O13: Develop community planning and engagement plan | P13: Community planning report; Social and economic benefit analysis | Q13: 17191 | R13: 1948 | S13: 679.79 | T13: TRUE | U13: FALSE | V13: TRUE
... A17: rag | B17: 4 | C17: 00_sample_project | D17: Leadership | E17: LD3.3 | F17: Conduct a Life-Cycle Assessment | G17: 12 | H17: Applicable | I17: No Level | J17: 0 | K17: 0 | M17: QA:Insufficient Data(No information on life-cycle assessment) | QB:Insufficient Data(No information on environmental impacts or material selection) | N17: A + B required for Improved | O17: Conduct life-cycle assessment | P17: Life-cycle assessment report; Environmental impact records | Q17: 17191 | R17: 1948 | S17: 679.79 | T17: TRUE | U17: FALSE | V17: TRUE
A18: rag | B18: 4 | C18: 00_sample_project | D18: Natural World | E18: NW1.1 | F18: Conserve Natural Areas | G18: 14 | H18: APPLICABLE | I18: No Level | J18: 0 | K18: 0 | L18: The project is located in a specific area (Brownsville, PA) and has a defined site boundary, indicating potential natural areas to conserve. | M18: QA:Insufficient Data(No information on natural areas within the project site) | QB:Insufficient Data(No data on habitat restoration or enhancement) | N18: A + B required for Improved | O18: Conduct site assessment to identify natural areas; Research local conservation goals and regulations | P18: Site assessment report; Conservation plan | Q18: 17916 | R18: 1404 | S18: 538.95 | T18: TRUE | U18: FALSE | V18: TRUE
A19: rag | B19: 4 | C19: 00_sample_project | D19: Natural World | E19: NW1.2 | F19: Provide Wetland and Surface Water Buffers | G19: 10 | H19: APPLICABLE | I19: No Level | J19: 0 | K19: 0 | L19: The project's location near a water body (implied by the presence of a stormwater management plan) suggests potential wetlands or surface waters that may require buffers. | M19: QA:Insufficient Data(No information on wetland or surface water buffers) | QB:Insufficient Data(No data on buffer zone maintenance) | N19: A + B required for Improved | O19: Conduct wetland delineation; Research local buffer zone requirements | P19: Wetland delineation report; Buffer zone maintenance plan | Q19: 17916 | R19: 1404 | S19: 538.95 | T19: TRUE | U19: FALSE | V19: TRUE
A20: rag | B20: 4 | C20: 00_sample_project | D20: Natural World | E20: NW2.2 | F20: Manage Stormwater | G20: 24 | H20: APPLICABLE | I20: Improved | J20: 2 | K20: 8.3 | L20: The project's stormwater management plan indicates an impact on stormwater runoff, making this credit applicable. | M20: QA:Likely Yes(Stormwater management plan mentioned in the PDF metadata) | QB:Insufficient Data(No data on rate or quantity of runoff) | N20: A + B required for Improved | O20: Develop stormwater management plan; Research local stormwater regulations | P20: Stormwater management plan; Runoff calculation report | Q20: 17916 | R20: 1404 | S20: 538.95 | T20: TRUE | U20: FALSE | V20: TRUE
A21: rag | B21: 4 | C21: 00_sample_project | D21: Natural World | E21: NW2.4 | F21: Protect Surface and Groundwater Quality | G21: 14 | H21: APPLICABLE | I21: No Level | J21: 0 | K21: 0 | L21: The project's potential impact on surface and groundwater quality, as implied by the stormwater management plan, makes this credit applicable. | M21: QA:Insufficient Data(No information on surface or groundwater protection measures) | QB:Insufficient Data(No data on water quality monitoring) | N21: A + B required for Improved | O21: Research local water quality regulations; Develop surface and groundwater protection plan | P21: Surface and groundwater protection plan; Water quality monitoring report | Q21: 17916 | R21: 1404 | S21: 538.95 | T21: TRUE | U21: FALSE | V21: TRUE
A22: rag | B22: 4 | C22: 00_sample_project | D22: Natural World | E22: NW3.3 | F22: Maintain Floodplain Functions | G22: 14 | H22: APPLICABLE | I22: No Level | J22: 0 | K22: 0 | L22: The project's location in a floodplain (implied by the presence of a stormwater management plan) suggests potential impacts on floodplain functions. | M22: QA:Insufficient Data(No information on floodplain functions) | QB:Insufficient Data(No data on vegetated zones within the floodplain) | N22: A + B required for Improved | O22: Conduct floodplain analysis; Research local floodplain regulations | P22: Floodplain analysis report; Vegetated zone maintenance plan | Q22: 17916 | R22: 1404 | S22: 538.95 | T22: TRUE | U22: FALSE | V22: TRUE
A23: rag | B23: 4 | C23: 00_sample_project | D23: Natural World | E23: NW3.5 | F23: Protect Soil Health | G23: 10 | H23: APPLICABLE | I23: No Level | J23: 0 | K23: 0 | L23: The project's potential impact on soil health, as implied by the presence of a site plan, makes this credit applicable. | M23: QA:Insufficient Data(No information on soil health protection measures) | QB:Insufficient Data(No data on soil erosion control) | N23: A + B required for Improved | O23: Research local soil health regulations; Develop soil health protection plan | P23: Soil health protection plan; Soil erosion control report | Q23: 17916 | R23: 1404 | S23: 538.95 | T23: TRUE | U23: FALSE | V23: TRUE
A24: rag | B24: 4 | C24: 00_sample_project | D24: Quality Of Life | E24: QL1.1 | F24: Improve Community Quality of Life | G24: 26 | H24: Applicable | I24: Improved | J24: 2 | K24: 7.7 | L24: The project is a mixed-use development with residential, commercial, and community spaces, indicating potential for community quality of life improvements. | M24: QA:Likely Yes(Project includes live/work units and community spaces.) | QB:Insufficient Data(Lack of information on community engagement and feedback mechanisms.) | N24: A + B required for Enhanced | O24: Engage with local stakeholders to understand community needs and priorities. | P24: Community engagement records; Stakeholder feedback mechanisms | Q24: 17220 | R24: 2438 | S24: 865.47 | T24: TRUE | U24: FALSE | V24: TRUE
A25: rag | B25: 4 | C25: 00_sample_project | D25: Quality Of Life | E25: QL1.2 | F25: Enhance Public Health & Safety | G25: 20 | H25: Applicable | I25: Improved | J25: 2 | K25: 10 | L25: The project includes residential units and commercial spaces, indicating potential public health and safety concerns. | M25: QA:Likely Yes(Project includes fire resistive walls and smoke barriers.) | QB:Insufficient Data(Lack of information on emergency response planning and evacuation procedures.) | N25: A + B required for Enhanced | O25: Develop emergency response plan and evacuation procedures. | P25: Emergency response plan; Evacuation procedure documents | Q25: 17220 | R25: 2438 | S25: 865.47 | T25: TRUE | U25: FALSE | V25: TRUE
A26: rag | B26: 4 | C26: 00_sample_project | D26: Quality Of Life | E26: QL1.3 | F26: Improve Construction Safety | G26: 14 | H26: Applicable | I26: Improved | J26: 2 | K26: 14.3 | L26: The project involves construction activities, indicating potential construction safety concerns. | M26: QA:Likely Yes(Project includes safety protocols for construction workers.) | QB:Insufficient Data(Lack of information on construction safety training programs.) | N26: A + B required for Enhanced | O26: Develop construction safety training program. | P26: Construction safety protocols; Safety training program documents | Q26: 17220 | R26: 2438 | S26: 865.47 | T26: TRUE | U26: FALSE | V26: TRUE
A27: rag | B27: 4 | C27: 00_sample_project | D27: Quality Of Life | E27: QL1.4 | F27: Minimize Noise & Vibration | G27: 12 | H27: Applicable | I27: Improved | J27: 1 | K27: 8.3 | L27: The project includes residential units and commercial spaces, indicating potential noise and vibration concerns. | M27: QA:Likely Yes(Project includes soundproofing measures.) | QB:Insufficient Data(Lack of information on vibration mitigation measures.) | N27: A + B required for Enhanced | O27: Investigate vibration mitigation measures. | P27: Soundproofing documents; Vibration mitigation reports | Q27: 17220 | R27: 2438 | S27: 865.47 | T27: TRUE | U27: FALSE | V27: TRUE
A28: rag | B28: 4 | C28: 00_sample_project | D28: Quality Of Life | E28: QL1.5 | F28: Minimize Light Pollution | G28: 12 | H28: Applicable | I28: Improved | J28: 1 | K28: 8.3 | L28: The project includes exterior lighting, indicating potential light pollution concerns. | M28: QA:Likely Yes(Project includes energy-efficient lighting.) | QB:Insufficient Data(Lack of information on lighting design and controls.) | N28: A + B required for Enhanced | O28: Develop lighting design and control strategy. | P28: Lighting design documents; Control strategy reports | Q28: 17220 | R28: 2438 | S28: 865.47 | T28: TRUE | U28: FALSE | V28: TRUE
A29: rag | B29: 4 | C29: 00_sample_project | D29: Quality Of Life | E29: QL1.6 | F29: Minimize Construction Impacts | G29: 8 | H29: Applicable | I29: Improved | J29: 1 | K29: 12.5 | L29: The project involves construction activities, indicating potential construction impacts. | M29: QA:Likely Yes(Project includes waste management plan.) | QB:Insufficient Data(Lack of information on construction scheduling and phasing.) | N29: A + B required for Enhanced | O29: Develop construction scheduling and phasing plan. | P29: Waste management plan; Construction scheduling documents | Q29: 17220 | R29: 2438 | S29: 865.47 | T29: TRUE | U29: FALSE | V29: TRUE
... A33: rag | B33: 4 | C33: 00_sample_project | D33: Quality Of Life | E33: QL3.1 | F33: Advance Equity & Social Justice | G33: 18 | H33: Applicable | I33: Improved | J33: 3 | K33: 16.7 | L33: The project includes residential units and commercial spaces, indicating potential equity and social justice concerns. | M33: QA:Likely Yes(Project includes community engagement plan.) | QB:Insufficient Data(Lack of information on social justice initiatives.) | N33: A + B required for Enhanced | O33: Investigate social justice initiatives. | P33: Community engagement plan; Social justice reports | Q33: 17220 | R33: 2438 | S33: 865.47 | T33: TRUE | U33: FALSE | V33: TRUE
A34: rag | B34: 4 | C34: 00_sample_project | D34: Quality Of Life | E34: QL3.2 | F34: Preserve Historic & Cultural Resources | G34: 18 | H34: Not Applicable | J34: 0 | K34: 0 | L34: The project does not involve historic or cultural resources. | Q34: 17220 | R34: 2438 | S34: 865.47 | T34: TRUE | U34: FALSE | V34: TRUE
A35: rag | B35: 4 | C35: 00_sample_project | D35: Quality Of Life | E35: QL3.3 | F35: Enhance Views & Local Character | G35: 14 | H35: Applicable | I35: Improved | J35: 1 | K35: 7.1 | L35: The project includes residential units and commercial spaces, indicating potential views and local character concerns. | M35: QA:Likely Yes(Project includes design that respects local character.) | QB:Insufficient Data(Lack of information on view preservation measures.) | N35: A + B required for Enhanced | O35: Investigate view preservation measures. | P35: Design documents; View preservation reports | Q35: 17220 | R35: 2438 | S35: 865.47 | T35: TRUE | U35: FALSE | V35: TRUE
A36: rag | B36: 4 | C36: 00_sample_project | D36: Resource Allocation | E36: RA1.1 | F36: Reduce Materials Use | G36: 12 | H36: Applicable | I36: No Level | J36: 0 | K36: 0 | M36: QA:Insufficient Data(No material takeoff or bill of quantities in the provided PDF) | QB:Insufficient Data(No information on material efficiency strategies) | N36: A + B required for Improved | O36: Develop a material takeoff and bill of quantities; Research material efficiency strategies | P36: Material takeoff and bill of quantities; Material efficiency strategy report | Q36: 17210 | R36: 2585 | S36: 772.29 | T36: TRUE | U36: FALSE | V36: TRUE
A37: rag | B37: 4 | C37: 00_sample_project | D37: Resource Allocation | E37: RA1.2 | F37: Use Recycled Materials | G37: 10 | H37: Applicable | I37: No Level | J37: 0 | K37: 0 | M37: QA:Insufficient Data(No information on recycled material use) | QB:Insufficient Data(No documentation of recycled material sourcing) | N37: A + B required for Improved | O37: Research recycled material options; Develop a plan for sourcing recycled materials | P37: Recycled material specification; Sourcing plan for recycled materials | Q37: 17210 | R37: 2585 | S37: 772.29 | T37: TRUE | U37: FALSE | V37: TRUE
A38: rag | B38: 4 | C38: 00_sample_project | D38: Resource Allocation | E38: RA1.3 | F38: Reduce Operational Waste | G38: 8 | H38: Applicable | I38: No Level | J38: 0 | K38: 0 | M38: QA:Insufficient Data(No information on operational waste reduction strategies) | QB:Insufficient Data(No documentation of waste management plan) | N38: A + B required for Improved | O38: Develop an operational waste reduction strategy; Create a waste management plan | P38: Operational waste reduction strategy report; Waste management plan | Q38: 17210 | R38: 2585 | S38: 772.29 | T38: TRUE | U38: FALSE | V38: TRUE
A39: rag | B39: 4 | C39: 00_sample_project | D39: Resource Allocation | E39: RA1.4 | F39: Reduce Construction Waste | G39: 10 | H39: Applicable | I39: No Level | J39: 0 | K39: 0 | M39: QA:Insufficient Data(No information on construction waste reduction strategies) | QB:Insufficient Data(No documentation of construction waste management plan) | N39: A + B required for Improved | O39: Develop a construction waste reduction strategy; Create a construction waste management plan | P39: Construction waste reduction strategy report; Construction waste management plan | Q39: 17210 | R39: 2585 | S39: 772.29 | T39: TRUE | U39: FALSE | V39: TRUE
A40: rag | B40: 4 | C40: 00_sample_project | D40: Resource Allocation | E40: RA1.5 | F40: Balance Earthwork On Site | G40: 6 | H40: Applicable | I40: No Level | J40: 0 | K40: 0 | M40: QA:Insufficient Data(No information on earthwork balancing strategies) | QB:Insufficient Data(No documentation of earthwork balancing plan) | N40: A + B required for Improved | O40: Develop an earthwork balancing strategy; Create an earthwork balancing plan | P40: Earthwork balancing strategy report; Earthwork balancing plan | Q40: 17210 | R40: 2585 | S40: 772.29 | T40: TRUE | U40: FALSE | V40: TRUE
A41: rag | B41: 4 | C41: 00_sample_project | D41: Resource Allocation | E41: RA2.1 | F41: Reduce Operational Energy Consumption | G41: 20 | H41: Applicable | I41: No Level | J41: 0 | K41: 0 | M41: QA:Insufficient Data(No information on operational energy reduction strategies) | QB:Insufficient Data(No documentation of energy-efficient design) | N41: A + B required for Improved | O41: Develop an operational energy reduction strategy; Create an energy-efficient design plan | P41: Operational energy reduction strategy report; Energy-efficient design plan | Q41: 17210 | R41: 2585 | S41: 772.29 | T41: TRUE | U41: FALSE | V41: TRUE
A42: rag | B42: 4 | C42: 00_sample_project | D42: Resource Allocation | E42: RA2.2 | F42: Reduce Construction Energy Consumption | G42: 12 | H42: Applicable | I42: No Level | J42: 0 | K42: 0 | M42: QA:Insufficient Data(No information on construction energy reduction strategies) | QB:Insufficient Data(No documentation of construction energy management plan) | N42: A + B required for Improved | O42: Develop a construction energy reduction strategy; Create a construction energy management plan | P42: Construction energy reduction strategy report; Construction energy management plan | Q42: 17210 | R42: 2585 | S42: 772.29 | T42: TRUE | U42: FALSE | V42: TRUE
A43: rag | B43: 4 | C43: 00_sample_project | D43: Resource Allocation | E43: RA2.3 | F43: Use Renewable Energy | G43: 10 | H43: Applicable | I43: No Level | J43: 0 | K43: 0 | M43: QA:Insufficient Data(No information on renewable energy sources) | QB:Insufficient Data(No documentation of renewable energy system design) | N43: A + B required for Improved | O43: Research renewable energy options; Develop a plan for integrating renewable energy systems | P43: Renewable energy feasibility study; Renewable energy system design plan | Q43: 17210 | R43: 2585 | S43: 772.29 | T43: TRUE | U43: FALSE | V43: TRUE
A44: rag | B44: 4 | C44: 00_sample_project | D44: Resource Allocation | E44: RA2.4 | F44: Commission and Monitor Energy Systems | G44: 8 | H44: Applicable | I44: No Level | J44: 0 | K44: 0 | M44: QA:Insufficient Data(No information on energy system commissioning) | QB:Insufficient Data(No documentation of energy system monitoring plan) | N44: A + B required for Improved | O44: Develop an energy system commissioning plan; Create an energy system monitoring plan | P44: Energy system commissioning plan; Energy system monitoring plan | Q44: 17210 | R44: 2585 | S44: 772.29 | T44: TRUE | U44: FALSE | V44: TRUE
A45: rag | B45: 4 | C45: 00_sample_project | D45: Resource Allocation | E45: RA3.1 | F45: Preserve Water Resources | G45: 14 | H45: Applicable | I45: No Level | J45: 0 | K45: 0 | M45: QA:Insufficient Data(No information on water conservation strategies) | QB:Insufficient Data(No documentation of water-efficient design) | N45: A + B required for Improved | O45: Develop a water conservation strategy; Create a water-efficient design plan | P45: Water conservation strategy report; Water-efficient design plan | Q45: 17210 | R45: 2585 | S45: 772.29 | T45: TRUE | U45: FALSE | V45: TRUE
A46: rag | B46: 4 | C46: 00_sample_project | D46: Resource Allocation | E46: RA3.2 | F46: Reduce Operational Water Consumption | G46: 12 | H46: Applicable | I46: No Level | J46: 0 | K46: 0 | M46: QA:Insufficient Data(No information on operational water reduction strategies) | QB:Insufficient Data(No documentation of water-efficient fixtures and appliances) | N46: A + B required for Improved | O46: Develop an operational water reduction strategy; Specify water-efficient fixtures and appliances | P46: Operational water reduction strategy report; Water-efficient fixture and appliance specification | Q46: 17210 | R46: 2585 | S46: 772.29 | T46: TRUE | U46: FALSE | V46: TRUE
A47: rag | B47: 4 | C47: 00_sample_project | D47: Resource Allocation | E47: RA3.3 | F47: Reduce Construction Water Consumption | G47: 8 | H47: Applicable | I47: No Level | J47: 0 | K47: 0 | M47: QA:Insufficient Data(No information on construction water reduction strategies) | QB:Insufficient Data(No documentation of construction water management plan) | N47: A + B required for Improved | O47: Develop a construction water reduction strategy; Create a construction water management plan | P47: Construction water reduction strategy report; Construction water management plan | Q47: 17210 | R47: 2585 | S47: 772.29 | T47: TRUE | U47: FALSE | V47: TRUE
A48: rag | B48: 4 | C48: 00_sample_project | D48: Resource Allocation | E48: RA3.4 | F48: Monitor Water Systems | G48: 6 | H48: Applicable | I48: No Level | J48: 0 | K48: 0 | M48: QA:Insufficient Data(No information on water system monitoring) | QB:Insufficient Data(No documentation of water system monitoring plan) | N48: A + B required for Improved | O48: Develop a water system monitoring plan; Specify water metering and monitoring equipment | P48: Water system monitoring plan; Water metering and monitoring equipment specification | Q48: 17210 | R48: 2585 | S48: 772.29 | T48: TRUE | U48: FALSE | V48: TRUE

Sheet RAG Run 5
A1: Arm | B1: Run | C1: File | D1: Category | E1: Credit ID | F1: Credit Name | G1: Max Points | H1: Applicability | I1: Estimated Level | J1: Estimated Points | K1: % Achieved | L1: Justification | M1: Questions Summary | N1: Level Guide Reference | O1: Concept Phase Actions | P1: Documentation Needed | Q1: Input Tokens | R1: Output Tokens | S1: Elapsed (s) | T1: Valid JSON | U1: Truncated | V1: Success
A2: rag | B2: 5 | C2: 00_sample_project | D2: Climate And Resilience | E2: CR2.1 | F2: Avoid Unsuitable Development | G2: 14 | H2: APPLICABLE | I2: No Level | J2: 0 | K2: 0 | L2: The project is located in Brownsville, PA, and the PDF metadata does not indicate that it avoids unsuitable development. | M2: QA:Insufficient Data(No information on site selection criteria) | QB:Insufficient Data(No information on environmental impact assessment) | N2: A + B required for Improved | O2: Conduct site selection criteria analysis; Perform environmental impact assessment | P2: Site selection report; Environmental impact assessment report | Q2: 17617 | R2: 1741 | S2: 515.75 | T2: TRUE | U2: FALSE | V2: TRUE
A3: rag | B3: 5 | C3: 00_sample_project | D3: Climate And Resilience | E3: CR2.2 | F3: Assess Climate Change Vulnerability | G3: 20 | H3: APPLICABLE | I3: No Level | J3: 0 | K3: 0 | L3: The project is located in Brownsville, PA, and climate change vulnerability assessment is relevant to the project. | M3: QA:Insufficient Data(No information on climate change threats) | QB:Insufficient Data(No information on project vulnerability) | QC:Insufficient Data(No information on infrastructure system vulnerability) | QD:Insufficient Data(No information on community vulnerability) | QE:Insufficient Data(No information on shared climate threat findings) | N3: A + B required for Improved | O3: Conduct climate change vulnerability assessment; Identify project and infrastructure system vulnerabilities | P3: Climate change vulnerability assessment report; Project and infrastructure system vulnerability reports | Q3: 17617 | R3: 1741 | S3: 515.75 | T3: TRUE | U3: FALSE | V3: TRUE
A4: rag | B4: 5 | C4: 00_sample_project | D4: Climate And Resilience | E4: CR2.3 | F4: Evaluate Risk and Resilience | G4: 26 | H4: APPLICABLE | I4: No Level | J4: 0 | K4: 0 | L4: The project is located in Brownsville, PA, and risk and resilience evaluation is relevant to the project. | M4: QA:Insufficient Data(No information on risk assessment scope) | QB:Insufficient Data(No information on critical functions and dependencies) | QC:Insufficient Data(No information on threats or hazards) | QD:Insufficient Data(No information on vulnerabilities of critical functions and dependencies) | QE:Insufficient Data(No information on risk evaluation methodology) | QF:Insufficient Data(No information on stakeholder participation in risk evaluation) | N4: A + B + C + D + E required for Improved | O4: Conduct risk assessment; Identify critical functions and dependencies; Evaluate risks | P4: Risk assessment report; Critical functions and dependencies report; Risk evaluation methodology report | Q4: 17617 | R4: 1741 | S4: 515.75 | T4: TRUE | U4: FALSE | V4: TRUE
A5: rag | B5: 5 | C5: 00_sample_project | D5: Climate And Resilience | E5: CR2.4 | F5: Establish Resilience Goals and Strategies | G5: 20 | H5: APPLICABLE | I5: No Level | J5: 0 | K5: 0 | L5: The project is located in Brownsville, PA, and establishing resilience goals and strategies is relevant to the project. | M5: QA:Insufficient Data(No information on project performance goals) | QB:Insufficient Data(No information on risk management strategies) | QC:Insufficient Data(No information on stakeholder engagement in resilience goal development) | QD:Insufficient Data(No information on community resilience goals) | N5: A + B required for Enhanced | O5: Develop project performance goals; Establish risk management strategies; Engage stakeholders in resilience goal development | P5: Project performance goals report; Risk management strategies report; Stakeholder engagement report | Q5: 17617 | R5: 1741 | S5: 515.75 | T5: TRUE | U5: FALSE | V5: TRUE
A6: rag | B6: 5 | C6: 00_sample_project | D6: Climate And Resilience | E6: CR2.5 | F6: Maximize Resilience | G6: 26 | H6: APPLICABLE | I6: No Level | J6: 0 | K6: 0 | L6: The project is located in Brownsville, PA, and maximizing resilience is relevant to the project. | M6: QA:Insufficient Data(No information on resilience goals and strategies) | QB:Insufficient Data(No information on implementation of resilience strategies) | QC:Insufficient Data(No information on monitoring and review of resilience strategies) | QD:Insufficient Data(No information on incorporation of resilience goals into operations and maintena) | QE:Insufficient Data(No information on methods for measuring resilience performance) | N6: A + B required for Improved | O6: Develop resilience goals and strategies; Implement resilience strategies; Monitor and review resilience strategies | P6: Resilience goals and strategies report; Implementation plan for resilience strategies; Monitoring and review plan for resilience strategies | Q6: 17617 | R6: 1741 | S6: 515.75 | T6: TRUE | U6: FALSE | V6: TRUE
A7: rag | B7: 5 | C7: 00_sample_project | D7: Climate And Resilience | E7: CR2.6 | F7: Improve Infrastructure Integration | G7: 18 | H7: APPLICABLE | I7: No Level | J7: 0 | K7: 0 | L7: The project is located in Brownsville, PA, and improving infrastructure integration is relevant to the project. | M7: QA:Insufficient Data(No information on infrastructure system connections) | QB:Insufficient Data(No information on benefits of improved integration) | N7: A + B required for Improved | O7: Analyze infrastructure system connections; Evaluate benefits of improved integration | P7: Infrastructure system connections report; Benefits of improved integration report | Q7: 17617 | R7: 1741 | S7: 515.75 | T7: TRUE | U7: FALSE | V7: TRUE
A8: rag | B8: 5 | C8: 00_sample_project | D8: Leadership | E8: LD1.1 | F8: Provide Effective Leadership and Commitment | G8: 10 | H8: Applicable | I8: Improved | J8: 2 | K8: 20 | M8: QA:Likely Yes(Project team includes multiple stakeholders (Cartesian Inverse, PA; Etienne Oise) | QB:Insufficient Data(No information on sustainability goals or targets) | N8: A + B required for Enhanced | O8: Develop sustainability goals and targets | P8: Sustainability management plan; Stakeholder engagement records | Q8: 17191 | R8: 1946 | S8: 535.67 | T8: TRUE | U8: FALSE | V8: TRUE
A9: rag | B9: 5 | C9: 00_sample_project | D9: Leadership | E9: LD1.2 | F9: Foster Collaboration and Teamwork | G9: 8 | H9: Applicable | I9: Improved | J9: 2 | K9: 25 | M9: QA:Likely Yes(Multiple stakeholders involved in project team (Cartesian Inverse, PA; Etienne O) | QB:Insufficient Data(No information on collaboration tools or processes) | N9: A + B required for Enhanced | O9: Establish collaboration tools and processes | P9: Collaboration plan; Meeting minutes | Q9: 17191 | R9: 1946 | S9: 535.67 | T9: TRUE | U9: FALSE | V9: TRUE
A10: rag | B10: 5 | C10: 00_sample_project | D10: Leadership | E10: LD1.3 | F10: Encourage Public Engagement and Participation | G10: 8 | H10: Applicable | I10: No Level | J10: 0 | K10: 0 | M10: QA:Insufficient Data(No information on public engagement or participation) | QB:Insufficient Data(No information on community outreach or education) | N10: A + B required for Improved | O10: Develop public engagement and participation plan | P10: Public engagement plan; Community outreach records | Q10: 17191 | R10: 1946 | S10: 535.67 | T10: TRUE | U10: FALSE | V10: TRUE
A11: rag | B11: 5 | C11: 00_sample_project | D11: Leadership | E11: LD1.4 | F11: Pursue Byproduct Synergies | G11: 10 | H11: Applicable | I11: No Level | J11: 0 | K11: 0 | M11: QA:Insufficient Data(No information on byproduct synergies) | QB:Insufficient Data(No information on waste reduction or material reuse) | N11: A + B required for Improved | O11: Investigate byproduct synergies opportunities | P11: Byproduct synergy plan; Waste reduction records | Q11: 17191 | R11: 1946 | S11: 535.67 | T11: TRUE | U11: FALSE | V11: TRUE
A12: rag | B12: 5 | C12: 00_sample_project | D12: Leadership | E12: LD2.1 | F12: Establish a Sustainability Management Plan | G12: 14 | H12: Applicable | I12: No Level | J12: 0 | K12: 0 | M12: QA:Insufficient Data(No information on sustainability management plan) | QB:Insufficient Data(No information on monitoring or reporting processes) | N12: A + B required for Improved | O12: Develop sustainability management plan | P12: Sustainability management plan; Monitoring and reporting records | Q12: 17191 | R12: 1946 | S12: 535.67 | T12: TRUE | U12: FALSE | V12: TRUE
A13: rag | B13: 5 | C13: 00_sample_project | D13: Leadership | E13: LD2.2 | F13: Plan for Sustainable Communities | G13: 12 | H13: Applicable | I13: No Level | J13: 0 | K13: 0 | M13: QA:Insufficient Data(No information on community planning or engagement) | QB:Insufficient Data(No information on social or economic benefits) | N13: A + B required for Improved | O13: Develop community planning and engagement plan | P13: Community planning documents; Social and economic benefit records | Q13: 17191 | R13: 1946 | S13: 535.67 | T13: TRUE | U13: FALSE | V13: TRUE
A14: rag | B14: 5 | C14: 00_sample_project | D14: Leadership | E14: LD2.3 | F14: Conduct a Life-Cycle Economic Evaluation | G14: 10 | H14: Applicable | I14: No Level | J14: 0 | K14: 0 | M14: QA:Insufficient Data(No information on life-cycle economic evaluation) | QB:Insufficient Data(No information on cost-benefit analysis or return on investment) | N14: A + B required for Improved | O14: Conduct life-cycle economic evaluation | P14: Life-cycle economic evaluation report; Cost-benefit analysis records | Q14: 17191 | R14: 1946 | S14: 535.67 | T14: TRUE | U14: FALSE | V14: TRUE
A15: rag | B15: 5 | C15: 00_sample_project | D15: Leadership | E15: LD3.1 | F15: Develop a Construction Management Plan | G15: 8 | H15: Applicable | I15: No Level | J15: 0 | K15: 0 | M15: QA:Insufficient Data(No information on construction management plan) | QB:Insufficient Data(No information on waste reduction or material reuse during construction) | N15: A + B required for Improved | O15: Develop construction management plan | P15: Construction management plan; Waste reduction records | Q15: 17191 | R15: 1946 | S15: 535.67 | T15: TRUE | U15: FALSE | V15: TRUE
A16: rag | B16: 5 | C16: 00_sample_project | D16: Leadership | E16: LD3.2 | F16: Implement a Quality Control Process | G16: 8 | H16: Applicable | I16: No Level | J16: 0 | K16: 0 | M16: QA:Insufficient Data(No information on quality control process) | QB:Insufficient Data(No information on testing or inspection procedures) | N16: A + B required for Improved | O16: Develop quality control process | P16: Quality control plan; Testing and inspection records | Q16: 17191 | R16: 1946 | S16: 535.67 | T16: TRUE | U16: FALSE | V16: TRUE
A17: rag | B17: 5 | C17: 00_sample_project | D17: Leadership | E17: LD3.3 | F17: Conduct a Life-Cycle Assessment | G17: 12 | H17: Applicable | I17: No Level | J17: 0 | K17: 0 | M17: QA:Insufficient Data(No information on life-cycle assessment) | QB:Insufficient Data(No information on environmental or social impacts) | N17: A + B required for Improved | O17: Conduct life-cycle assessment | P17: Life-cycle assessment report; Environmental and social impact records | Q17: 17191 | R17: 1946 | S17: 535.67 | T17: TRUE | U17: FALSE | V17: TRUE
A18: rag | B18: 5 | C18: 00_sample_project | D18: Natural World | E18: NW1.1 | F18: Conserve Natural Areas | G18: 14 | H18: Applicable | I18: Improved | J18: 2 | K18: 14.3 | L18: The project is located in Brownsville, PA, and has a site plan, indicating potential natural areas to conserve. | M18: QA:Insufficient Data(No information on natural area conservation) | QB:Insufficient Data(No information on habitat preservation) | N18: A + B required for Improved | O18: Conduct site analysis to identify natural areas; Develop conservation plan | P18: Site analysis report; Conservation plan | Q18: 17916 | R18: 1311 | S18: 384.86 | T18: TRUE | U18: FALSE | V18: TRUE
A19: rag | B19: 5 | C19: 00_sample_project | D19: Natural World | E19: NW1.2 | F19: Provide Wetland and Surface Water Buffers | G19: 10 | H19: Applicable | I19: Improved | J19: 2 | K19: 20 | L19: The project has a site plan, indicating potential wetlands or surface water to buffer. | M19: QA:Insufficient Data(No information on wetland or surface water buffers) | QB:Insufficient Data(No information on buffer zone size) | N19: A + B required for Improved | O19: Conduct site analysis to identify wetlands or surface water; Develop buffer zone plan | P19: Site analysis report; Buffer zone plan | Q19: 17916 | R19: 1311 | S19: 384.86 | T19: TRUE | U19: FALSE | V19: TRUE
A20: rag | B20: 5 | C20: 00_sample_project | D20: Natural World | E20: NW2.2 | F20: Manage Stormwater | G20: 24 | H20: Applicable | I20: Improved | J20: 2 | K20: 8.3 | L20: The project has a site plan, indicating potential stormwater management needs. | M20: QA:Insufficient Data(No information on stormwater management) | QB:Insufficient Data(No information on rate or quantity of runoff) | N20: A + B required for Improved | O20: Conduct stormwater analysis; Develop stormwater management plan | P20: Stormwater analysis report; Stormwater management plan | Q20: 17916 | R20: 1311 | S20: 384.86 | T20: TRUE | U20: FALSE | V20: TRUE
A21: rag | B21: 5 | C21: 00_sample_project | D21: Natural World | E21: NW2.4 | F21: Protect Surface and Groundwater Quality | G21: 14 | H21: Applicable | I21: Improved | J21: 1 | K21: 7.1 | L21: The project has a site plan, indicating potential surface or groundwater quality concerns. | M21: QA:Insufficient Data(No information on surface or groundwater quality protection) | QB:Insufficient Data(No information on pollution control measures) | N21: A + B required for Improved | O21: Conduct water quality analysis; Develop pollution control plan | P21: Water quality analysis report; Pollution control plan | Q21: 17916 | R21: 1311 | S21: 384.86 | T21: TRUE | U21: FALSE | V21: TRUE
A22: rag | B22: 5 | C22: 00_sample_project | D22: Natural World | E22: NW3.3 | F22: Maintain Floodplain Functions | G22: 14 | H22: Applicable | I22: Improved | J22: 1 | K22: 7.1 | L22: The project is located in a floodplain, as indicated by the site plan. | M22: QA:Insufficient Data(No information on floodplain functions) | QB:Insufficient Data(No information on vegetated zones preservation) | N22: A + B required for Improved | O22: Conduct floodplain analysis; Develop floodplain management plan | P22: Floodplain analysis report; Floodplain management plan | Q22: 17916 | R22: 1311 | S22: 384.86 | T22: TRUE | U22: FALSE | V22: TRUE
A23: rag | B23: 5 | C23: 00_sample_project | D23: Natural World | E23: NW3.5 | F23: Protect Soil Health | G23: 10 | H23: Applicable | I23: Improved | J23: 1 | K23: 10 | L23: The project has a site plan, indicating potential soil health concerns. | M23: QA:Insufficient Data(No information on soil health protection) | QB:Insufficient Data(No information on erosion control measures) | N23: A + B required for Improved | O23: Conduct soil analysis; Develop erosion control plan | P23: Soil analysis report; Erosion control plan | Q23: 17916 | R23: 1311 | S23: 384.86 | T23: TRUE | U23: FALSE | V23: TRUE
A24: rag | B24: 5 | C24: 00_sample_project | D24: Quality Of Life | E24: QL1.1 | F24: Improve Community Quality of Life | G24: 26 | H24: Applicable | I24: Improved | J24: 2 | K24: 7.7 | L24: The project is a mixed-use development with residential, commercial, and community spaces, indicating potential for community quality of life improvements. | M24: QA:Likely Yes(Project includes live/work units and community spaces.) | QB:Insufficient Data(Lack of information on community engagement and feedback mechanisms.) | N24: A + B required for Enhanced | O24: Engage with local stakeholders to understand community needs and priorities. | P24: Community engagement records; Stakeholder feedback mechanisms | Q24: 17220 | R24: 2492 | S24: 782.95 | T24: TRUE | U24: FALSE | V24: TRUE
A25: rag | B25: 5 | C25: 00_sample_project | D25: Quality Of Life | E25: QL1.2 | F25: Enhance Public Health & Safety | G25: 20 | H25: Applicable | I25: Improved | J25: 2 | K25: 10 | L25: The project includes residential and commercial spaces, which can impact public health and safety. | M25: QA:Likely Yes(Project includes fire resistive walls and smoke barriers.) | QB:Insufficient Data(Lack of information on emergency response planning and evacuation procedures.) | N25: A + B required for Enhanced | O25: Develop emergency response plan and evacuation procedures. | P25: Emergency response plan; Evacuation procedure documents | Q25: 17220 | R25: 2492 | S25: 782.95 | T25: TRUE | U25: FALSE | V25: TRUE
A26: rag | B26: 5 | C26: 00_sample_project | D26: Quality Of Life | E26: QL1.3 | F26: Improve Construction Safety | G26: 14 | H26: Applicable | I26: Improved | J26: 2 | K26: 14.3 | L26: The project involves construction activities that can impact worker safety. | M26: QA:Likely Yes(Project includes safety protocols for workers.) | QB:Insufficient Data(Lack of information on worker training programs and site-specific hazard assessm) | N26: A + B required for Enhanced | O26: Develop worker training programs and conduct site-specific hazard assessments. | P26: Worker training records; Site-specific hazard assessment reports | Q26: 17220 | R26: 2492 | S26: 782.95 | T26: TRUE | U26: FALSE | V26: TRUE
A27: rag | B27: 5 | C27: 00_sample_project | D27: Quality Of Life | E27: QL1.4 | F27: Minimize Noise & Vibration | G27: 12 | H27: Applicable | I27: Improved | J27: 1 | K27: 8.3 | L27: The project includes residential and commercial spaces that can be impacted by noise and vibration. | M27: QA:Likely Yes(Project includes soundproofing measures.) | QB:Insufficient Data(Lack of information on vibration mitigation strategies.) | N27: A + B required for Enhanced | O27: Investigate vibration mitigation strategies and implement soundproofing measures. | P27: Soundproofing design documents; Vibration mitigation strategy reports | Q27: 17220 | R27: 2492 | S27: 782.95 | T27: TRUE | U27: FALSE | V27: TRUE
A28: rag | B28: 5 | C28: 00_sample_project | D28: Quality Of Life | E28: QL1.5 | F28: Minimize Light Pollution | G28: 12 | H28: Applicable | I28: Improved | J28: 1 | K28: 8.3 | L28: The project includes exterior lighting that can contribute to light pollution. | M28: QA:Likely Yes(Project includes energy-efficient lighting.) | QB:Insufficient Data(Lack of information on lighting design and controls.) | N28: A + B required for Enhanced | O28: Develop lighting design and control strategies to minimize light pollution. | P28: Lighting design documents; Control strategy reports | Q28: 17220 | R28: 2492 | S28: 782.95 | T28: TRUE | U28: FALSE | V28: TRUE
A29: rag | B29: 5 | C29: 00_sample_project | D29: Quality Of Life | E29: QL1.6 | F29: Minimize Construction Impacts | G29: 8 | H29: Applicable | I29: Improved | J29: 1 | K29: 12.5 | L29: The project involves construction activities that can impact the surrounding environment. | M29: QA:Likely Yes(Project includes measures to reduce waste and pollution.) | QB:Insufficient Data(Lack of information on construction sequencing and scheduling.) | N29: A + B required for Enhanced | O29: Develop construction sequencing and scheduling strategies to minimize impacts. | P29: Construction sequencing documents; Scheduling reports | Q29: 17220 | R29: 2492 | S29: 782.95 | T29: TRUE | U29: FALSE | V29: TRUE
... A33: rag | B33: 5 | C33: 00_sample_project | D33: Quality Of Life | E33: QL3.1 | F33: Advance Equity & Social Justice | G33: 18 | H33: Applicable | I33: Improved | J33: 3 | K33: 16.7 | L33: The project includes community spaces that can impact social justice and equity. | M33: QA:Likely Yes(Project includes community engagement and outreach programs.) | QB:Insufficient Data(Lack of information on diversity and inclusion strategies.) | N33: A + B required for Enhanced | O33: Develop diversity and inclusion strategies. | P33: Diversity and inclusion policy documents; Community engagement reports | Q33: 17220 | R33: 2492 | S33: 782.95 | T33: TRUE | U33: FALSE | V33: TRUE
A34: rag | B34: 5 | C34: 00_sample_project | D34: Quality Of Life | E34: QL3.2 | F34: Preserve Historic & Cultural Resources | G34: 18 | H34: Not Applicable | J34: 0 | K34: 0 | L34: The project does not involve historic or cultural resources. | Q34: 17220 | R34: 2492 | S34: 782.95 | T34: TRUE | U34: FALSE | V34: TRUE
A35: rag | B35: 5 | C35: 00_sample_project | D35: Quality Of Life | E35: QL3.3 | F35: Enhance Views & Local Character | G35: 14 | H35: Applicable | I35: Improved | J35: 1 | K35: 7.1 | L35: The project includes public spaces that can impact views and local character. | M35: QA:Likely Yes(Project includes design elements that enhance local character.) | QB:Insufficient Data(Lack of information on view preservation strategies.) | N35: A + B required for Enhanced | O35: Investigate view preservation strategies. | P35: View preservation strategy reports; Local character design documents | Q35: 17220 | R35: 2492 | S35: 782.95 | T35: TRUE | U35: FALSE | V35: TRUE
A36: rag | B36: 5 | C36: 00_sample_project | D36: Resource Allocation | E36: RA1.1 | F36: Reduce Materials Use | G36: 12 | H36: Applicable | I36: No Level | J36: 0 | K36: 0 | M36: QA:Insufficient Data(No material takeoff or bill of quantities in the model) | QB:Insufficient Data(No information on recycled content or sustainable materials) | N36: A + B required for Improved | O36: Develop a material takeoff and bill of quantities; Research sustainable materials and recycled content options | P36: Material takeoff and bill of quantities; Sustainable materials and recycled content research | Q36: 17210 | R36: 2648 | S36: 821.87 | T36: TRUE | U36: FALSE | V36: TRUE
A37: rag | B37: 5 | C37: 00_sample_project | D37: Resource Allocation | E37: RA1.2 | F37: Use Recycled Materials | G37: 10 | H37: Applicable | I37: No Level | J37: 0 | K37: 0 | M37: QA:Insufficient Data(No information on recycled materials used in the project) | QB:Insufficient Data(No documentation of recycled material quantities) | N37: A + B required for Improved | O37: Research recycled material options; Develop a plan for incorporating recycled materials into the project | P37: Recycled material research; Plan for incorporating recycled materials | Q37: 17210 | R37: 2648 | S37: 821.87 | T37: TRUE | U37: FALSE | V37: TRUE
A38: rag | B38: 5 | C38: 00_sample_project | D38: Resource Allocation | E38: RA1.3 | F38: Reduce Operational Waste | G38: 8 | H38: Applicable | I38: No Level | J38: 0 | K38: 0 | M38: QA:Insufficient Data(No information on operational waste reduction strategies) | QB:Insufficient Data(No documentation of waste reduction goals or targets) | N38: A + B required for Improved | O38: Develop a plan for reducing operational waste; Research waste reduction strategies and technologies | P38: Operational waste reduction plan; Waste reduction goals or targets | Q38: 17210 | R38: 2648 | S38: 821.87 | T38: TRUE | U38: FALSE | V38: TRUE
A39: rag | B39: 5 | C39: 00_sample_project | D39: Resource Allocation | E39: RA1.4 | F39: Reduce Construction Waste | G39: 10 | H39: Applicable | I39: No Level | J39: 0 | K39: 0 | M39: QA:Insufficient Data(No information on construction waste reduction strategies) | QB:Insufficient Data(No documentation of waste reduction goals or targets) | N39: A + B required for Improved | O39: Develop a plan for reducing construction waste; Research waste reduction strategies and technologies | P39: Construction waste reduction plan; Waste reduction goals or targets | Q39: 17210 | R39: 2648 | S39: 821.87 | T39: TRUE | U39: FALSE | V39: TRUE
A40: rag | B40: 5 | C40: 00_sample_project | D40: Resource Allocation | E40: RA1.5 | F40: Balance Earthwork On Site | G40: 6 | H40: Applicable | I40: No Level | J40: 0 | K40: 0 | M40: QA:Insufficient Data(No information on earthwork balancing strategies) | QB:Insufficient Data(No documentation of earthwork balancing goals or targets) | N40: A + B required for Improved | O40: Develop a plan for balancing earthwork on site; Research earthwork balancing strategies and technologies | P40: Earthwork balancing plan; Earthwork balancing goals or targets | Q40: 17210 | R40: 2648 | S40: 821.87 | T40: TRUE | U40: FALSE | V40: TRUE
A41: rag | B41: 5 | C41: 00_sample_project | D41: Resource Allocation | E41: RA2.1 | F41: Reduce Operational Energy Consumption | G41: 20 | H41: Applicable | I41: No Level | J41: 0 | K41: 0 | M41: QA:Insufficient Data(No information on operational energy consumption reduction strategies) | QB:Insufficient Data(No documentation of energy reduction goals or targets) | N41: A + B required for Improved | O41: Develop a plan for reducing operational energy consumption; Research energy reduction strategies and technologies | P41: Operational energy consumption reduction plan; Energy reduction goals or targets | Q41: 17210 | R41: 2648 | S41: 821.87 | T41: TRUE | U41: FALSE | V41: TRUE
A42: rag | B42: 5 | C42: 00_sample_project | D42: Resource Allocation | E42: RA2.2 | F42: Reduce Construction Energy Consumption | G42: 12 | H42: Applicable | I42: No Level | J42: 0 | K42: 0 | M42: QA:Insufficient Data(No information on construction energy consumption reduction strategies) | QB:Insufficient Data(No documentation of energy reduction goals or targets) | N42: A + B required for Improved | O42: Develop a plan for reducing construction energy consumption; Research energy reduction strategies and technologies | P42: Construction energy consumption reduction plan; Energy reduction goals or targets | Q42: 17210 | R42: 2648 | S42: 821.87 | T42: TRUE | U42: FALSE | V42: TRUE
A43: rag | B43: 5 | C43: 00_sample_project | D43: Resource Allocation | E43: RA2.3 | F43: Use Renewable Energy | G43: 10 | H43: Applicable | I43: No Level | J43: 0 | K43: 0 | M43: QA:Insufficient Data(No information on renewable energy sources) | QB:Insufficient Data(No documentation of renewable energy goals or targets) | N43: A + B required for Improved | O43: Research renewable energy sources; Develop a plan for incorporating renewable energy into the project | P43: Renewable energy research; Plan for incorporating renewable energy | Q43: 17210 | R43: 2648 | S43: 821.87 | T43: TRUE | U43: FALSE | V43: TRUE
A44: rag | B44: 5 | C44: 00_sample_project | D44: Resource Allocation | E44: RA2.4 | F44: Commission and Monitor Energy Systems | G44: 8 | H44: Applicable | I44: No Level | J44: 0 | K44: 0 | M44: QA:Insufficient Data(No information on energy system commissioning and monitoring) | QB:Insufficient Data(No documentation of energy system performance goals or targets) | N44: A + B required for Improved | O44: Develop a plan for commissioning and monitoring energy systems; Research energy system performance metrics and benchmarks | P44: Energy system commissioning and monitoring plan; Energy system performance goals or targets | Q44: 17210 | R44: 2648 | S44: 821.87 | T44: TRUE | U44: FALSE | V44: TRUE
A45: rag | B45: 5 | C45: 00_sample_project | D45: Resource Allocation | E45: RA3.1 | F45: Preserve Water Resources | G45: 14 | H45: Applicable | I45: No Level | J45: 0 | K45: 0 | M45: QA:Insufficient Data(No information on water conservation strategies) | QB:Insufficient Data(No documentation of water reduction goals or targets) | N45: A + B required for Improved | O45: Develop a plan for preserving water resources; Research water conservation strategies and technologies | P45: Water preservation plan; Water reduction goals or targets | Q45: 17210 | R45: 2648 | S45: 821.87 | T45: TRUE | U45: FALSE | V45: TRUE
A46: rag | B46: 5 | C46: 00_sample_project | D46: Resource Allocation | E46: RA3.2 | F46: Reduce Operational Water Consumption | G46: 12 | H46: Applicable | I46: No Level | J46: 0 | K46: 0 | M46: QA:Insufficient Data(No information on operational water consumption reduction strategies) | QB:Insufficient Data(No documentation of water reduction goals or targets) | N46: A + B required for Improved | O46: Develop a plan for reducing operational water consumption; Research water reduction strategies and technologies | P46: Operational water consumption reduction plan; Water reduction goals or targets | Q46: 17210 | R46: 2648 | S46: 821.87 | T46: TRUE | U46: FALSE | V46: TRUE
A47: rag | B47: 5 | C47: 00_sample_project | D47: Resource Allocation | E47: RA3.3 | F47: Reduce Construction Water Consumption | G47: 10 | H47: Applicable | I47: No Level | J47: 0 | K47: 0 | M47: QA:Insufficient Data(No information on construction water consumption reduction strategies) | QB:Insufficient Data(No documentation of water reduction goals or targets) | N47: A + B required for Improved | O47: Develop a plan for reducing construction water consumption; Research water reduction strategies and technologies | P47: Construction water consumption reduction plan; Water reduction goals or targets | Q47: 17210 | R47: 2648 | S47: 821.87 | T47: TRUE | U47: FALSE | V47: TRUE
A48: rag | B48: 5 | C48: 00_sample_project | D48: Resource Allocation | E48: RA3.4 | F48: Monitor Water Systems | G48: 8 | H48: Applicable | I48: No Level | J48: 0 | K48: 0 | M48: QA:Insufficient Data(No information on water system monitoring) | QB:Insufficient Data(No documentation of water system performance goals or targets) | N48: A + B required for Improved | O48: Develop a plan for monitoring water systems; Research water system performance metrics and benchmarks | P48: Water system monitoring plan; Water system performance goals or targets | Q48: 17210 | R48: 2648 | S48: 821.87 | T48: TRUE | U48: FALSE | V48: TRUE

Sheet Zero Shot Run 1
A1: Arm | B1: Run | C1: File | D1: Category | E1: Credit ID | F1: Credit Name | G1: Max Points | H1: Applicability | I1: Estimated Level | J1: Estimated Points | K1: % Achieved | L1: Justification | M1: Questions Summary | N1: Level Guide Reference | O1: Concept Phase Actions | P1: Documentation Needed | Q1: Input Tokens | R1: Output Tokens | S1: Elapsed (s) | T1: Valid JSON | U1: Truncated | V1: Success
A2: zero_shot | B2: 1 | C2: 00_sample_project | D2: Climate And Resilience | E2: CR1.1 | F2: Reduce Net Embodied Carbon | H2: Applicable | I2: No Level | J2: 0 | M2: QA:Insufficient Data(No embodied carbon assessment in PDF metadata) | QB:Insufficient Data(No calculation of primary contributors to overall embodied carbon in PDF metadat) | QC:Insufficient Data(No information on reduction of net embodied carbon in PDF metadata) | N2: A + B + C required for Improved | O2: Conduct embodied carbon assessment; Calculate primary contributors to overall embodied carbon | P2: Embodied carbon assessment report; Calculation of primary contributors to overall embodied carbon | Q2: 22526 | R2: 2626 | S2: 1278.94 | T2: TRUE | U2: FALSE | V2: TRUE
A3: zero_shot | B3: 1 | C3: 00_sample_project | D3: Climate And Resilience | E3: CR1.2 | F3: Reduce Greenhouse Gas Emissions | H3: Applicable | I3: No Level | J3: 0 | M3: QA:Insufficient Data(No information on reduction of greenhouse gas emissions in PDF metadata) | QB:Insufficient Data(No calculation and reporting of annual greenhouse gas emissions in PDF metadata) | N3: A + B required for Improved | O3: Conduct greenhouse gas emissions assessment; Calculate and report annual greenhouse gas emissions | P3: Greenhouse gas emissions assessment report; Calculation and reporting of annual greenhouse gas emissions | Q3: 22526 | R3: 2626 | S3: 1278.94 | T3: TRUE | U3: FALSE | V3: TRUE
A4: zero_shot | B4: 1 | C4: 00_sample_project | D4: Climate And Resilience | E4: CR1.3 | F4: Reduce Air Pollutant Emissions | H4: Applicable | I4: No Level | J4: 0 | M4: QA:Insufficient Data(No information on meeting minimum air quality standards in PDF metadata) | QB:Insufficient Data(No information on reduction of air pollutant emissions in PDF metadata) | QC:Insufficient Data(No information on ongoing monitoring and management of direct air pollutant emis) | QD:Insufficient Data(No assessment of materiality of volatile organic compounds in PDF metadata) | QE:Insufficient Data(No information on removal of existing air pollutant sources in PDF metadata) | N4: A + B required for Improved | O4: Conduct air pollutant emissions assessment; Implement strategies to reduce air pollutant emissions | P4: Air pollutant emissions assessment report; Implementation plan for reducing air pollutant emissions | Q4: 22526 | R4: 2626 | S4: 1278.94 | T4: TRUE | U4: FALSE | V4: TRUE
A5: zero_shot | B5: 1 | C5: 00_sample_project | D5: Climate And Resilience | E5: CR2.1 | F5: Avoid Unsuitable Development | H5: Applicable | I5: No Level | J5: 0 | M5: QA:Insufficient Data(No information on identification of potential siting hazards in PDF metadata) | QB:Insufficient Data(No information on consideration of siting and project alternatives in PDF metada) | QC:Insufficient Data(No information on implementation of strategies to mitigate site hazards in PDF m) | QD:Insufficient Data(No information on chosen project and site resulting in lowest exposure to site h) | QE:Insufficient Data(No information on intentional avoidance of known site hazards in PDF metadata) | QF:Insufficient Data(No information on removal or modification of structures subject to frequent dama) | N5: A + B required for Improved | O5: Conduct siting hazard assessment; Consider siting and project alternatives | P5: Siting hazard assessment report; Consideration of siting and project alternatives | Q5: 22526 | R5: 2626 | S5: 1278.94 | T5: TRUE | U5: FALSE | V5: TRUE
A6: zero_shot | B6: 1 | C6: 00_sample_project | D6: Climate And Resilience | E6: CR2.2 | F6: Assess Climate Change Vulnerability | H6: Applicable | I6: No Level | J6: 0 | M6: QA:Insufficient Data(No information on determination of climate change threats in PDF metadata) | QB:Insufficient Data(No information on determination of vulnerability to climate change threats in PD) | QC:Insufficient Data(No information on determination of infrastructure system vulnerability to climat) | QD:Insufficient Data(No information on determination of community vulnerability to climate change thr) | QE:Insufficient Data(No information on sharing of climate threat findings in PDF metadata) | N6: A + B required for Improved | O6: Conduct climate change vulnerability assessment; Determine vulnerability to climate change threats | P6: Climate change vulnerability assessment report; Vulnerability determination | Q6: 22526 | R6: 2626 | S6: 1278.94 | T6: TRUE | U6: FALSE | V6: TRUE
A7: zero_shot | B7: 1 | C7: 00_sample_project | D7: Climate And Resilience | E7: CR2.3 | F7: Evaluate Risk and Resilience | H7: Applicable | I7: No Level | J7: 0 | M7: QA:Insufficient Data(No information on risk assessment in PDF metadata) | QB:Insufficient Data(No information on identification of critical functions and dependencies in PDF m) | QC:Insufficient Data(No information on identification of threats or hazards in PDF metadata) | QD:Insufficient Data(No information on identification of vulnerabilities in PDF metadata) | QE:Insufficient Data(No information on evaluation of risks in PDF metadata) | QF:Insufficient Data(No information on participation of owner and stakeholders in risk evaluation in ) | N7: A + B + C + D + E required for Conserving | O7: Conduct risk assessment; Identify critical functions and dependencies | P7: Risk assessment report; Identification of critical functions and dependencies | Q7: 22526 | R7: 2626 | S7: 1278.94 | T7: TRUE | U7: FALSE | V7: TRUE
A8: zero_shot | B8: 1 | C8: 00_sample_project | D8: Climate And Resilience | E8: CR2.4 | F8: Establish Resilience Goals and Strategies | H8: Applicable | I8: No Level | J8: 0 | M8: QA:Insufficient Data(No information on identification of project performance goals in PDF metadata) | QB:Insufficient Data(No information on development of risk management strategies in PDF metadata) | QC:Insufficient Data(No information on engagement of key stakeholders in PDF metadata) | QD:Insufficient Data(No information on support for larger community resilience or climate change adap) | N8: A + B required for Enhanced | O8: Identify project performance goals; Develop risk management strategies | P8: Project performance goals report; Risk management strategies | Q8: 22526 | R8: 2626 | S8: 1278.94 | T8: TRUE | U8: FALSE | V8: TRUE
A9: zero_shot | B9: 1 | C9: 00_sample_project | D9: Climate And Resilience | E9: CR2.5 | F9: Maximize Resilience | H9: Applicable | I9: No Level | J9: 0 | M9: QA:Insufficient Data(No information on development of resilience goals and strategies in PDF metadata) | QB:Insufficient Data(No information on implementation of resilience strategies in PDF metadata) | QC:Insufficient Data(No information on monitoring and review of resilience strategies in PDF metadata) | QD:Insufficient Data(No information on incorporation of resilience goals and strategies into operatio) | QE:Insufficient Data(No information on measurement or quantification of resilience performance target) | N9: A + B + C + D + E required for Conserving | O9: Develop resilience goals and strategies; Implement resilience strategies | P9: Resilience goals and strategies report; Implementation plan for resilience strategies | Q9: 22526 | R9: 2626 | S9: 1278.94 | T9: TRUE | U9: FALSE | V9: TRUE
A10: zero_shot | B10: 1 | C10: 00_sample_project | D10: Climate And Resilience | E10: CR2.6 | F10: Improve Infrastructure Integration | H10: Applicable | I10: No Level | J10: 0 | M10: QA:Insufficient Data(No information on increase of internal systems integration in PDF metadata) | QB:Insufficient Data(No information on reduction of risk of systemic or cascading failures in PDF met) | QC:Insufficient Data(No information on increase of external systems integration in PDF metadata) | QD:Insufficient Data(No information on integration of infrastructure networks in PDF metadata) | QE:Insufficient Data(No information on integration of data or monitoring systems in PDF metadata) | N10: A required for Improved | O10: Increase internal systems integration; Reduce risk of systemic or cascading failures | P10: Internal systems integration report; Risk reduction plan | Q10: 22526 | R10: 2626 | S10: 1278.94 | T10: TRUE | U10: FALSE | V10: TRUE
A11: zero_shot | B11: 1 | C11: 00_sample_project | D11: Leadership | E11: LD1.1 | F11: Provide Effective Leadership and Commitment | H11: Applicable | I11: Improved | J11: 2 | M11: QA:Insufficient Data(No community needs assessment in model) | QB:Insufficient Data(No sustainability management plan in model) | QC:Insufficient Data(No periodic revisit of project sustainability commitments in model) | QD:Insufficient Data(No organizational commitments to sustainability from key team members in model) | N11: A + B required for Enhanced | O11: Begin community engagement to address A, B, D | P11: Community needs assessment report; Sustainability management plan | Q11: 24260 | R11: 3255 | S11: 1177.26 | T11: TRUE | U11: FALSE | V11: TRUE
A12: zero_shot | B12: 1 | C12: 00_sample_project | D12: Leadership | E12: LD1.2 | F12: Foster Collaboration and Teamwork | H12: Applicable | I12: Improved | J12: 2 | M12: QA:Insufficient Data(No interdisciplinary collaborative kickoff meeting in model) | QB:Insufficient Data(No sustainability performance enhancements from collaboration in model) | QC:Insufficient Data(No regular interdisciplinary and collaborative meetings in model) | QD:Insufficient Data(No inclusion of construction, operations, or maintenance stakeholders in model) | N12: A + B required for Enhanced | O12: Establish interdisciplinary collaborative meetings | P12: Meeting minutes; Collaboration plan | Q12: 24260 | R12: 3255 | S12: 1177.26 | T12: TRUE | U12: FALSE | V12: TRUE
A13: zero_shot | B13: 1 | C13: 00_sample_project | D13: Leadership | E13: LD1.3 | F13: Provide for Stakeholder Involvement | H13: Applicable | I13: Improved | J13: 3 | M13: QA:Insufficient Data(No stakeholder mapping exercise in model) | QB:Insufficient Data(No proactive stakeholder engagement process in model) | QC:Insufficient Data(No lead member of project team involved with stakeholders in model) | QD:Insufficient Data(No stakeholder engagement feedback incorporated into project plans in model) | QE:Insufficient Data(No stakeholder satisfaction assessment in model) | QF:No(Project team has not engaged stakeholders as partners) | N13: A, B required for Enhanced | O13: Conduct stakeholder mapping exercise | P13: Stakeholder engagement plan; Stakeholder feedback report | Q13: 24260 | R13: 3255 | S13: 1177.26 | T13: TRUE | U13: FALSE | V13: TRUE
... A21: zero_shot | B21: 1 | C21: 00_sample_project | D21: Leadership | E21: LD3.3 | F21: Conduct a Life-Cycle Economic Evaluation | H21: Applicable | I21: Improved | J21: 5 | M21: QA:Insufficient Data(No life-cycle cost analysis conducted to identify financial impacts of whole pro) | QB:Insufficient Data(No use of life-cycle cost analyses to compare alternatives for major project com) | QC:Insufficient Data(No mapping of social, environmental, and financial costs and benefits of project) | QD:Insufficient Data(No conduct of cost-benefit analysis to identify financial, social, and environme) | QE:Insufficient Data(No use of cost-benefit analyses to compare alternatives for major project compon) | N21: A required for Enhanced | O21: Conduct life-cycle cost analysis | P21: Life-cycle cost report; Cost-benefit analysis report | Q21: 24260 | R21: 3255 | S21: 1177.26 | T21: TRUE | U21: FALSE | V21: TRUE
A22: zero_shot | B22: 1 | C22: 00_sample_project | D22: Natural World | Q22: 28099 | R22: 3901 | S22: 1505.17 | T22: FALSE | U22: TRUE | V22: TRUE
A23: zero_shot | B23: 1 | C23: 00_sample_project | D23: Quality Of Life | Q23: 27044 | R23: 4956 | S23: 1605.45 | T23: FALSE | U23: TRUE | V23: TRUE
